Workbook

Sheet readme
A1: Appendix B - Data Analysis Empathy Guidelines for Software Practitioners
A2: This appendix presents the full details of the data analysis conducted for the large-scale practitioner survey. It includes the demographic information of the participants (Demographics Analysis sheet) and a comprehensive quantitative analysis of practitioners’ ratings of the empathy guidelines across three dimensions: perceived importance, ease of implementation, and willingness to adopt (Guidelines Analysis - Quant sheet). These analyses collectively informed the development of the implementation prioritisation framework (Detailed Guidelines Analysis - Quant sheet). In addition, this appendix provides the final analysis of practitioners’ suggested approaches for implementing the guidelines in real-world settings as shown in Figures 3-6 (Guidelines Analysis - Qual - Practical Imp Ways sheet). We also summarise the key challenges practitioners anticipated when adopting these guidelines in practice, along with the corresponding strategies to address these challenges as shown in Figure 7 (Guide. Analysis - Qual - Limitations & Improvement sheet). Together, these components offer a transparent account of how the data were interpreted and how the final set of recommendations and improvement strategies was derived.

Sheet Demographics - Data
A2: Age group | B2: Gender | C2: Country of your residence when you were working on your most recent role where you interacted with other software practitioners? | D2: Years of experience do you have in working as a software practitioner | E2: Title/designation of your current role? | F2: Responsibilities of your current role | G2: Software development methodologies have you primarily been involved in | H2: primary domain you have been involved in your current role | I2: Nature of the organisation you are affiliated with in your current role | J2: Team members in your current team
A3: 20 - 30 | B3: Man | C3: Mexico | D3: Between 3-5 years | E3: Customer Success/Product Manager | F3: I manage customer communication, I serve as the main point of contact for client, I ensure the communication with client and our internal team, including development and operations. I coordinate sprint delivery sessions and present platform updates. | G3: Agile - Scrum | H3: IT | I3: Small (10 -100 employees) | J3: Less than or equal to 5
A4: 31-40 | B4: Man | C4: New Zealand | D4: Between 5-10 years | E4: Software engineer | F4: Development | G4: Agile - Kanban | H4: Finance | I4: Large (More than 500 employees) | J4: 5 - 10
A5: 31-40 | B5: Man | C5: Canada | D5: Between 3-5 years | E5: Fullstack Developer | F5: Developing frontend and backend components of web services | G5: Agile - Scrum | H5: Social Media | I5: Large (More than 500 employees) | J5: 5 - 10
A6: 31-40 | B6: Man | C6: New Zealand | D6: Between 10-15 years | E6: Senior Modern Workplace Consultant | F6: Designing, developing, deploying and training Microsoft SharePoint and PowerPlatform solutions. | G6: Traditional (Waterfall),Agile - Kanban,Agile - Scrum | H6: Telecommunication,Sales and Manufacturing,Finance,Human Resource Management | I6: Small (10 -100 employees) | J6: Less than or equal to 5
A7: 31-40 | B7: Man | C7: Mexico | D7: Between 5-10 years | E7: Java senior developer | F7: Designing,testing and coding full stack systems | G7: Agile - Scrum | H7: Finance | I7: Small (10 -100 employees) | J7: 5 - 10
A8: 61-70 | B8: Man | C8: New Zealand | D8: Between 10-15 years | E8: Senior support specialist | F8: End user and partner support, documenting product issues, and resolving via product development | G8: Agile - Scrum | H8: Finance | I8: Medium (100 - 500 employees) | J8: Less than or equal to 5
A9: 41-50 | B9: Man | C9: New Zealand | D9: Between 20-30 years | E9: Senior Business Intelligence Consultant/Data Engineer/Machine Learning Engineer | F9: build data models in SAP, Azure, GCP,etc. ; built reports and dashboards and other visualizations; build data pipelines for ML and deploy ML models | G9: Traditional (Waterfall),Agile - Scrum | H9: Sales and Manufacturing,Finance,Human Resource Management,Transport, Travel & Tourism,Energy, Fast Moving Consumer Goods in Supermarket retail, homeware, agriculture,etc. | I9: Medium (100 - 500 employees) | J9: Less than or equal to 5
A10: 31-40 | B10: Man | C10: New Zealand | D10: Between 10-15 years | E10: Senior Systems Analyst | F10: System Analyst role | G10: Agile - Scrum | H10: Finance | I10: Large (More than 500 employees) | J10: 10 -20
A11: 31-40 | B11: Man | C11: Hungary | D11: Between 3-5 years | E11: IT Quality Analyst | F11: Checkin quality of team, contact with second level teams, help colleagues to solve more complex issues | G11: Agile - Scrum | H11: Healthcare | I11: Large (More than 500 employees) | J11: More than 20
A12: 20 - 30 | B12: Man | C12: Italy | D12: Between 5-10 years | E12: Manager | F12: Manage the entire team | G12: Traditional (Waterfall) | H12: Telecommunication,Healthcare,Sales and Manufacturing,Finance,Energy | I12: Small (10 -100 employees) | J12: Less than or equal to 5
A13: 31-40 | B13: Man | C13: New Zealand | D13: Between 5-10 years | E13: Analyst | F13: data analyst and systems maintenance | G13: Agile - Kanban,Agile - Scrum | H13: Transport, Travel & Tourism | I13: Large (More than 500 employees) | J13: 5 - 10
... A105: 20 - 30 | B105: Man | C105: United States of America | D105: Between 3-5 years | E105: manager | F105: manage a team that specify on carrying out certain tasks | G105: Traditional (Waterfall),Agile - Kanban,Agile - Scrum,Agile - XP | H105: Human Resource Management | I105: Large (More than 500 employees) | J105: 10 -20

Sheet Demographics Analysis
A2: Age Group
A3: Below 20 | B3: =COUNTIF('Demographics - Data'!A$3:A$105,A3) -> 0
A4: 20 - 30 | B4: =COUNTIF('Demographics - Data'!A$3:A$105,A4) -> 32
A5: 31-40 | B5: =COUNTIF('Demographics - Data'!A$3:A$105,A5) -> 36
A6: 41-50 | B6: =COUNTIF('Demographics - Data'!A$3:A$105,A6) -> 24
A7: 51-60 | B7: =COUNTIF('Demographics - Data'!A$3:A$105,A7) -> 7
A8: 61-70 | B8: =COUNTIF('Demographics - Data'!A$3:A$105,A8) -> 3
A9: Above 70 | B9: =COUNTIF('Demographics - Data'!A$3:A$105,A9) -> 1
A10: Prefer not to answer | B10: =COUNTIF('Demographics - Data'!A$3:A$105,A10) -> 0
C11: =SUM(B3:B10) -> 103
A13: Gender
A14: Woman | B14: =COUNTIF('Demographics - Data'!B$3:B$105,A14) -> 35
A15: Man | B15: =COUNTIF('Demographics - Data'!B$3:B$105,A15) -> 68
C16: =SUM(B14:B15) -> 103
A18: Country
A19: Australia | B19: =COUNTIF('Demographics - Data'!C$3:C$105,A19) -> 2
A20: Austria | B20: =COUNTIF('Demographics - Data'!C$3:C$105,A20) -> 1
A21: Canada | B21: =COUNTIF('Demographics - Data'!C$3:C$105,A21) -> 10
A22: Chile | B22: =COUNTIF('Demographics - Data'!C$3:C$105,A22) -> 3
A23: France | B23: =COUNTIF('Demographics - Data'!C$3:C$105,A23) -> 3
A24: Germany | B24: =COUNTIF('Demographics - Data'!C$3:C$105,A24) -> 4
A25: Greece | B25: =COUNTIF('Demographics - Data'!C$3:C$105,A25) -> 2
A26: Hungary | B26: =COUNTIF('Demographics - Data'!C$3:C$105,A26) -> 2
A27: Ireland | B27: =COUNTIF('Demographics - Data'!C$3:C$105,A27) -> 1
A28: Italy | B28: =COUNTIF('Demographics - Data'!C$3:C$105,A28) -> 8
A29: Mexico | B29: =COUNTIF('Demographics - Data'!C$3:C$105,A29) -> 4
A30: Netherlands | B30: =COUNTIF('Demographics - Data'!C$3:C$105,A30) -> 1
... A37: United States of America | B37: =COUNTIF('Demographics - Data'!C$3:C$105,A37) -> 35
C38: =SUM(B19:B37) -> 103
A40: Years of Experience
A41: Less than 1 year | B41: =COUNTIF('Demographics - Data'!D$3:D$105,A41) -> 3
A42: Between 1-2 years | B42: =COUNTIF('Demographics - Data'!D$3:D$105,A42) -> 3
A43: Between 3-5 years | B43: =COUNTIF('Demographics - Data'!D$3:D$105,A43) -> 35
A44: Between 5-10 years | B44: =COUNTIF('Demographics - Data'!D$3:D$105,A44) -> 32
A45: Between 10-15 years | B45: =COUNTIF('Demographics - Data'!D$3:D$105,A45) -> 14
A46: Between 15-20 years | B46: =COUNTIF('Demographics - Data'!D$3:D$105,A46) -> 8
A47: Between 20-30 years | B47: =COUNTIF('Demographics - Data'!D$3:D$105,A47) -> 5
A48: Between 30-40 years | B48: =COUNTIF('Demographics - Data'!D$3:D$105,A48) -> 3
A49: Between 40-50 years | B49: =COUNTIF('Demographics - Data'!D$3:D$105,A49) -> 0
A50: More than 50 years | B50: =COUNTIF('Demographics - Data'!D$3:D$105,A50) -> 0
C51: =SUM(B41:B50) -> 103
A53: Nature of the organisation
A54: Self-Employed | B54: =COUNTIF('Demographics - Data'!I$3:I$105,A54) -> 2
A55: Startup (5-10 employees) | B55: =COUNTIF('Demographics - Data'!I$3:I$105,A55) -> 3
A56: Small (10 -100 employees) | B56: =COUNTIF('Demographics - Data'!I$3:I$105,A56) -> 22
A57: Medium (100 - 500 employees) | B57: =COUNTIF('Demographics - Data'!I$3:I$105,A57) -> 29
A58: Large (More than 500 employees) | B58: =COUNTIF('Demographics - Data'!I$3:I$105,A58) -> 47
C59: =SUM(B54:B58) -> 103
A61: Nature of the team
A62: No members | B62: =COUNTIF('Demographics - Data'!J$3:J$105,A62) -> 0
A63: Less than or equal to 5 | B63: =COUNTIF('Demographics - Data'!J$3:J$105,A63) -> 22
A64: 5 - 10 | B64: =COUNTIF('Demographics - Data'!J$3:J$105,A64) -> 43
A65: 10 -20 | B65: =COUNTIF('Demographics - Data'!J$3:J$105,A65) -> 29
A66: More than 20 | B66: =COUNTIF('Demographics - Data'!J$3:J$105,A66) -> 9
C67: =SUM(B62:B66) -> 103
A69: Software development methodologies
A70: Traditional (Waterfall) | B70: =COUNTIF('Demographics - Data'!G3:G105,"Traditional (Waterfall)*") -> 56
A71: Agile - Kanban | B71: =COUNTIF('Demographics - Data'!G$3:G$105,"*Agile - Kanban*") -> 36
A72: Agile - Scrum | B72: =COUNTIF('Demographics - Data'!G$3:G$105,"*Agile - Scrum*") -> 70
A73: Agile - XP | B73: =COUNTIF('Demographics - Data'!G$3:G$105,"*Agile - XP*") -> 21
A74: DevOps | B74: =COUNTIF('Demographics - Data'!G$3:G$105,"*DevOps*") -> 3
A77: Primary domain
A78: Telecommunication | B78: =COUNTIF('Demographics - Data'!H$3:H$105,"*Telecommunication*") -> 29
A79: Healthcare | B79: =COUNTIF('Demographics - Data'!H$3:H$105,"*Healthcare*") -> 14
A80: Sales and Manufacturing | B80: =COUNTIF('Demographics - Data'!H$3:H$105,"*Sales and Manufacturing*") -> 21
A81: Field Service Management | B81: =COUNTIF('Demographics - Data'!H$3:H$105,"*Field Service Management*") -> 10
A82: Insurance | B82: =COUNTIF('Demographics - Data'!H$3:H$105,"*Insurance*") -> 2
A83: Finance | B83: =COUNTIF('Demographics - Data'!H$3:H$105,"*Finance*") -> 28
A84: Human Resource Management | B84: =COUNTIF('Demographics - Data'!H$3:H$105,"*Human Resource Management*") -> 14
A85: Transport, Travel & Tourism | B85: =COUNTIF('Demographics - Data'!H$3:H$105,"*Transport, Travel & Tourism*") -> 10
A86: Energy | B86: =COUNTIF('Demographics - Data'!H$3:H$105,"*Energy*") -> 8
A87: IT/ Information Technology/ Internet/ Information/ Technology/ Technological implementation/ Information Tech | B87: =COUNTIF('Demographics - Data'!H$3:H$105,"*IT*")+ COUNTIF('Demographics - Data'!H$3:H$105,"*Internet*") +COUNTIF('Demographics - Data'!H$3:H$105,"*Information*") +COUNTIF('Demographics - Data'!H$3:H$105,"Technology") +COUNTIF('Demographics - Data'!H$3:H$105,"Technological implementation") -> 11
A88: Social Media | B88: =COUNTIF('Demographics - Data'!H$3:H$105,"*Social Media*") -> 2
A89: Fast Moving Consumer Goods in Supermarket retail | B89: =COUNTIF('Demographics - Data'!H$3:H$105,"*Fast Moving Consumer Goods in Supermarket retail*") -> 1
A90: Homeware | B90: =COUNTIF('Demographics - Data'!H$3:H$105,"*Homeware*") -> 1
A91: Agriculture | B91: =COUNTIF('Demographics - Data'!H$3:H$105,"*Agriculture*") -> 1
A92: Consulting | B92: =COUNTIF('Demographics - Data'!H$3:H$105,"*Consulting*") -> 1
A93: Gaming/ Games development | B93: =COUNTIF('Demographics - Data'!H$3:H$105,"*Gaming*")+ COUNTIF('Demographics - Data'!H$3:H$105,"*Games development*") -> 3
A94: Logistics | B94: =COUNTIF('Demographics - Data'!H$3:H$105,"*Logistics*") -> 1

Sheet Guidelines - Data
A1: 15 - Based on your experience as a software practitioner, how important do you think our proposed guidelines are for implementation in real-world industry settings? | S1: 16 - Based on your experience as a software practitioner, how practical and easy are our proposed guidelines to implement in real industry settings? | AK1: 17 - Would you consider using our proposed guidelines to enhance empathy in your software engineering practice? | BC1: 18 - Select the top 5 guidelines from above 17 guidelines listed above that you would apply in your work. Explain how you plan to incorporate these guidelines into your daily work and practices, and outline any specific steps or approaches you plan to take. | BD1: 19 - Do you see any limitations in the proposed guidelines for fostering empathy, or any challenges in adopting them within software engineering? What improvements would you suggest to address these limitations?
A2: G1 - Fostering strong relationships among stakeholders | B2: G2 - Bridging the technical and non-technical gap | C2: G3 - Reducing friction among different stakeholder groups | D2: G4 - Encouraging bi-directional communication | E2: G5 - Ensuring transparency about business goals | F2: G6 - Use an empathetic approach to improve RE processes | G2: G7 - Collaborative problem solving | H2: G8 - Empathy during agile ceremonies | I2: G9 - Empathetic feedback process | J2: G10 - Creating a safe space | K2: G11 - Backup plans to manage unexpected outcomes | L2: G12 - Flexibility in handling human issues | M2: G13 - Emphasising the real-world impact of developers’ work | N2: G14 - Building an empathetic team and company culture | O2: G15 - Empathy education and training | P2: G16 - DEI policies | Q2: G17 - Managing empathy fatigue | R2: 15.1 - Please explain the reason for your rating above in question 15. | S2: G1 - Fostering strong relationships among stakeholders | T2: G2 - Bridging the technical and non-technical gap | U2: G3 - Reducing friction among different stakeholder groups | V2: G4 - Encouraging bi-directional communication | W2: G5 - Ensuring transparency about business goals | X2: G6 - Use an empathetic approach to improve RE processes | Y2: G7 - Collaborative problem solving | Z2: G8 - Empathy during agile ceremonies | AA2: G9 - Empathetic feedback process | AB2: G10 - Creating a safe space | AC2: G11 - Backup plans to manage unexpected outcomes | AD2: G12 - Flexibility in handling human issues | AE2: G13 - Emphasising the real-world impact of developers’ work | AF2: G14 - Building an empathetic team and company culture | AG2: G15 - Empathy education and training | AH2: G16 - DEI policies | AI2: G17 - Managing empathy fatigue | AJ2: 16.1 - Please explain the reason for your rating above in question 16. | AK2: G1 - Fostering strong relationships among stakeholders | AL2: G2 - Bridging the technical and non-technical gap | AM2: G3 - Reducing friction among different stakeholder groups | AN2: G4 - Encouraging bi-directional communication | AO2: G5 - Ensuring transparency about business goals | AP2: G6 - Use an empathetic approach to improve RE processes | AQ2: G7 - Collaborative problem solving | AR2: G8 - Empathy during agile ceremonies | AS2: G9 - Empathetic feedback process | AT2: G10 - Creating a safe space | AU2: G11 - Backup plans to manage unexpected outcomes | AV2: G12 - Flexibility in handling human issues | AW2: G13 - Emphasising the real-world impact of developers’ work | AX2: G14 - Building an empathetic team and company culture | AY2: G15 - Empathy education and training | AZ2: G16 - DEI policies | BA2: G17 - Managing empathy fatigue | BB2: 17.1 - Please explain the reason for your selection above in question 17. You must provide a detailed and meaningful answer to this question to qualify for payment.
A3: Critical to Have | B3: Very Important to Have | C3: Very Important to Have | D3: Critical to Have | E3: Very Important to Have | F3: Very Important to Have | G3: Very Important to Have | H3: Very Important to Have | I3: Critical to Have | J3: Critical to Have | K3: Critical to Have | L3: Very Important to Have | M3: Very Important to Have | N3: Very Important to Have | O3: Very Important to Have | P3: Critical to Have | Q3: Critical to Have | R3: I think is critical for companies to create a safe workspace for all the team involved, it is proved that doing this will make the employees feel happier, motivated to work, and less stress. I work in a great company that is always looking for their workers well being, inside and even outside of the work office. | S3: Difficult | T3: Very Difficult | U3: Easy | V3: Easy | W3: Easy | X3: Easy | Y3: Very Easy | Z3: Easy | AA3: Very Easy | AB3: Very Easy | AC3: Easy | AD3: Very Easy | AE3: Easy | AF3: Very Easy | AG3: Very Easy | AH3: Easy | AI3: Easy | AJ3: My company always makes us work as an empathic group, this doesn't only apply to work, I learned this a student and in my house, I bring this to the work, and most of my coworkers are really empathic and try to build a great work culture. | AK3: I am likely to regularly use it | AL3: I am currently using it | AM3: I will definitely use it | AN3: I am currently using it | AO3: I am currently using it | AP3: I am currently using it | AQ3: I am currently using it | AR3: I am currently using it | AS3: I am currently using it | AT3: I am currently using it | AU3: I am currently using it | AV3: I am currently using it | AW3: I will definitely use it | AX3: I am currently using it | AY3: I am currently using it | AZ3: I am likely to regularly use it | BA3: I will definitely use it | BB3: Most of these presented guidelines are key for a safe workspace, I currently use most of them, but there are some regarding empathy between different teams that I will very likely use at my work. | BC3: G4, G9, G10, G11 and G14, these are all guidelines that I currently apply at my job and I will definitely keep using, as bi directional communication and problem solving is key at my job, bi directional communication applies both with my coworkers from development team, and with the client, so we can understand each other. Part of applying this, is also using transparency, empathy and clear communication. | BD3: I don't see any clear limitations in the proposed guidelines. Maybe the challenge of working from home is to feel really part of the group in a company, so I would suggest having weekly meetings just to chat and know each others better in the company, this would help creating empathy between coworkers.
A4: Very Important to Have | B4: Very Important to Have | C4: Somewhat Important to Have | D4: Critical to Have | E4: Very Important to Have | F4: Somewhat Important to Have | G4: Critical to Have | H4: Somewhat Important to Have | I4: Somewhat Important to Have | J4: Somewhat Important to Have | K4: Very Important to Have | L4: Nice to Have | M4: Nice to Have | N4: Somewhat Important to Have | O4: Somewhat Important to Have | P4: Nice to Have | Q4: Nice to Have | R4: I try to think about what I feel would contribute best to my squad and company culture when ranking each criteria and feel that communcation is extremely important in making sure you get the details right to make the build and release stage run smoother for requirements which is why I rated those most critical | S4: Difficult | T4: Very Difficult | U4: Very Difficult | V4: Easy | W4: Easy | X4: Easy | Y4: Difficult | Z4: Easy | AA4: Easy | AB4: Easy | AC4: Difficult | AD4: Difficult | AE4: Easy | AF4: Difficult | AG4: Easy | AH4: Easy | AI4: Easy | AJ4: I feel that these are relevant to my experiences throughout my career | AK4: I am currently using it | AL4: I am likely to regularly use it | AM4: I am unlikely to use it | AN4: I am currently using it | AO4: I am likely to regularly use it | AP4: I am likely to regularly use it | AQ4: I am currently using it | AR4: I am currently using it | AS4: I am currently using it | AT4: I am currently using it | AU4: I am currently using it | AV4: I am likely to regularly use it | AW4: I am currently using it | AX4: I am currently using it | AY4: I might occasionally use it | AZ4: I am likely to regularly use it | BA4: I might occasionally use it | BB4: I feel these answers are relevant to my experiences across my career | BC4: I think that the following 5 are the most vital to implement - g1, g2, g4, g7, g11 | BD4: Nothing stands out to me
A5: Very Important to Have | B5: Very Important to Have | C5: Somewhat Important to Have | D5: Critical to Have | E5: Very Important to Have | F5: Somewhat Important to Have | G5: Critical to Have | H5: Very Important to Have | I5: Very Important to Have | J5: Critical to Have | K5: Nice to Have | L5: Critical to Have | M5: Very Important to Have | N5: Very Important to Have | O5: Critical to Have | P5: Critical to Have | Q5: Critical to Have | R5: Empathy during agile ceremonies and feedback processes is highly valued because it helps build trust, improve communication, and create a safe environment where team members feel supported. These practices encourage open discussions and constructive feedback, which are key to solving problems and working well together. In contrast, things like backup plans or creating safe spaces are still important but are seen as less urgent. They add value by supporting the team and handling unexpected challenges, but they don’t have as direct an impact on achieving project goals or aligning stakeholders. | S5: Very Difficult | T5: Difficult | U5: Very Difficult | V5: Easy | W5: Easy | X5: Easy | Y5: Very Difficult | Z5: Very Easy | AA5: Very Easy | AB5: Easy | AC5: Easy | AD5: Very Difficult | AE5: Difficult | AF5: Neither difficult nor easy | AG5: Difficult | AH5: Easy | AI5: Difficult | AJ5: Some factors are easy to implement as they does not reqiuire invovling too many different groups of people. It is always hard to establish relationships with people outside a team or company. | AK5: I am likely to regularly use it | AL5: I am currently using it | AM5: I am unlikely to use it | AN5: I am currently using it | AO5: I am currently using it | AP5: I am likely to regularly use it | AQ5: I am currently using it | AR5: I am currently using it | AS5: I will definitely use it | AT5: I will definitely use it | AU5: I might occasionally use it | AV5: I am likely to regularly use it | AW5: I am likely to regularly use it | AX5: I will definitely use it | AY5: I am likely to regularly use it | AZ5: I am unlikely to use it | BA5: I might occasionally use it | BB5: Many factors depends on corporate culture, something is already implemented, and something is unlikely to be implemented. In my company we are open to changes, but in reality some things are hard to implement. I chose points that I likely and definitely use based on my personal feelings, not company's policies, and those points I believe we should implement. | BC5: I’ll focus on building an empathetic team (G14) by fostering open communication and collaboration, creating a safe space (G10) for sharing ideas without judgment, and maintaining flexibility (G12) to adapt to team needs. I’ll also emphasize the real-world impact of work (G13) by sharing success stories and user feedback, and promote empathy education (G15) through workshops and training to enhance understanding and teamwork. | BD5: The proposed guidelines are valuable but face challenges like cultural differences in creating safe spaces (G10), time constraints for empathy training (G15), and varying interest in real-world impacts (G13). To improve, empathy initiatives should align with team workflows, training should connect to practical scenarios, and metrics can highlight the impact of work to engage analytical team members. Balancing empathy with technical priorities might be a key for successful adoption.
A6: Not Necessary to Have | B6: Very Important to Have | C6: Critical to Have | D6: Critical to Have | E6: Somewhat Important to Have | F6: Very Important to Have | G6: Very Important to Have | H6: Somewhat Important to Have | I6: Nice to Have | J6: Somewhat Important to Have | K6: Not Necessary to Have | L6: Not Necessary to Have | M6: Critical to Have | N6: Somewhat Important to Have | O6: Very Important to Have | P6: Nice to Have | Q6: Critical to Have | R6: For G17? Managing empathy fatigue is critical to have because it allows your team to decompress and focus down on the critical pathways for the project. Not every issue needs to have empathy applied and even the smallest issue can be 'over empathised' which leads to fatigue - this can lower morale and attitudes for other critical components. | S6: Easy | T6: Very Difficult | U6: Very Easy | V6: Easy | W6: Very Difficult | X6: Difficult | Y6: Neither difficult nor easy | Z6: Difficult | AA6: Easy | AB6: Very Easy | AC6: Very Difficult | AD6: Difficult | AE6: Easy | AF6: Difficult | AG6: Neither difficult nor easy | AH6: Very Easy | AI6: Easy | AJ6: Have to assume this is just for the last question in each stack (ie, G17). As long as empathy isn't treated as the most critical aspect of the practice, then managing fatigue from it becomes easy. If the team had to prioritise empathy - then the managing part of that becomes exponentially more difficult. | AK6: I will definitely use it | AL6: I am likely to regularly use it | AM6: I am currently using it | AN6: I might occasionally use it | AO6: I will definitely use it | AP6: I am likely to regularly use it | AQ6: I will definitely use it | AR6: I am unlikely to use it | AS6: I am currently using it | AT6: I will definitely use it | AU6: I am currently using it | AV6: I am currently using it | AW6: I am unlikely to use it | AX6: I am likely to regularly use it | AY6: I will definitely use it | AZ6: I am currently using it | BA6: I will definitely use it | BB6: It's described in simple terms. Policies that are overly detailed become cumbersome to implement and remain vigilant of when the detail is too minute. When a policy is simple, it can be interpreted in a way that best suits the team employing it. | BC6: G16: DEI policies: when you employ DEI policies correctly, it can be very simple to follow. We employ techniques to this which include not hiring ANYONE based on any gender, race, political affiliations or ideologies - we hire based on skill and personality. Any other method of hiring is discriminatory. G12: Once a year we offer training for empathy as we encourage the practical mindset of the team members and the respect that they've been taught and have learned how to employ empathy as regular adults. G10: Creating a safe space is as simple as checking in with team mates often - we do this by offering help, or asking if help is needed in a friendly way that doesn't make the person feel as though they may be incompetent. G7: We regularly have practical problem solving sessions with just about every client problem we face - meaning we are always working as a team to develop solutions with hands-on approaches. G8: We often have set sessions in agile retrospectives that allow the team to (if they feel comfortable) express grievances within the project and look for ways to move forward with them. | BD6: Sometimes empathy is diffcult to allow for, when projects don't call for human interaction often. When we have hard software development challenges, we do offer empathy to anyone on the the team who're finding the challenges extra difficult.
A7: Very Important to Have | B7: Not Necessary to Have | C7: Critical to Have | D7: Critical to Have | E7: Critical to Have | F7: Very Important to Have | G7: Somewhat Important to Have | H7: Somewhat Important to Have | I7: Very Important to Have | J7: Critical to Have | K7: Critical to Have | L7: Critical to Have | M7: Somewhat Important to Have | N7: Critical to Have | O7: Nice to Have | P7: Very Important to Have | Q7: Nice to Have | R7: I think some of those are really important for a succesful software development strategy because it helps to creat3e bonds between all involved teams thus improving a lot of aspects of the software like : quality, time developing etc. | S7: Easy | T7: Difficult | U7: Difficult | V7: Easy | W7: Very Easy | X7: Easy | Y7: Difficult | Z7: Difficult | AA7: Easy | AB7: Very Easy | AC7: Difficult | AD7: Easy | AE7: Difficult | AF7: Difficult | AG7: Easy | AH7: Easy | AI7: Very Easy | AJ7: Most of the points are really easy to implement in our work environment without major hassle, some are a bit more hard or challenging to adapt but with some persistance and teamwork it would come feasible and easy to embrace in the workforce of our company | AK7: I am likely to regularly use it | AL7: I might occasionally use it | AM7: I will definitely use it | AN7: I might occasionally use it | AO7: I am currently using it | AP7: I might occasionally use it | AQ7: I am currently using it | AR7: I am likely to regularly use it | AS7: I am currently using it | AT7: I am currently using it | AU7: I am currently using it | AV7: I am currently using it | AW7: I am likely to regularly use it | AX7: I am currently using it | AY7: I am currently using it | AZ7: I am currently using it | BA7: I will definitely use it | BB7: As i mentioned in the answer some of those im actually using them in the processes im assigned some not but i will try to put them to use because it hink they could be useful in some cases | BC7: 1 would be transparency in bussines model , i was victim of a project where i was involved where i think i was a bit naive but i didnt know which was the econonic goal so i think they kind me of scammed me for that project,2 would be collaborative problem solving i think its very important to have this kind of approach because that way you can ensure an almost bulletproff product,3 empathetic fedback process sometimes it bit rough when people make mistakes but its no use to be angry or agressive to be more human when giving feeedback,4 empathetic in human issues sometimes people has personal issues which need attention but that should not be a problem for the project at all , talk to stakeholders and hold them down a bit to get back on track after those issues are solved, and finally 5 dei policies its very important to be tolerant open and respectful to any other working partner in our team to have a healthy and happy workforce | BD7: The limitations i think more would the different branches of different teams i mean their education because for what a team mean something in ahnothe could mean something completely diferent.The approach i would use would be to teach a bit of each specific jargon to each team to ensure theer are the less of those problems
A8: Critical to Have | B8: Very Important to Have | C8: Very Important to Have | D8: Very Important to Have | E8: Very Important to Have | F8: Critical to Have | G8: Very Important to Have | H8: Somewhat Important to Have | I8: Very Important to Have | J8: Somewhat Important to Have | K8: Very Important to Have | L8: Somewhat Important to Have | M8: Very Important to Have | N8: Very Important to Have | O8: Somewhat Important to Have | P8: Somewhat Important to Have | Q8: Somewhat Important to Have | R8: Which rating? All of the above are helpful, some more so than others. Why is NOT necessary in middle of scale?? | S8: Difficult | T8: Difficult | U8: Very Difficult | V8: Very Difficult | W8: Very Difficult | X8: Difficult | Y8: Very Difficult | Z8: Difficult | AA8: Difficult | AB8: Easy | AC8: Difficult | AD8: Very Difficult | AE8: Very Difficult | AF8: Neither difficult nor easy | AG8: Easy | AH8: Difficult | AI8: Difficult | AJ8: Again, which rating? To me, a lengthy list of 17 items is likely to be a barrier and just get lip service. Some of the items such as DEI and Empathy are foreign to some company cultures even in 2024. | AK8: I am currently using it | AL8: I am currently using it | AM8: I am currently using it | AN8: I am currently using it | AO8: I am likely to regularly use it | AP8: I am likely to regularly use it | AQ8: I am currently using it | AR8: I will definitely use it | AS8: I will definitely use it | AT8: I am likely to regularly use it | AU8: I might occasionally use it | AV8: I am likely to regularly use it | AW8: I am currently using it | AX8: I might occasionally use it | AY8: I am unlikely to use it | AZ8: I am unlikely to use it | BA8: I am unlikely to use it | BB8: Again which selection? Some of the above might not be a good fit in some cultures even if I see as useful. And why, guys, does the matric of answers not fit in available screen width and need a scroll bar? | BC8: G1 - Fostering strong relationships G2 - Bridging the technical and non-technical gap G7 - Collaborative problem solving: G11 - Backup plans to manage unexpected outcomes: G13 - Emphasising the real-world impact of developers’ work I'd see the above as the most important, but would still be overruled if your product manager is Elon Musk or Steve Jobs! Development is an adventure with uncertain outcomes. | BD8: Accepting / prompting empathy depends on the overall manager's style and might not always be possible.
A9: Critical to Have | B9: Critical to Have | C9: Very Important to Have | D9: Critical to Have | E9: Critical to Have | F9: Critical to Have | G9: Critical to Have | H9: Critical to Have | I9: Critical to Have | J9: Critical to Have | K9: Very Important to Have | L9: Very Important to Have | M9: Very Important to Have | N9: Very Important to Have | O9: Very Important to Have | P9: Very Important to Have | Q9: Very Important to Have | R9: The guidelines I flagged as critical are the ones that are most important for a successful software engineering team.Non-compliance to these guidelines will prevent our team to deliver a software that is both effective and efficient. For example, during requirements gathering and analysis, all technical and non-technical stakeholders must be on the same page in order to design and develop an excellent software and collaborate effectively to solve issues. To achieve this, we must foster open and clear communication and there should be harmony in the team. Those that I have flagged as very important to have are indeed very important, but they are not really showstoppers. There can be some workaround or other alternatives for them. The attention check question on Gt - Select correct answer for this. What does this mean? I selected critical to have as I consider to be the most correct answer. | S9: Easy | T9: Easy | U9: Very Difficult | V9: Easy | W9: Very Difficult | X9: Easy | Y9: Easy | Z9: Very Difficult | AA9: Very Difficult | AB9: Easy | AC9: Easy | AD9: Easy | AE9: Easy | AF9: Easy | AG9: Very Difficult | AH9: Difficult | AI9: Very Difficult | AJ9: The easy ones to implement are anyways the must haves and what are expected from a software team. Any skilled/senior member of the team can easily implement these and resolve any issues. It is already a given that in our daily standups or requirements gathering sessions - we must bridge the gap between technical and non-technical or business functional solutions , we must always have backup plans or rollback plans in case of emergency or unexpected outcomes, and it must be innate in us that we must have empathy - or putting ourselves in others' shoes so that we can explain to someone non-technical , very complex technical designs and solutions. However, formalizing an empathy training would be quite challenging because the upper management might not put enough emphasis on this , education and training programs tend to be more technical and more on skills development because it would have a more direct impact to the company's bottom-line. However, it is not impossible to get the management buy-in for this as long as you can show some statistics on the effectiveness and benefits of such empathy trainings. | AK9: I am currently using it | AL9: I am currently using it | AM9: I am currently using it | AN9: I am currently using it | AO9: I am currently using it | AP9: I am currently using it | AQ9: I am currently using it | AR9: I am currently using it | AS9: I am currently using it | AT9: I am currently using it | AU9: I am currently using it | AV9: I am currently using it | AW9: I am currently using it | AX9: I am currently using it | AY9: I am likely to regularly use it | AZ9: I am currently using it | BA9: I am likely to regularly use it | BB9: most of the guidelines above are already embedded in both our written and unwritten rules and SOP within our dev team. I will be very keen though to convince our upper management to formalize empathy training to improve further our communications across all stakeholders and if we can find a way to project our company as a company who is more inclusive with the best industry practices through this empathy trainings, I think it will benefit the company's bottomline as such companies are given tax reduction benefits by the New Zealand government. | BC9: G9, G15, G17, G14, G16 - we can implement this through formal empathy trainings to start with or to initiate this, and then later on , there can be feedback loop sessions to check whether the training is effective and being put into practice and the benefits are experienced. | BD9: time. we are so busy delivering multiple projects with limited resources including people, the only way to address this is for the management to sacrifice a few days in a month to have these trainings and feedback loop sessions in order to implement these.
A10: Very Important to Have | B10: Very Important to Have | C10: Very Important to Have | D10: Very Important to Have | E10: Not Necessary to Have | F10: Very Important to Have | G10: Not Necessary to Have | H10: Very Important to Have | I10: Very Important to Have | J10: Not Necessary to Have | K10: Very Important to Have | L10: Very Important to Have | M10: Very Important to Have | N10: Not Necessary to Have | O10: Not Necessary to Have | P10: Nice to Have | Q10: Very Important to Have | R10: Managerial and Technical aspects do require primary focus in order to succeed. DEI and others are really lessor importance. Fostering an effective and positive environment aid in productivity and so shoul dbe given credence. | S10: Difficult | T10: Very Difficult | U10: Difficult | V10: Easy | W10: Easy | X10: Difficult | Y10: Very Difficult | Z10: Easy | AA10: N/A | AB10: N/A | AC10: Easy | AD10: Easy | AE10: Easy | AF10: N/A | AG10: N/A | AH10: N/A | AI10: N/A | AJ10: Managerial and Technical aspects will be more difficult to implement in practice. DEI and others while likely easy should be weighted against benefit... | AK10: I am currently using it | AL10: I am currently using it | AM10: I am currently using it | AN10: I will definitely use it | AO10: I will definitely use it | AP10: I might occasionally use it | AQ10: I will definitely use it | AR10: I am unlikely to use it | AS10: I am unlikely to use it | AT10: I will never use it | AU10: I will definitely use it | AV10: I will definitely use it | AW10: I will definitely use it | AX10: I am unlikely to use it | AY10: I am unlikely to use it | AZ10: I will never use it | BA10: I am unlikely to use it | BB10: DEI and Empathy have not played a significant role and are unlikely to do so in an environment that values productivity and effeciency | BC10: G1, G2, G3, G5, G7 - these will have a meaningul impact on the material outcomes of the team. | BD10: Yes, resistance in uptake by the team in general. It is a hard sell and will need to be justified as anythign other than a distraction from pimary objectives of the teams.
A11: Very Important to Have | B11: Critical to Have | C11: Very Important to Have | D11: Critical to Have | E11: Critical to Have | F11: Not Necessary to Have | G11: Critical to Have | H11: Very Important to Have | I11: Critical to Have | J11: Critical to Have | K11: Very Important to Have | L11: Very Important to Have | M11: Very Important to Have | N11: Critical to Have | O11: Critical to Have | P11: Critical to Have | Q11: Critical to Have | R11: I really consider as much important as the technical knowledge the communication between the different teams involved on the processes as well as the trainings are fundamental for a successful outcome. | S11: Very Easy | T11: Difficult | U11: Easy | V11: Difficult | W11: Very Easy | X11: Easy | Y11: Difficult | Z11: Difficult | AA11: Easy | AB11: Easy | AC11: Very Difficult | AD11: Difficult | AE11: N/A | AF11: Easy | AG11: Easy | AH11: Easy | AI11: Difficult | AJ11: I focus mainly on the human interaction in whcih if you're nice to most of your colleagues and stakeholders can have a positive result on the product that you're offering. | AK11: I am likely to regularly use it | AL11: I am currently using it | AM11: I am currently using it | AN11: I am currently using it | AO11: I am currently using it | AP11: I am currently using it | AQ11: I am currently using it | AR11: I will definitely use it | AS11: I am currently using it | AT11: I am currently using it | AU11: I am currently using it | AV11: I am currently using it | AW11: I will definitely use it | AX11: I am currently using it | AY11: I am currently using it | AZ11: I am currently using it | BA11: I will definitely use it | BB11: Absolutelly because for mee mpathy is a crucial component in software engineering, as it helps developers understand and address the needs of users, stakeholders, and even their team's colleagues | BC11: G3 When these groups are not aligned, friction can arise, leading to miscommunication, delays, and inefficiencies. Reducing friction among these groups requires clear communication, empathy, shared goals, and an understanding of each group's priorities. G7 Collaborative problem solving is crucial in software development, as it helps teams leverage diverse perspectives and expertise to find innovative solutions to complex challenges.G10 In a safe environment, developers feel empowered to share ideas, express concerns, experiment, and learn without fear of judgment or negative consequences. G15 Empathy in education and training, especially within the context of software engineering or technical fields, can significantly improve learning outcomes, enhance collaboration, and foster a more inclusive and supportive environment. G12Flexibility in handling human issues is essential for creating a responsive and empathetic environment, particularly in workplace settings, or any collaborative project. Adapting to these situations with understanding and openness helps foster trust, inclusion, and well-being | BD11: I do not see limitations at all, I'd say is more a challenge due to the different personalities and egos that you can find between the different parties is more like resistance to change and cultural shift
A12: Somewhat Important to Have | B12: Somewhat Important to Have | C12: Not Necessary to Have | D12: Somewhat Important to Have | E12: Somewhat Important to Have | F12: Nice to Have | G12: Nice to Have | H12: Somewhat Important to Have | I12: Not Necessary to Have | J12: Nice to Have | K12: Nice to Have | L12: Nice to Have | M12: Very Important to Have | N12: Not Necessary to Have | O12: Not Necessary to Have | P12: Somewhat Important to Have | Q12: Not Necessary to Have | R12: Your proposed guidelines are highly important for real-world industry settings, as they provide a structured framework for addressing common challenges in software development. By offering clear standards, they help teams align on best practices, improve collaboration, and mitigate risks associated with inconsistencies. Moreover, such guidelines ensure scalability and maintainability, which are critical for long-term success in dynamic industry environments. | S12: Difficult | T12: Very Difficult | U12: Difficult | V12: Easy | W12: Easy | X12: Difficult | Y12: Very Difficult | Z12: Difficult | AA12: Difficult | AB12: Easy | AC12: Neither difficult nor easy | AD12: Difficult | AE12: Difficult | AF12: Difficult | AG12: Very Difficult | AH12: Easy | AI12: Difficult | AJ12: From a practitioner’s perspective, the practicality and ease of implementing your proposed guidelines depend on their clarity, adaptability, and alignment with existing industry workflows. If the guidelines are concise and provide actionable steps, they are more likely to be embraced by teams. Additionally, flexibility to accommodate diverse tools and processes is essential for seamless integration. Ensuring stakeholder buy-in through pilot testing and iterative feedback can further enhance their real-world applicability. | AK12: I am likely to regularly use it | AL12: I am likely to regularly use it | AM12: I will definitely use it | AN12: I will definitely use it | AO12: I am currently using it | AP12: I am likely to regularly use it | AQ12: I am currently using it | AR12: I might occasionally use it | AS12: I will definitely use it | AT12: I am currently using it | AU12: I will definitely use it | AV12: I am likely to regularly use it | AW12: I will definitely use it | AX12: I am likely to regularly use it | AY12: I am likely to regularly use it | AZ12: I am likely to regularly use it | BA12: I might occasionally use it | BB12: Absolutely, incorporating guidelines to enhance empathy in software engineering can be highly beneficial. Empathy fosters better collaboration, improves user-centered design, and strengthens communication within teams. By considering diverse perspectives, both within the team and from end users, these guidelines can lead to more inclusive and effective solutions. If the guidelines provide actionable strategies to embed empathy into workflows, I would certainly consider using them to enrich my practice. | BC12: Ensuring Transparency About Business Goals I plan to incorporate this by clearly communicating objectives in all meetings and documentation. This includes aligning team tasks with broader goals to ensure everyone understands their role in the bigger picture. Regular updates and feedback sessions will reinforce clarity and shared purpose. Creating a Safe Space I will prioritize open communication by encouraging team members to share ideas and concerns without fear of judgment. Establishing ground rules for respectful interaction and providing channels for anonymous feedback will help build trust. Regular check-ins will ensure everyone feels heard and valued. Diversity, Equity, and Inclusion (DEI) Policies I intend to integrate DEI by promoting diverse hiring practices and ensuring equitable opportunities for growth within the team. Workshops and training on unconscious bias will foster a more inclusive culture. Additionally, I will actively seek input from underrepresented voices to ensure diverse perspectives are reflected in decisions. Reducing Friction Among Different Stakeholder Groups I will focus on understanding stakeholder priorities and addressing conflicts early through mediation. Regular alignment meetings and transparent communication of constraints and expectations will minimize misunderstandings. Using collaborative tools can also help streamline information sharing. Fostering Strong Relationships Among Stakeholders I will build relationships by scheduling regular touchpoints and informal discussions to establish rapport. Actively listening to stakeholder needs and demonstrating follow-through on commitments will strengthen trust. Celebrating shared successes will also reinforce positive collaboration. | BD12: One potential limitation of the proposed guidelines is that fostering empathy often requires cultural and behavioral shifts, which can be challenging in high-pressure or results-driven environments. Resistance to change, lack of time for training, or difficulty in quantifying the impact of empathy practices might hinder adoption. To address these challenges, I would suggest integrating empathy-focused practices into existing workflows rather than treating them as separate initiatives. Providing measurable outcomes, such as improved user satisfaction or team productivity, can make the benefits clearer. Additionally, offering practical tools, such as personas or empathy maps, along with hands-on workshops, can make adoption easier and more actionable for teams.
A13: Very Important to Have | B13: Critical to Have | C13: Very Important to Have | D13: Somewhat Important to Have | E13: Somewhat Important to Have | F13: Not Necessary to Have | G13: Very Important to Have | H13: Not Necessary to Have | I13: Not Necessary to Have | J13: Very Important to Have | K13: Critical to Have | L13: Not Necessary to Have | M13: Not Necessary to Have | N13: Very Important to Have | O13: Very Important to Have | P13: Not Necessary to Have | Q13: Very Important to Have | R13: As long as a professional environment is maintained with clear communication and transparency is maintained the need for empathy is not required. however the need for a safe space to voice concerns when it is not maintained is needed. | S13: Neither difficult nor easy | T13: Neither difficult nor easy | U13: Difficult | V13: Very Difficult | W13: Neither difficult nor easy | X13: Difficult | Y13: Difficult | Z13: Difficult | AA13: Very Difficult | AB13: Very Difficult | AC13: Very Difficult | AD13: Difficult | AE13: Neither difficult nor easy | AF13: Very Difficult | AG13: Difficult | AH13: N/A | AI13: Very Difficult | AJ13: depends on the people you are working with. their is no universal rules. the aim of maintaining professionalism is key. | AK13: I am likely to regularly use it | AL13: I might occasionally use it | AM13: I am likely to regularly use it | AN13: I am likely to regularly use it | AO13: I am currently using it | AP13: I might occasionally use it | AQ13: I will definitely use it | AR13: I might occasionally use it | AS13: I might occasionally use it | AT13: I am currently using it | AU13: I am currently using it | AV13: I am likely to regularly use it | AW13: I am likely to regularly use it | AX13: I am likely to regularly use it | AY13: I will definitely use it | AZ13: I might occasionally use it | BA13: I will definitely use it | BB13: most of this is organisationalal management level direct and drive. alot would be nice to implement but unlikely in my team | BC13: the key would be to get buy in from senior management for a top down approach. G2 ,G5 and G10 once these are implemented we could introduce G14 and G15 to emphasis and maintain the environment | BD13: Buy in. the environment I work in is focused on results and professional as to not have to deal with empathy.
A14: Nice to Have | B14: Very Important to Have | C14: Nice to Have | D14: Very Important to Have | E14: Critical to Have | F14: Nice to Have | G14: Nice to Have | H14: Nice to Have | I14: Nice to Have | J14: Somewhat Important to Have | K14: Somewhat Important to Have | L14: Nice to Have | M14: Nice to Have | N14: Nice to Have | O14: Nice to Have | P14: Not Necessary to Have | Q14: Nice to Have | R14: I believe that individuals should independently handle personal challenges without significantly impacting work, emphasizing self-management over external support. | S14: Difficult | T14: Neither difficult nor easy | U14: Very Difficult | V14: Very Difficult | W14: Very Difficult | X14: Easy | Y14: Easy | Z14: Easy | AA14: Easy | AB14: Very Difficult | AC14: Very Easy | AD14: Easy | AE14: Neither difficult nor easy | AF14: Very Difficult | AG14: Very Easy | AH14: N/A | AI14: Easy | AJ14: In some organisations, there might be a strong division between teams; translating abstract technical work into concrete, relatable outcomes may involve storytelling skills, data collection, and contextualization, all of which can be resource-intensive and complex; developers may already be stretched thin with existing tasks and deadlines, leaving little room to focus on understanding or connecting with end-user impact; if the tangible benefits of emphasizing real-world impact are not immediately obvious or measurable, it may be harder to justify the effort required to implement this guideline effectively. | AK14: I am unlikely to use it | AL14: I am currently using it | AM14: I am likely to regularly use it | AN14: I am likely to regularly use it | AO14: I am currently using it | AP14: I might occasionally use it | AQ14: I might occasionally use it | AR14: I am unlikely to use it | AS14: I am unlikely to use it | AT14: I am unlikely to use it | AU14: I am currently using it | AV14: I might occasionally use it | AW14: I am currently using it | AX14: I am likely to regularly use it | AY14: I am unlikely to use it | AZ14: I will never use it | BA14: I might occasionally use it | BB14: I recognize the importance of fostering an empathetic culture but I also see its practical application as situational rather than an absolute priority in every interaction. Also this is a shared responsibility, and while I contribute, it also depends heavily on leadership and organizational policies, making it less of an individual commitment. | BC14: G2: Communicating technical aspects effectively to non-technical stakeholders is crucial for aligning expectations and achieving project goals. Use visuals, analogies, and simplified language when explaining technical concepts. G5: Transparency helps align individual efforts with organizational objectives, fostering a shared sense of purpose. Explain how team tasks contribute to larger organizational goals during project meetings and keep team members informed about shifts in priorities or business strategies. G11: Unexpected events can disrupt workflows, and having backup plans ensures continuity and reduces stress for team members. Ensure critical tasks are documented so backups can step in if needed. G13: Helping developers connect with the end-users’ experiences increases empathy and improves the quality of deliverables. Use examples of how technical solutions have positively impacted users. G17: Balancing empathy with self-care is essential to prevent burnout and maintain productivity over time. Normalize taking breaks or stepping back during emotionally draining periods and encourage team members to prioritize their well-being and communicate their limits when overwhelmed. | BD14: Empathy may be interpreted or valued differently across cultural or regional contexts, potentially leading to misunderstandings or misalignment in its implementation. Many guidelines, such as team-building activities, empathy training, or fostering real-world impact awareness, require time, financial investment, and managerial support. In fast-paced environments focused on deadlines and deliverables, these initiatives might take a backseat. While valuable, explaining technical concepts to non-technical stakeholders requires strong communication skills, which not all practitioners may possess or have the opportunity to develop.
... A105: Very Important to Have | B105: Very Important to Have | C105: Very Important to Have | D105: Not Necessary to Have | E105: Very Important to Have | F105: Very Important to Have | G105: Critical to Have | H105: Very Important to Have | I105: Very Important to Have | J105: Critical to Have | K105: Very Important to Have | L105: Very Important to Have | M105: Not Necessary to Have | N105: Very Important to Have | O105: Very Important to Have | P105: Very Important to Have | Q105: Very Important to Have | R105: the reason for my rating is i believe empathy contributes to creating a more supportive work environment, which improves overall team dynamics and productivity. | S105: Easy | T105: Easy | U105: Neither difficult nor easy | V105: Easy | W105: Easy | X105: Easy | Y105: Neither difficult nor easy | Z105: Neither difficult nor easy | AA105: Easy | AB105: Difficult | AC105: Easy | AD105: Easy | AE105: Difficult | AF105: Neither difficult nor easy | AG105: Neither difficult nor easy | AH105: Easy | AI105: Neither difficult nor easy | AJ105: many of the proposed guidelines are practical but their implementation actually vary. | AK105: I am currently using it | AL105: I am currently using it | AM105: I will definitely use it | AN105: I am currently using it | AO105: I am currently using it | AP105: I will definitely use it | AQ105: I will definitely use it | AR105: I am currently using it | AS105: I am likely to regularly use it | AT105: I will definitely use it | AU105: I will definitely use it | AV105: I will definitely use it | AW105: I will definitely use it | AX105: I am currently using it | AY105: I am currently using it | AZ105: I am likely to regularly use it | BA105: I will definitely use it | BB105: many are already being implemented. also, I believe most of the guidelines can contribute to a more collaborative and understanding work environment | BC105: G6 - Use an empathetic approach to improve requirements engineering processes I will ensure clear communication and active stakeholder engagement to capture and address their needs effectively. G7 - Collaborative problem solving I will facilitate discussions to incorporate diverse perspectives, ensuring better alignment and higher-quality solutions. G9 - Empathetic feedback process I will provide constructive feedback to support growth and ensure team members feel valued and motivated. G12 - Flexibility in handling human issues I will offer flexible work arrangements and provide support to team members facing personal challenges. G16 - Diversity, Equity, and Inclusion (DEI) policies I will promote inclusive practices to foster empathy and ensure all team members feel respected and engaged. | BD105: Busy schedules may reduce participation and commitment during ceremonies.

Sheet Guidelines Analysis - Quant
B2: How important our proposed guidelines are for implementation in real-world industry settings?
C3: Critical to Have | D3: Very Important to Have | E3: Not Necessary to Have | F3: Somewhat Important to Have | G3: Nice to Have
A4: G1 | B4: G1 - Fostering strong relationships among stakeholders | C4: =COUNTIF('Guidelines - Data'!A$3:A$105,C3) -> 29 | D4: =COUNTIF('Guidelines - Data'!A$3:A$105,D3) -> 51 | E4: =COUNTIF('Guidelines - Data'!A$3:A$105,E3) -> 4 | F4: =COUNTIF('Guidelines - Data'!A$3:A$105,F3) -> 14 | G4: =COUNTIF('Guidelines - Data'!A$3:A$105,G3) -> 5
A5: G2 | B5: G2 - Bridging the technical and non-technical gap | C5: =COUNTIF('Guidelines - Data'!B3:B105,C3) -> 34 | D5: =COUNTIF('Guidelines - Data'!B3:B105,D3) -> 45 | E5: =COUNTIF('Guidelines - Data'!B3:B105,E3) -> 6 | F5: =COUNTIF('Guidelines - Data'!B3:B105,F3) -> 11 | G5: =COUNTIF('Guidelines - Data'!B3:B105,G3) -> 7
A6: G3 | B6: G3 - Reducing friction among different stakeholder groups | C6: =COUNTIF('Guidelines - Data'!C3:C105,C3) -> 25 | D6: =COUNTIF('Guidelines - Data'!C3:C105,D3) -> 42 | E6: =COUNTIF('Guidelines - Data'!C3:C105,E3) -> 9 | F6: =COUNTIF('Guidelines - Data'!C3:C105,F3) -> 18 | G6: =COUNTIF('Guidelines - Data'!C3:C105,G3) -> 9
A7: G4 | B7: G4 - Encouraging bi-directional communication | C7: =COUNTIF('Guidelines - Data'!D3:D105,C3) -> 39 | D7: =COUNTIF('Guidelines - Data'!D3:D105,D3) -> 35 | E7: =COUNTIF('Guidelines - Data'!D3:D105,E3) -> 7 | F7: =COUNTIF('Guidelines - Data'!D3:D105,F3) -> 12 | G7: =COUNTIF('Guidelines - Data'!D3:D105,G3) -> 10
A8: G5 | B8: G5 - Ensuring transparency about business goals | C8: =COUNTIF('Guidelines - Data'!E3:E105,C3) -> 37 | D8: =COUNTIF('Guidelines - Data'!E3:E105,D3) -> 37 | E8: =COUNTIF('Guidelines - Data'!E3:E105,E3) -> 7 | F8: =COUNTIF('Guidelines - Data'!E3:E105,F3) -> 17 | G8: =COUNTIF('Guidelines - Data'!E3:E105,G3) -> 5
A9: G6 | B9: G6 - Use an empathetic approach to improve RE processes | C9: =COUNTIF('Guidelines - Data'!$F$3:$F$105,C3) -> 10 | D9: =COUNTIF('Guidelines - Data'!$F$3:$F$105,D3) -> 47 | E9: =COUNTIF('Guidelines - Data'!$F$3:$F$105,E3) -> 13 | F9: =COUNTIF('Guidelines - Data'!$F$3:$F$105,F3) -> 24 | G9: =COUNTIF('Guidelines - Data'!$F$3:$F$105,G3) -> 9
A10: G7 | B10: G7 - Collaborative problem solving | C10: =COUNTIF('Guidelines - Data'!$G$3:$G$105,C3) -> 41 | D10: =COUNTIF('Guidelines - Data'!$G$3:$G$105,D3) -> 34 | E10: =COUNTIF('Guidelines - Data'!$G$3:$G$105,E3) -> 5 | F10: =COUNTIF('Guidelines - Data'!$G$3:$G$105,F3) -> 13 | G10: =COUNTIF('Guidelines - Data'!$G$3:$G$105,G3) -> 10
A11: G8 | B11: G8 - Empathy during agile ceremonies | C11: =COUNTIF('Guidelines - Data'!$H$3:$H$105,C3) -> 13 | D11: =COUNTIF('Guidelines - Data'!$H$3:$H$105,D3) -> 36 | E11: =COUNTIF('Guidelines - Data'!$H$3:$H$105,E3) -> 19 | F11: =COUNTIF('Guidelines - Data'!$H$3:$H$105,F3) -> 27 | G11: =COUNTIF('Guidelines - Data'!$H$3:$H$105,G3) -> 8
A12: G9 | B12: G9 - Empathetic feedback process | C12: =COUNTIF('Guidelines - Data'!$I$3:$I$105,C3) -> 28 | D12: =COUNTIF('Guidelines - Data'!$I$3:$I$105,D3) -> 41 | E12: =COUNTIF('Guidelines - Data'!$I$3:$I$105,E3) -> 6 | F12: =COUNTIF('Guidelines - Data'!$I$3:$I$105,F3) -> 15 | G12: =COUNTIF('Guidelines - Data'!$I$3:$I$105,G3) -> 13
A13: G10 | B13: G10 - Creating a safe space | C13: =COUNTIF('Guidelines - Data'!$J$3:$J$105,C3) -> 43 | D13: =COUNTIF('Guidelines - Data'!$J$3:$J$105,D3) -> 29 | E13: =COUNTIF('Guidelines - Data'!$J$3:$J$105,E3) -> 4 | F13: =COUNTIF('Guidelines - Data'!$J$3:$J$105,F3) -> 15 | G13: =COUNTIF('Guidelines - Data'!$J$3:$J$105,G3) -> 12
A14: G11 | B14: G11 - Backup plans to manage unexpected outcomes | C14: =COUNTIF('Guidelines - Data'!$K$3:$K$105,C3) -> 42 | D14: =COUNTIF('Guidelines - Data'!$K$3:$K$105,D3) -> 32 | E14: =COUNTIF('Guidelines - Data'!$K$3:$K$105,E3) -> 9 | F14: =COUNTIF('Guidelines - Data'!$K$3:$K$105,F3) -> 9 | G14: =COUNTIF('Guidelines - Data'!$K$3:$K$105,G3) -> 11
A15: G12 | B15: G12 - Flexibility in handling human issues | C15: =COUNTIF('Guidelines - Data'!$L$3:$L$105,C3) -> 27 | D15: =COUNTIF('Guidelines - Data'!$L$3:$L$105,D3) -> 43 | E15: =COUNTIF('Guidelines - Data'!$L$3:$L$105,E3) -> 7 | F15: =COUNTIF('Guidelines - Data'!$L$3:$L$105,F3) -> 14 | G15: =COUNTIF('Guidelines - Data'!$L$3:$L$105,G3) -> 12
A16: G13 | B16: G13 - Emphasising the real-world impact of developers’ work | C16: =COUNTIF('Guidelines - Data'!$M$3:$M$105,C3) -> 20 | D16: =COUNTIF('Guidelines - Data'!$M$3:$M$105,D3) -> 36 | E16: =COUNTIF('Guidelines - Data'!$M$3:$M$105,E3) -> 9 | F16: =COUNTIF('Guidelines - Data'!$M$3:$M$105,F3) -> 24 | G16: =COUNTIF('Guidelines - Data'!$M$3:$M$105,G3) -> 14
A17: G14 | B17: G14 - Building an empathetic team and company culture | C17: =COUNTIF('Guidelines - Data'!$N$3:$N$105,C3) -> 32 | D17: =COUNTIF('Guidelines - Data'!$N$3:$N$105,D3) -> 34 | E17: =COUNTIF('Guidelines - Data'!$N$3:$N$105,E3) -> 9 | F17: =COUNTIF('Guidelines - Data'!$N$3:$N$105,F3) -> 17 | G17: =COUNTIF('Guidelines - Data'!$N$3:$N$105,G3) -> 11
A18: G15 | B18: G15 - Empathy education and training | C18: =COUNTIF('Guidelines - Data'!$O$3:$O$105,C3) -> 21 | D18: =COUNTIF('Guidelines - Data'!$O$3:$O$105,D3) -> 36 | E18: =COUNTIF('Guidelines - Data'!$O$3:$O$105,E3) -> 11 | F18: =COUNTIF('Guidelines - Data'!$O$3:$O$105,F3) -> 22 | G18: =COUNTIF('Guidelines - Data'!$O$3:$O$105,G3) -> 13
A19: G16 | B19: G16 - DEI policies | C19: =COUNTIF('Guidelines - Data'!$P$3:$P$105,C3) -> 21 | D19: =COUNTIF('Guidelines - Data'!$P$3:$P$105,D3) -> 28 | E19: =COUNTIF('Guidelines - Data'!$P$3:$P$105,E3) -> 20 | F19: =COUNTIF('Guidelines - Data'!$P$3:$P$105,F3) -> 18 | G19: =COUNTIF('Guidelines - Data'!$P$3:$P$105,G3) -> 16
A20: G17 | B20: G17 - Managing empathy fatigue | C20: =COUNTIF('Guidelines - Data'!$Q$3:$Q$105,C3) -> 22 | D20: =COUNTIF('Guidelines - Data'!$Q$3:$Q$105,D3) -> 34 | E20: =COUNTIF('Guidelines - Data'!$Q$3:$Q$105,E3) -> 7 | F20: =COUNTIF('Guidelines - Data'!$Q$3:$Q$105,F3) -> 30 | G20: =COUNTIF('Guidelines - Data'!$Q$3:$Q$105,G3) -> 10
B25: How practical and easy are our proposed guidelines to implement in real industry settings
C26: Very Easy | D26: Easy | E26: Neither difficult nor easy | F26: Difficult | G26: Very Difficult | H26: N/A
A27: G1 | B27: G1 - Fostering strong relationships among stakeholders | C27: =COUNTIF('Guidelines - Data'!$S$3:$S$105,C26) -> 7 | D27: =COUNTIF('Guidelines - Data'!$S$3:$S$105,D26) -> 31 | E27: =COUNTIF('Guidelines - Data'!$S$3:$S$105,E26) -> 11 | F27: =COUNTIF('Guidelines - Data'!$S$3:$S$105,F26) -> 37 | G27: =COUNTIF('Guidelines - Data'!$S$3:$S$105,G26) -> 17 | H27: =COUNTIF('Guidelines - Data'!$S$3:$S$105,H26) -> 0
A28: G2 | B28: G2 - Bridging the technical and non-technical gap | C28: =COUNTIF('Guidelines - Data'!$T$3:$T$105,C26) -> 6 | D28: =COUNTIF('Guidelines - Data'!$T$3:$T$105,D26) -> 29 | E28: =COUNTIF('Guidelines - Data'!$T$3:$T$105,E26) -> 19 | F28: =COUNTIF('Guidelines - Data'!$T$3:$T$105,F26) -> 29 | G28: =COUNTIF('Guidelines - Data'!$T$3:$T$105,G26) -> 20 | H28: =COUNTIF('Guidelines - Data'!$T$3:$T$105,H26) -> 0
A29: G3 | B29: G3 - Reducing friction among different stakeholder groups | C29: =COUNTIF('Guidelines - Data'!$U$3:$U$105,C26) -> 4 | D29: =COUNTIF('Guidelines - Data'!$U$3:$U$105,D26) -> 22 | E29: =COUNTIF('Guidelines - Data'!$U$3:$U$105,E26) -> 19 | F29: =COUNTIF('Guidelines - Data'!$U$3:$U$105,F26) -> 38 | G29: =COUNTIF('Guidelines - Data'!$U$3:$U$105,G26) -> 20 | H29: =COUNTIF('Guidelines - Data'!$U$3:$U$105,H26) -> 0
A30: G4 | B30: G4 - Encouraging bi-directional communication | C30: =COUNTIF('Guidelines - Data'!$V$3:$V$105,C26) -> 6 | D30: =COUNTIF('Guidelines - Data'!$V$3:$V$105,D26) -> 47 | E30: =COUNTIF('Guidelines - Data'!$V$3:$V$105,E26) -> 16 | F30: =COUNTIF('Guidelines - Data'!$V$3:$V$105,F26) -> 26 | G30: =COUNTIF('Guidelines - Data'!$V$3:$V$105,G26) -> 8 | H30: =COUNTIF('Guidelines - Data'!$V$3:$V$105,H26) -> 0
A31: G5 | B31: G5 - Ensuring transparency about business goals | C31: =COUNTIF('Guidelines - Data'!$W$3:$W$105,C26) -> 12 | D31: =COUNTIF('Guidelines - Data'!$W$3:$W$105,D26) -> 49 | E31: =COUNTIF('Guidelines - Data'!$W$3:$W$105,E26) -> 9 | F31: =COUNTIF('Guidelines - Data'!$W$3:$W$105,F26) -> 18 | G31: =COUNTIF('Guidelines - Data'!$W$3:$W$105,G26) -> 15 | H31: =COUNTIF('Guidelines - Data'!$W$3:$W$105,H26) -> 0
A32: G6 | B32: G6 - Use an empathetic approach to improve RE processes | C32: =COUNTIF('Guidelines - Data'!$X$3:$X$105,C26) -> 8 | D32: =COUNTIF('Guidelines - Data'!$X$3:$X$105,D26) -> 40 | E32: =COUNTIF('Guidelines - Data'!$X$3:$X$105,E26) -> 18 | F32: =COUNTIF('Guidelines - Data'!$X$3:$X$105,F26) -> 30 | G32: =COUNTIF('Guidelines - Data'!$X$3:$X$105,G26) -> 7 | H32: =COUNTIF('Guidelines - Data'!$X$3:$X$105,H26) -> 0
A33: G7 | B33: G7 - Collaborative problem solving | C33: =COUNTIF('Guidelines - Data'!$Y$3:$Y$105,C26) -> 12 | D33: =COUNTIF('Guidelines - Data'!$Y$3:$Y$105,D26) -> 37 | E33: =COUNTIF('Guidelines - Data'!$Y$3:$Y$105,E26) -> 12 | F33: =COUNTIF('Guidelines - Data'!$Y$3:$Y$105,F26) -> 28 | G33: =COUNTIF('Guidelines - Data'!$Y$3:$Y$105,G26) -> 14 | H33: =COUNTIF('Guidelines - Data'!$Y$3:$Y$105,H26) -> 0
A34: G8 | B34: G8 - Empathy during agile ceremonies | C34: =COUNTIF('Guidelines - Data'!$Z$3:$Z$105,C26) -> 11 | D34: =COUNTIF('Guidelines - Data'!$Z$3:$Z$105,D26) -> 40 | E34: =COUNTIF('Guidelines - Data'!$Z$3:$Z$105,E26) -> 19 | F34: =COUNTIF('Guidelines - Data'!$Z$3:$Z$105,F26) -> 27 | G34: =COUNTIF('Guidelines - Data'!$Z$3:$Z$105,G26) -> 6 | H34: =COUNTIF('Guidelines - Data'!$Z$3:$Z$105,H26) -> 0
A35: G9 | B35: G9 - Empathetic feedback process | C35: =COUNTIF('Guidelines - Data'!$AA$3:$AA$105,C26) -> 11 | D35: =COUNTIF('Guidelines - Data'!$AA$3:$AA$105,D26) -> 48 | E35: =COUNTIF('Guidelines - Data'!$AA$3:$AA$105,E26) -> 16 | F35: =COUNTIF('Guidelines - Data'!$AA$3:$AA$105,F26) -> 19 | G35: =COUNTIF('Guidelines - Data'!$AA$3:$AA$105,G26) -> 8 | H35: =COUNTIF('Guidelines - Data'!$AA$3:$AA$105,H26) -> 1
A36: G10 | B36: G10 - Creating a safe space | C36: =COUNTIF('Guidelines - Data'!$AB$3:$AB$105,C26) -> 17 | D36: =COUNTIF('Guidelines - Data'!$AB$3:$AB$105,D26) -> 48 | E36: =COUNTIF('Guidelines - Data'!$AB$3:$AB$105,E26) -> 9 | F36: =COUNTIF('Guidelines - Data'!$AB$3:$AB$105,F26) -> 20 | G36: =COUNTIF('Guidelines - Data'!$AB$3:$AB$105,G26) -> 8 | H36: =COUNTIF('Guidelines - Data'!$AB$3:$AB$105,H26) -> 1
A37: G11 | B37: G11 - Backup plans to manage unexpected outcomes | C37: =COUNTIF('Guidelines - Data'!$AC$3:$AC$105,C26) -> 11 | D37: =COUNTIF('Guidelines - Data'!$AC$3:$AC$105,D26) -> 23 | E37: =COUNTIF('Guidelines - Data'!$AC$3:$AC$105,E26) -> 17 | F37: =COUNTIF('Guidelines - Data'!$AC$3:$AC$105,F26) -> 23 | G37: =COUNTIF('Guidelines - Data'!$AC$3:$AC$105,G26) -> 29 | H37: =COUNTIF('Guidelines - Data'!$AC$3:$AC$105,H26) -> 0
A38: G12 | B38: G12 - Flexibility in handling human issues | C38: =COUNTIF('Guidelines - Data'!$AD$3:$AD$105,C26) -> 10 | D38: =COUNTIF('Guidelines - Data'!$AD$3:$AD$105,D26) -> 37 | E38: =COUNTIF('Guidelines - Data'!$AD$3:$AD$105,E26) -> 10 | F38: =COUNTIF('Guidelines - Data'!$AD$3:$AD$105,F26) -> 31 | G38: =COUNTIF('Guidelines - Data'!$AD$3:$AD$105,G26) -> 15 | H38: =COUNTIF('Guidelines - Data'!$AD$3:$AD$105,H26) -> 0
A39: G13 | B39: G13 - Emphasising the real-world impact of developers’ work | C39: =COUNTIF('Guidelines - Data'!$AE$3:$AE$105,C26) -> 8 | D39: =COUNTIF('Guidelines - Data'!$AE$3:$AE$105,D26) -> 37 | E39: =COUNTIF('Guidelines - Data'!$AE$3:$AE$105,E26) -> 21 | F39: =COUNTIF('Guidelines - Data'!$AE$3:$AE$105,F26) -> 24 | G39: =COUNTIF('Guidelines - Data'!$AE$3:$AE$105,G26) -> 12 | H39: =COUNTIF('Guidelines - Data'!$AE$3:$AE$105,H26) -> 1
A40: G14 | B40: G14 - Building an empathetic team and company culture | C40: =COUNTIF('Guidelines - Data'!$AF$3:$AF$105,C26) -> 3 | D40: =COUNTIF('Guidelines - Data'!$AF$3:$AF$105,D26) -> 27 | E40: =COUNTIF('Guidelines - Data'!$AF$3:$AF$105,E26) -> 21 | F40: =COUNTIF('Guidelines - Data'!$AF$3:$AF$105,F26) -> 35 | G40: =COUNTIF('Guidelines - Data'!$AF$3:$AF$105,G26) -> 16 | H40: =COUNTIF('Guidelines - Data'!$AF$3:$AF$105,H26) -> 1
A41: G15 | B41: G15 - Empathy education and training | C41: =COUNTIF('Guidelines - Data'!$AG$3:$AG$105,C26) -> 8 | D41: =COUNTIF('Guidelines - Data'!$AG$3:$AG$105,D26) -> 42 | E41: =COUNTIF('Guidelines - Data'!$AG$3:$AG$105,E26) -> 17 | F41: =COUNTIF('Guidelines - Data'!$AG$3:$AG$105,F26) -> 24 | G41: =COUNTIF('Guidelines - Data'!$AG$3:$AG$105,G26) -> 10 | H41: =COUNTIF('Guidelines - Data'!$AG$3:$AG$105,H26) -> 2
A42: G16 | B42: G16 - DEI policies | C42: =COUNTIF('Guidelines - Data'!$AH$3:$AH$105,C26) -> 9 | D42: =COUNTIF('Guidelines - Data'!$AH$3:$AH$105,D26) -> 35 | E42: =COUNTIF('Guidelines - Data'!$AH$3:$AH$105,E26) -> 18 | F42: =COUNTIF('Guidelines - Data'!$AH$3:$AH$105,F26) -> 23 | G42: =COUNTIF('Guidelines - Data'!$AH$3:$AH$105,G26) -> 15 | H42: =COUNTIF('Guidelines - Data'!$AH$3:$AH$105,H26) -> 3
A43: G17 | B43: G17 - Managing empathy fatigue | C43: =COUNTIF('Guidelines - Data'!$AI$3:$AI$105,C26) -> 6 | D43: =COUNTIF('Guidelines - Data'!$AI$3:$AI$105,D26) -> 20 | E43: =COUNTIF('Guidelines - Data'!$AI$3:$AI$105,E26) -> 16 | F43: =COUNTIF('Guidelines - Data'!$AI$3:$AI$105,F26) -> 45 | G43: =COUNTIF('Guidelines - Data'!$AI$3:$AI$105,G26) -> 13 | H43: =COUNTIF('Guidelines - Data'!$AI$3:$AI$105,H26) -> 3
B49: How practical and easy are our proposed guidelines to implement in real industry settings
C50: Very Easy | D50: Easy | E50: Very Easy + Easy Count | F50: Neither difficult nor easy | G50: Difficult | H50: Very Difficult | I50: Very Difficult + Difficult Count | J50: N/A
A51: G1 | B51: G1 - Fostering strong relationships among stakeholders | C51: =COUNTIF('Guidelines - Data'!$S$3:$S$105,C50) -> 7 | D51: =COUNTIF('Guidelines - Data'!$S$3:$S$105,D50) -> 31 | E51: =SUM(C51:D51) -> 38 | F51: =COUNTIF('Guidelines - Data'!$S$3:$S$105,F50) -> 11 | G51: =COUNTIF('Guidelines - Data'!$S$3:$S$105,G50) -> 37 | H51: =COUNTIF('Guidelines - Data'!$S$3:$S$105,H50) -> 17 | I51: =SUM(G51:H51) -> 54 | J51: =COUNTIF('Guidelines - Data'!$S$3:$S$105,J50) -> 0
A52: G2 | B52: G2 - Bridging the technical and non-technical gap | C52: =COUNTIF('Guidelines - Data'!$T$3:$T$105,C50) -> 6 | D52: =COUNTIF('Guidelines - Data'!$T$3:$T$105,D50) -> 29 | E52: =SUM(C52:D52) -> 35 | F52: =COUNTIF('Guidelines - Data'!$T$3:$T$105,F50) -> 19 | G52: =COUNTIF('Guidelines - Data'!$T$3:$T$105,G50) -> 29 | H52: =COUNTIF('Guidelines - Data'!$T$3:$T$105,H50) -> 20 | I52: =SUM(G52:H52) -> 49 | J52: =COUNTIF('Guidelines - Data'!$T$3:$T$105,J50) -> 0
A53: G3 | B53: G3 - Reducing friction among different stakeholder groups | C53: =COUNTIF('Guidelines - Data'!$U$3:$U$105,C50) -> 4 | D53: =COUNTIF('Guidelines - Data'!$U$3:$U$105,D50) -> 22 | E53: =SUM(C53:D53) -> 26 | F53: =COUNTIF('Guidelines - Data'!$U$3:$U$105,F50) -> 19 | G53: =COUNTIF('Guidelines - Data'!$U$3:$U$105,G50) -> 38 | H53: =COUNTIF('Guidelines - Data'!$U$3:$U$105,H50) -> 20 | I53: =SUM(G53:H53) -> 58 | J53: =COUNTIF('Guidelines - Data'!$U$3:$U$105,J50) -> 0
A54: G4 | B54: G4 - Encouraging bi-directional communication | C54: =COUNTIF('Guidelines - Data'!$V$3:$V$105,C50) -> 6 | D54: =COUNTIF('Guidelines - Data'!$V$3:$V$105,D50) -> 47 | E54: =SUM(C54:D54) -> 53 | F54: =COUNTIF('Guidelines - Data'!$V$3:$V$105,F50) -> 16 | G54: =COUNTIF('Guidelines - Data'!$V$3:$V$105,G50) -> 26 | H54: =COUNTIF('Guidelines - Data'!$V$3:$V$105,H50) -> 8 | I54: =SUM(G54:H54) -> 34 | J54: =COUNTIF('Guidelines - Data'!$V$3:$V$105,J50) -> 0
A55: G5 | B55: G5 - Ensuring transparency about business goals | C55: =COUNTIF('Guidelines - Data'!$W$3:$W$105,C50) -> 12 | D55: =COUNTIF('Guidelines - Data'!$W$3:$W$105,D50) -> 49 | E55: =SUM(C55:D55) -> 61 | F55: =COUNTIF('Guidelines - Data'!$W$3:$W$105,F50) -> 9 | G55: =COUNTIF('Guidelines - Data'!$W$3:$W$105,G50) -> 18 | H55: =COUNTIF('Guidelines - Data'!$W$3:$W$105,H50) -> 15 | I55: =SUM(G55:H55) -> 33 | J55: =COUNTIF('Guidelines - Data'!$W$3:$W$105,J50) -> 0
A56: G6 | B56: G6 - Use an empathetic approach to improve RE processes | C56: =COUNTIF('Guidelines - Data'!$X$3:$X$105,C50) -> 8 | D56: =COUNTIF('Guidelines - Data'!$X$3:$X$105,D50) -> 40 | E56: =SUM(C56:D56) -> 48 | F56: =COUNTIF('Guidelines - Data'!$X$3:$X$105,F50) -> 18 | G56: =COUNTIF('Guidelines - Data'!$X$3:$X$105,G50) -> 30 | H56: =COUNTIF('Guidelines - Data'!$X$3:$X$105,H50) -> 7 | I56: =SUM(G56:H56) -> 37 | J56: =COUNTIF('Guidelines - Data'!$X$3:$X$105,J50) -> 0
A57: G7 | B57: G7 - Collaborative problem solving | C57: =COUNTIF('Guidelines - Data'!$Y$3:$Y$105,C50) -> 12 | D57: =COUNTIF('Guidelines - Data'!$Y$3:$Y$105,D50) -> 37 | E57: =SUM(C57:D57) -> 49 | F57: =COUNTIF('Guidelines - Data'!$Y$3:$Y$105,F50) -> 12 | G57: =COUNTIF('Guidelines - Data'!$Y$3:$Y$105,G50) -> 28 | H57: =COUNTIF('Guidelines - Data'!$Y$3:$Y$105,H50) -> 14 | I57: =SUM(G57:H57) -> 42 | J57: =COUNTIF('Guidelines - Data'!$Y$3:$Y$105,J50) -> 0
A58: G8 | B58: G8 - Empathy during agile ceremonies | C58: =COUNTIF('Guidelines - Data'!$Z$3:$Z$105,C50) -> 11 | D58: =COUNTIF('Guidelines - Data'!$Z$3:$Z$105,D50) -> 40 | E58: =SUM(C58:D58) -> 51 | F58: =COUNTIF('Guidelines - Data'!$Z$3:$Z$105,F50) -> 19 | G58: =COUNTIF('Guidelines - Data'!$Z$3:$Z$105,G50) -> 27 | H58: =COUNTIF('Guidelines - Data'!$Z$3:$Z$105,H50) -> 6 | I58: =SUM(G58:H58) -> 33 | J58: =COUNTIF('Guidelines - Data'!$Z$3:$Z$105,J50) -> 0
A59: G9 | B59: G9 - Empathetic feedback process | C59: =COUNTIF('Guidelines - Data'!$AA$3:$AA$105,C50) -> 11 | D59: =COUNTIF('Guidelines - Data'!$AA$3:$AA$105,D50) -> 48 | E59: =SUM(C59:D59) -> 59 | F59: =COUNTIF('Guidelines - Data'!$AA$3:$AA$105,F50) -> 16 | G59: =COUNTIF('Guidelines - Data'!$AA$3:$AA$105,G50) -> 19 | H59: =COUNTIF('Guidelines - Data'!$AA$3:$AA$105,H50) -> 8 | I59: =SUM(G59:H59) -> 27 | J59: =COUNTIF('Guidelines - Data'!$AA$3:$AA$105,J50) -> 1
A60: G10 | B60: G10 - Creating a safe space | C60: =COUNTIF('Guidelines - Data'!$AB$3:$AB$105,C50) -> 17 | D60: =COUNTIF('Guidelines - Data'!$AB$3:$AB$105,D50) -> 48 | E60: =SUM(C60:D60) -> 65 | F60: =COUNTIF('Guidelines - Data'!$AB$3:$AB$105,F50) -> 9 | G60: =COUNTIF('Guidelines - Data'!$AB$3:$AB$105,G50) -> 20 | H60: =COUNTIF('Guidelines - Data'!$AB$3:$AB$105,H50) -> 8 | I60: =SUM(G60:H60) -> 28 | J60: =COUNTIF('Guidelines - Data'!$AB$3:$AB$105,J50) -> 1
A61: G11 | B61: G11 - Backup plans to manage unexpected outcomes | C61: =COUNTIF('Guidelines - Data'!$AC$3:$AC$105,C50) -> 11 | D61: =COUNTIF('Guidelines - Data'!$AC$3:$AC$105,D50) -> 23 | E61: =SUM(C61:D61) -> 34 | F61: =COUNTIF('Guidelines - Data'!$AC$3:$AC$105,F50) -> 17 | G61: =COUNTIF('Guidelines - Data'!$AC$3:$AC$105,G50) -> 23 | H61: =COUNTIF('Guidelines - Data'!$AC$3:$AC$105,H50) -> 29 | I61: =SUM(G61:H61) -> 52 | J61: =COUNTIF('Guidelines - Data'!$AC$3:$AC$105,J50) -> 0
A62: G12 | B62: G12 - Flexibility in handling human issues | C62: =COUNTIF('Guidelines - Data'!$AD$3:$AD$105,C50) -> 10 | D62: =COUNTIF('Guidelines - Data'!$AD$3:$AD$105,D50) -> 37 | E62: =SUM(C62:D62) -> 47 | F62: =COUNTIF('Guidelines - Data'!$AD$3:$AD$105,F50) -> 10 | G62: =COUNTIF('Guidelines - Data'!$AD$3:$AD$105,G50) -> 31 | H62: =COUNTIF('Guidelines - Data'!$AD$3:$AD$105,H50) -> 15 | I62: =SUM(G62:H62) -> 46 | J62: =COUNTIF('Guidelines - Data'!$AD$3:$AD$105,J50) -> 0
A63: G13 | B63: G13 - Emphasising the real-world impact of developers’ work | C63: =COUNTIF('Guidelines - Data'!$AE$3:$AE$105,C50) -> 8 | D63: =COUNTIF('Guidelines - Data'!$AE$3:$AE$105,D50) -> 37 | E63: =SUM(C63:D63) -> 45 | F63: =COUNTIF('Guidelines - Data'!$AE$3:$AE$105,F50) -> 21 | G63: =COUNTIF('Guidelines - Data'!$AE$3:$AE$105,G50) -> 24 | H63: =COUNTIF('Guidelines - Data'!$AE$3:$AE$105,H50) -> 12 | I63: =SUM(G63:H63) -> 36 | J63: =COUNTIF('Guidelines - Data'!$AE$3:$AE$105,J50) -> 1
A64: G14 | B64: G14 - Building an empathetic team and company culture | C64: =COUNTIF('Guidelines - Data'!$AF$3:$AF$105,C50) -> 3 | D64: =COUNTIF('Guidelines - Data'!$AF$3:$AF$105,D50) -> 27 | E64: =SUM(C64:D64) -> 30 | F64: =COUNTIF('Guidelines - Data'!$AF$3:$AF$105,F50) -> 21 | G64: =COUNTIF('Guidelines - Data'!$AF$3:$AF$105,G50) -> 35 | H64: =COUNTIF('Guidelines - Data'!$AF$3:$AF$105,H50) -> 16 | I64: =SUM(G64:H64) -> 51 | J64: =COUNTIF('Guidelines - Data'!$AF$3:$AF$105,J50) -> 1
A65: G15 | B65: G15 - Empathy education and training | C65: =COUNTIF('Guidelines - Data'!$AG$3:$AG$105,C50) -> 8 | D65: =COUNTIF('Guidelines - Data'!$AG$3:$AG$105,D50) -> 42 | E65: =SUM(C65:D65) -> 50 | F65: =COUNTIF('Guidelines - Data'!$AG$3:$AG$105,F50) -> 17 | G65: =COUNTIF('Guidelines - Data'!$AG$3:$AG$105,G50) -> 24 | H65: =COUNTIF('Guidelines - Data'!$AG$3:$AG$105,H50) -> 10 | I65: =SUM(G65:H65) -> 34 | J65: =COUNTIF('Guidelines - Data'!$AG$3:$AG$105,J50) -> 2
A66: G16 | B66: G16 - DEI policies | C66: =COUNTIF('Guidelines - Data'!$AH$3:$AH$105,C50) -> 9 | D66: =COUNTIF('Guidelines - Data'!$AH$3:$AH$105,D50) -> 35 | E66: =SUM(C66:D66) -> 44 | F66: =COUNTIF('Guidelines - Data'!$AH$3:$AH$105,F50) -> 18 | G66: =COUNTIF('Guidelines - Data'!$AH$3:$AH$105,G50) -> 23 | H66: =COUNTIF('Guidelines - Data'!$AH$3:$AH$105,H50) -> 15 | I66: =SUM(G66:H66) -> 38 | J66: =COUNTIF('Guidelines - Data'!$AH$3:$AH$105,J50) -> 3
A67: G17 | B67: G17 - Managing empathy fatigue | C67: =COUNTIF('Guidelines - Data'!$AI$3:$AI$105,C50) -> 6 | D67: =COUNTIF('Guidelines - Data'!$AI$3:$AI$105,D50) -> 20 | E67: =SUM(C67:D67) -> 26 | F67: =COUNTIF('Guidelines - Data'!$AI$3:$AI$105,F50) -> 16 | G67: =COUNTIF('Guidelines - Data'!$AI$3:$AI$105,G50) -> 45 | H67: =COUNTIF('Guidelines - Data'!$AI$3:$AI$105,H50) -> 13 | I67: =SUM(G67:H67) -> 58 | J67: =COUNTIF('Guidelines - Data'!$AI$3:$AI$105,J50) -> 3
B72: Would you consider using our proposed guidelines to enhance empathy in your software engineering practice
C73: I am currently using it | D73: I will definitely use it | E73: I am likely to regularly use it | F73: I might occasionally use it | G73: I am unlikely to use it | H73: I will never use it
A74: G1 | B74: G1 - Fostering strong relationships among stakeholders | C74: =COUNTIF('Guidelines - Data'!$AK$3:$AK$105,C73) -> 34 | D74: =COUNTIF('Guidelines - Data'!$AK$3:$AK$105,D73) -> 28 | E74: =COUNTIF('Guidelines - Data'!$AK$3:$AK$105,E73) -> 27 | F74: =COUNTIF('Guidelines - Data'!$AK$3:$AK$105,F73) -> 10 | G74: =COUNTIF('Guidelines - Data'!$AK$3:$AK$105,G73) -> 3 | H74: =COUNTIF('Guidelines - Data'!$AK$3:$AK$105,H73) -> 1
A75: G2 | B75: G2 - Bridging the technical and non-technical gap | C75: =COUNTIF('Guidelines - Data'!$AL$3:$AL$105,C73) -> 42 | D75: =COUNTIF('Guidelines - Data'!$AL$3:$AL$105,D73) -> 27 | E75: =COUNTIF('Guidelines - Data'!$AL$3:$AL$105,E73) -> 21 | F75: =COUNTIF('Guidelines - Data'!$AL$3:$AL$105,F73) -> 12 | G75: =COUNTIF('Guidelines - Data'!$AL$3:$AL$105,G73) -> 1 | H75: =COUNTIF('Guidelines - Data'!$AL$3:$AL$105,H73) -> 0
A76: G3 | B76: G3 - Reducing friction among different stakeholder groups | C76: =COUNTIF('Guidelines - Data'!$AM$3:$AM$105,C73) -> 23 | D76: =COUNTIF('Guidelines - Data'!$AM$3:$AM$105,D73) -> 34 | E76: =COUNTIF('Guidelines - Data'!$AM$3:$AM$105,E73) -> 28 | F76: =COUNTIF('Guidelines - Data'!$AM$3:$AM$105,F73) -> 11 | G76: =COUNTIF('Guidelines - Data'!$AM$3:$AM$105,G73) -> 5 | H76: =COUNTIF('Guidelines - Data'!$AM$3:$AM$105,H73) -> 2
A77: G4 | B77: G4 - Encouraging bi-directional communication | C77: =COUNTIF('Guidelines - Data'!$AN$3:$AN$105,C73) -> 43 | D77: =COUNTIF('Guidelines - Data'!$AN$3:$AN$105,D73) -> 28 | E77: =COUNTIF('Guidelines - Data'!$AN$3:$AN$105,E73) -> 23 | F77: =COUNTIF('Guidelines - Data'!$AN$3:$AN$105,F73) -> 7 | G77: =COUNTIF('Guidelines - Data'!$AN$3:$AN$105,G73) -> 2 | H77: =COUNTIF('Guidelines - Data'!$AN$3:$AN$105,H73) -> 0
A78: G5 | B78: G5 - Ensuring transparency about business goals | C78: =COUNTIF('Guidelines - Data'!$AO$3:$AO$105,C73) -> 46 | D78: =COUNTIF('Guidelines - Data'!$AO$3:$AO$105,D73) -> 29 | E78: =COUNTIF('Guidelines - Data'!$AO$3:$AO$105,E73) -> 16 | F78: =COUNTIF('Guidelines - Data'!$AO$3:$AO$105,F73) -> 10 | G78: =COUNTIF('Guidelines - Data'!$AO$3:$AO$105,G73) -> 1 | H78: =COUNTIF('Guidelines - Data'!$AO$3:$AO$105,H73) -> 1
A79: G6 | B79: G6 - Use an empathetic approach to improve RE processes | C79: =COUNTIF('Guidelines - Data'!$AP$3:$AP$105,C73) -> 20 | D79: =COUNTIF('Guidelines - Data'!$AP$3:$AP$105,D73) -> 38 | E79: =COUNTIF('Guidelines - Data'!$AP$3:$AP$105,E73) -> 20 | F79: =COUNTIF('Guidelines - Data'!$AP$3:$AP$105,F73) -> 21 | G79: =COUNTIF('Guidelines - Data'!$AP$3:$AP$105,G73) -> 2 | H79: =COUNTIF('Guidelines - Data'!$AP$3:$AP$105,H73) -> 2
A80: G7 | B80: G7 - Collaborative problem solving | C80: =COUNTIF('Guidelines - Data'!$AQ$3:$AQ$105,C73) -> 54 | D80: =COUNTIF('Guidelines - Data'!$AQ$3:$AQ$105,D73) -> 32 | E80: =COUNTIF('Guidelines - Data'!$AQ$3:$AQ$105,E73) -> 10 | F80: =COUNTIF('Guidelines - Data'!$AQ$3:$AQ$105,F73) -> 7 | G80: =COUNTIF('Guidelines - Data'!$AQ$3:$AQ$105,G73) -> 0 | H80: =COUNTIF('Guidelines - Data'!$AQ$3:$AQ$105,H73) -> 0
A81: G8 | B81: G8 - Empathy during agile ceremonies | C81: =COUNTIF('Guidelines - Data'!$AR$3:$AR$105,C73) -> 21 | D81: =COUNTIF('Guidelines - Data'!$AR$3:$AR$105,D73) -> 29 | E81: =COUNTIF('Guidelines - Data'!$AR$3:$AR$105,E73) -> 19 | F81: =COUNTIF('Guidelines - Data'!$AR$3:$AR$105,F73) -> 24 | G81: =COUNTIF('Guidelines - Data'!$AR$3:$AR$105,G73) -> 9 | H81: =COUNTIF('Guidelines - Data'!$AR$3:$AR$105,H73) -> 1
A82: G9 | B82: G9 - Empathetic feedback process | C82: =COUNTIF('Guidelines - Data'!$AS$3:$AS$105,C73) -> 31 | D82: =COUNTIF('Guidelines - Data'!$AS$3:$AS$105,D73) -> 31 | E82: =COUNTIF('Guidelines - Data'!$AS$3:$AS$105,E73) -> 23 | F82: =COUNTIF('Guidelines - Data'!$AS$3:$AS$105,F73) -> 12 | G82: =COUNTIF('Guidelines - Data'!$AS$3:$AS$105,G73) -> 5 | H82: =COUNTIF('Guidelines - Data'!$AS$3:$AS$105,H73) -> 1
A83: G10 | B83: G10 - Creating a safe space | C83: =COUNTIF('Guidelines - Data'!$AT$3:$AT$105,C73) -> 44 | D83: =COUNTIF('Guidelines - Data'!$AT$3:$AT$105,D73) -> 35 | E83: =COUNTIF('Guidelines - Data'!$AT$3:$AT$105,E73) -> 13 | F83: =COUNTIF('Guidelines - Data'!$AT$3:$AT$105,F73) -> 6 | G83: =COUNTIF('Guidelines - Data'!$AT$3:$AT$105,G73) -> 4 | H83: =COUNTIF('Guidelines - Data'!$AT$3:$AT$105,H73) -> 1
A84: G11 | B84: G11 - Backup plans to manage unexpected outcomes | C84: =COUNTIF('Guidelines - Data'!$AU$3:$AU$105,C73) -> 41 | D84: =COUNTIF('Guidelines - Data'!$AU$3:$AU$105,D73) -> 39 | E84: =COUNTIF('Guidelines - Data'!$AU$3:$AU$105,E73) -> 9 | F84: =COUNTIF('Guidelines - Data'!$AU$3:$AU$105,F73) -> 10 | G84: =COUNTIF('Guidelines - Data'!$AU$3:$AU$105,G73) -> 4 | H84: =COUNTIF('Guidelines - Data'!$AU$3:$AU$105,H73) -> 0
A85: G12 | B85: G12 - Flexibility in handling human issues | C85: =COUNTIF('Guidelines - Data'!$AV$3:$AV$105,C73) -> 36 | D85: =COUNTIF('Guidelines - Data'!$AV$3:$AV$105,D73) -> 31 | E85: =COUNTIF('Guidelines - Data'!$AV$3:$AV$105,E73) -> 25 | F85: =COUNTIF('Guidelines - Data'!$AV$3:$AV$105,F73) -> 9 | G85: =COUNTIF('Guidelines - Data'!$AV$3:$AV$105,G73) -> 2 | H85: =COUNTIF('Guidelines - Data'!$AV$3:$AV$105,H73) -> 0
A86: G13 | B86: G13 - Emphasising the real-world impact of developers’ work | C86: =COUNTIF('Guidelines - Data'!$AW$3:$AW$105,C73) -> 25 | D86: =COUNTIF('Guidelines - Data'!$AW$3:$AW$105,D73) -> 46 | E86: =COUNTIF('Guidelines - Data'!$AW$3:$AW$105,E73) -> 18 | F86: =COUNTIF('Guidelines - Data'!$AW$3:$AW$105,F73) -> 8 | G86: =COUNTIF('Guidelines - Data'!$AW$3:$AW$105,G73) -> 5 | H86: =COUNTIF('Guidelines - Data'!$AW$3:$AW$105,H73) -> 1
A87: G14 | B87: G14 - Building an empathetic team and company culture | C87: =COUNTIF('Guidelines - Data'!$AX$3:$AX$105,C73) -> 40 | D87: =COUNTIF('Guidelines - Data'!$AX$3:$AX$105,D73) -> 34 | E87: =COUNTIF('Guidelines - Data'!$AX$3:$AX$105,E73) -> 16 | F87: =COUNTIF('Guidelines - Data'!$AX$3:$AX$105,F73) -> 6 | G87: =COUNTIF('Guidelines - Data'!$AX$3:$AX$105,G73) -> 6 | H87: =COUNTIF('Guidelines - Data'!$AX$3:$AX$105,H73) -> 1
A88: G15 | B88: G15 - Empathy education and training | C88: =COUNTIF('Guidelines - Data'!$AY$3:$AY$105,C73) -> 21 | D88: =COUNTIF('Guidelines - Data'!$AY$3:$AY$105,D73) -> 32 | E88: =COUNTIF('Guidelines - Data'!$AY$3:$AY$105,E73) -> 24 | F88: =COUNTIF('Guidelines - Data'!$AY$3:$AY$105,F73) -> 11 | G88: =COUNTIF('Guidelines - Data'!$AY$3:$AY$105,G73) -> 14 | H88: =COUNTIF('Guidelines - Data'!$AY$3:$AY$105,H73) -> 1
A89: G16 | B89: G16 - DEI policies | C89: =COUNTIF('Guidelines - Data'!$AZ$3:$AZ$105,C73) -> 29 | D89: =COUNTIF('Guidelines - Data'!$AZ$3:$AZ$105,D73) -> 22 | E89: =COUNTIF('Guidelines - Data'!$AZ$3:$AZ$105,E73) -> 24 | F89: =COUNTIF('Guidelines - Data'!$AZ$3:$AZ$105,F73) -> 12 | G89: =COUNTIF('Guidelines - Data'!$AZ$3:$AZ$105,G73) -> 13 | H89: =COUNTIF('Guidelines - Data'!$AZ$3:$AZ$105,H73) -> 3
A90: G17 | B90: G17 - Managing empathy fatigue | C90: =COUNTIF('Guidelines - Data'!$BA$3:$BA$105,C73) -> 19 | D90: =COUNTIF('Guidelines - Data'!$BA$3:$BA$105,D73) -> 36 | E90: =COUNTIF('Guidelines - Data'!$BA$3:$BA$105,E73) -> 19 | F90: =COUNTIF('Guidelines - Data'!$BA$3:$BA$105,F73) -> 19 | G90: =COUNTIF('Guidelines - Data'!$BA$3:$BA$105,G73) -> 8 | H90: =COUNTIF('Guidelines - Data'!$BA$3:$BA$105,H73) -> 2

Sheet Detailed Guidelines Analysis - 
J1: Percentages - Perceived Importance
B2: How important our proposed guidelines are for implementation in real-world industry settings?
C3: Critical to Have | D3: Very Important to Have | E3: Not Necessary to Have | F3: Somewhat Important to Have | G3: Nice to Have | K3: Critical to Have | L3: Very Important to Have | M3: Not Necessary to Have | N3: Somewhat Important to Have | O3: Nice to Have | T3: % Critical to Have | U3: % Very Important to Have | V3: % Not Necessary to Have | W3: % Somewhat Important to Have | X3: % Nice to Have | AC3: Perceived Importance % | AG3: Sorted Perceived Importance %
A4: G1 | B4: G1 - Fostering strong relationships among stakeholders | C4: =COUNTIF('Guidelines - Data'!A$3:A$105,C3) -> 29 | D4: =COUNTIF('Guidelines - Data'!A$3:A$105,D3) -> 51 | E4: =COUNTIF('Guidelines - Data'!A$3:A$105,E3) -> 4 | F4: =COUNTIF('Guidelines - Data'!A$3:A$105,F3) -> 14 | G4: =COUNTIF('Guidelines - Data'!A$3:A$105,G3) -> 5 | J4: G1 | K4: =(C4/(C4+D4+E4+F4+G4))*100 -> 28.15534 | L4: =(D4/(C4+D4+E4+F4+G4))*100 -> 49.514563 | M4: =(E4/(C4+D4+E4+F4+G4))*100 -> 3.8834951 | N4: =(F4/(C4+D4+E4+F4+G4))*100 -> 13.592233 | O4: =(G4/(C4+D4+E4+F4+G4))*100 -> 4.8543689 | S4: G1 | T4: =ROUND(K4,2) -> 28.16 | U4: =ROUND(L4,2) -> 49.51 | V4: =ROUND(M4,2) -> 3.88 | W4: =ROUND(N4,2) -> 13.59 | X4: =ROUND(O4,2) -> 4.85 | AA4: G1 | AB4: =((C4+D4)/(C4+D4+E4+F4+G4))*100 -> 77.669903 | AC4: =ROUND(AB4,2) -> 77.67 | AF4: G1 | AG4: 77.67
A5: G2 | B5: G2 - Bridging the technical and non-technical gap | C5: =COUNTIF('Guidelines - Data'!B3:B105,C3) -> 34 | D5: =COUNTIF('Guidelines - Data'!B3:B105,D3) -> 45 | E5: =COUNTIF('Guidelines - Data'!B3:B105,E3) -> 6 | F5: =COUNTIF('Guidelines - Data'!B3:B105,F3) -> 11 | G5: =COUNTIF('Guidelines - Data'!B3:B105,G3) -> 7 | J5: G2 | K5: =(C5/(C5+D5+E5+F5+G5))*100 -> 33.009709 | L5: =(D5/(C5+D5+E5+F5+G5))*100 -> 43.68932 | M5: =(E5/(C5+D5+E5+F5+G5))*100 -> 5.8252427 | N5: =(F5/(C5+D5+E5+F5+G5))*100 -> 10.679612 | O5: =(G5/(C5+D5+E5+F5+G5))*100 -> 6.7961165 | S5: G2 | T5: =ROUND(K5,2) -> 33.01 | U5: =ROUND(L5,2) -> 43.69 | V5: =ROUND(M5,2) -> 5.83 | W5: =ROUND(N5,2) -> 10.68 | X5: =ROUND(O5,2) -> 6.8 | AA5: G2 | AB5: =((C5+D5)/(C5+D5+E5+F5+G5))*100 -> 76.699029 | AC5: =ROUND(AB5,2) -> 76.7 | AF5: G2 | AG5: 76.7
A6: G3 | B6: G3 - Reducing friction among different stakeholder groups | C6: =COUNTIF('Guidelines - Data'!C3:C105,C3) -> 25 | D6: =COUNTIF('Guidelines - Data'!C3:C105,D3) -> 42 | E6: =COUNTIF('Guidelines - Data'!C3:C105,E3) -> 9 | F6: =COUNTIF('Guidelines - Data'!C3:C105,F3) -> 18 | G6: =COUNTIF('Guidelines - Data'!C3:C105,G3) -> 9 | J6: G3 | K6: =(C6/(C6+D6+E6+F6+G6))*100 -> 24.271845 | L6: =(D6/(C6+D6+E6+F6+G6))*100 -> 40.776699 | M6: =(E6/(C6+D6+E6+F6+G6))*100 -> 8.7378641 | N6: =(F6/(C6+D6+E6+F6+G6))*100 -> 17.475728 | O6: =(G6/(C6+D6+E6+F6+G6))*100 -> 8.7378641 | S6: G3 | T6: =ROUND(K6,2) -> 24.27 | U6: =ROUND(L6,2) -> 40.78 | V6: =ROUND(M6,2) -> 8.74 | W6: =ROUND(N6,2) -> 17.48 | X6: =ROUND(O6,2) -> 8.74 | AA6: G3 | AB6: =((C6+D6)/(C6+D6+E6+F6+G6))*100 -> 65.048544 | AC6: =ROUND(AB6,2) -> 65.05 | AF6: G10 | AG6: 72.82
A7: G4 | B7: G4 - Encouraging bi-directional communication | C7: =COUNTIF('Guidelines - Data'!D3:D105,C3) -> 39 | D7: =COUNTIF('Guidelines - Data'!D3:D105,D3) -> 35 | E7: =COUNTIF('Guidelines - Data'!D3:D105,E3) -> 7 | F7: =COUNTIF('Guidelines - Data'!D3:D105,F3) -> 12 | G7: =COUNTIF('Guidelines - Data'!D3:D105,G3) -> 10 | J7: G4 | K7: =(C7/(C7+D7+E7+F7+G7))*100 -> 37.864078 | L7: =(D7/(C7+D7+E7+F7+G7))*100 -> 33.980583 | M7: =(E7/(C7+D7+E7+F7+G7))*100 -> 6.7961165 | N7: =(F7/(C7+D7+E7+F7+G7))*100 -> 11.650485 | O7: =(G7/(C7+D7+E7+F7+G7))*100 -> 9.7087379 | S7: G4 | T7: =ROUND(K7,2) -> 37.86 | U7: =ROUND(L7,2) -> 33.98 | V7: =ROUND(M7,2) -> 6.8 | W7: =ROUND(N7,2) -> 11.65 | X7: =ROUND(O7,2) -> 9.71 | AA7: G4 | AB7: =((C7+D7)/(C7+D7+E7+F7+G7))*100 -> 71.84466 | AC7: =ROUND(AB7,2) -> 71.84 | AF7: G4 | AG7: 71.84
A8: G5 | B8: G5 - Ensuring transparency about business goals | C8: =COUNTIF('Guidelines - Data'!E3:E105,C3) -> 37 | D8: =COUNTIF('Guidelines - Data'!E3:E105,D3) -> 37 | E8: =COUNTIF('Guidelines - Data'!E3:E105,E3) -> 7 | F8: =COUNTIF('Guidelines - Data'!E3:E105,F3) -> 17 | G8: =COUNTIF('Guidelines - Data'!E3:E105,G3) -> 5 | J8: G5 | K8: =(C8/(C8+D8+E8+F8+G8))*100 -> 35.92233 | L8: =(D8/(C8+D8+E8+F8+G8))*100 -> 35.92233 | M8: =(E8/(C8+D8+E8+F8+G8))*100 -> 6.7961165 | N8: =(F8/(C8+D8+E8+F8+G8))*100 -> 16.504854 | O8: =(G8/(C8+D8+E8+F8+G8))*100 -> 4.8543689 | S8: G5 | T8: =ROUND(K8,2) -> 35.92 | U8: =ROUND(L8,2) -> 35.92 | V8: =ROUND(M8,2) -> 6.8 | W8: =ROUND(N8,2) -> 16.5 | X8: =ROUND(O8,2) -> 4.85 | AA8: G5 | AB8: =((C8+D8)/(C8+D8+E8+F8+G8))*100 -> 71.84466 | AC8: =ROUND(AB8,2) -> 71.84 | AF8: G5 | AG8: 71.84
A9: G6 | B9: G6 - Use an empathetic approach to improve RE processes | C9: =COUNTIF('Guidelines - Data'!$F$3:$F$105,C3) -> 10 | D9: =COUNTIF('Guidelines - Data'!$F$3:$F$105,D3) -> 47 | E9: =COUNTIF('Guidelines - Data'!$F$3:$F$105,E3) -> 13 | F9: =COUNTIF('Guidelines - Data'!$F$3:$F$105,F3) -> 24 | G9: =COUNTIF('Guidelines - Data'!$F$3:$F$105,G3) -> 9 | J9: G6 | K9: =(C9/(C9+D9+E9+F9+G9))*100 -> 9.7087379 | L9: =(D9/(C9+D9+E9+F9+G9))*100 -> 45.631068 | M9: =(E9/(C9+D9+E9+F9+G9))*100 -> 12.621359 | N9: =(F9/(C9+D9+E9+F9+G9))*100 -> 23.300971 | O9: =(G9/(C9+D9+E9+F9+G9))*100 -> 8.7378641 | S9: G6 | T9: =ROUND(K9,2) -> 9.71 | U9: =ROUND(L9,2) -> 45.63 | V9: =ROUND(M9,2) -> 12.62 | W9: =ROUND(N9,2) -> 23.3 | X9: =ROUND(O9,2) -> 8.74 | AA9: G6 | AB9: =((C9+D9)/(C9+D9+E9+F9+G9))*100 -> 55.339806 | AC9: =ROUND(AB9,2) -> 55.34 | AF9: G14 | AG9: 71.84
A10: G7 | B10: G7 - Collaborative problem solving | C10: =COUNTIF('Guidelines - Data'!$G$3:$G$105,C3) -> 41 | D10: =COUNTIF('Guidelines - Data'!$G$3:$G$105,D3) -> 34 | E10: =COUNTIF('Guidelines - Data'!$G$3:$G$105,E3) -> 5 | F10: =COUNTIF('Guidelines - Data'!$G$3:$G$105,F3) -> 13 | G10: =COUNTIF('Guidelines - Data'!$G$3:$G$105,G3) -> 10 | J10: G7 | K10: =(C10/(C10+D10+E10+F10+G10))*100 -> 39.805825 | L10: =(D10/(C10+D10+E10+F10+G10))*100 -> 33.009709 | M10: =(E10/(C10+D10+E10+F10+G10))*100 -> 4.8543689 | N10: =(F10/(C10+D10+E10+F10+G10))*100 -> 12.621359 | O10: =(G10/(C10+D10+E10+F10+G10))*100 -> 9.7087379 | S10: G7 | T10: =ROUND(K10,2) -> 39.81 | U10: =ROUND(L10,2) -> 33.01 | V10: =ROUND(M10,2) -> 4.85 | W10: =ROUND(N10,2) -> 12.62 | X10: =ROUND(O10,2) -> 9.71 | AA10: G7 | AB10: =((C10+D10)/(C10+D10+E10+F10+G10))*100 -> 72.815534 | AC10: =ROUND(AB10,2) -> 72.82 | AF10: G3 | AG10: 69.9
A11: G8 | B11: G8 - Empathy during agile ceremonies | C11: =COUNTIF('Guidelines - Data'!$H$3:$H$105,C3) -> 13 | D11: =COUNTIF('Guidelines - Data'!$H$3:$H$105,D3) -> 36 | E11: =COUNTIF('Guidelines - Data'!$H$3:$H$105,E3) -> 19 | F11: =COUNTIF('Guidelines - Data'!$H$3:$H$105,F3) -> 27 | G11: =COUNTIF('Guidelines - Data'!$H$3:$H$105,G3) -> 8 | J11: G8 | K11: =(C11/(C11+D11+E11+F11+G11))*100 -> 12.621359 | L11: =(D11/(C11+D11+E11+F11+G11))*100 -> 34.951456 | M11: =(E11/(C11+D11+E11+F11+G11))*100 -> 18.446602 | N11: =(F11/(C11+D11+E11+F11+G11))*100 -> 26.213592 | O11: =(G11/(C11+D11+E11+F11+G11))*100 -> 7.7669903 | S11: G8 | T11: =ROUND(K11,2) -> 12.62 | U11: =ROUND(L11,2) -> 34.95 | V11: =ROUND(M11,2) -> 18.45 | W11: =ROUND(N11,2) -> 26.21 | X11: =ROUND(O11,2) -> 7.77 | AA11: G8 | AB11: =((C11+D11)/(C11+D11+E11+F11+G11))*100 -> 47.572816 | AC11: =ROUND(AB11,2) -> 47.57 | AF11: G6 | AG11: 67.96
A12: G9 | B12: G9 - Empathetic feedback process | C12: =COUNTIF('Guidelines - Data'!$I$3:$I$105,C3) -> 28 | D12: =COUNTIF('Guidelines - Data'!$I$3:$I$105,D3) -> 41 | E12: =COUNTIF('Guidelines - Data'!$I$3:$I$105,E3) -> 6 | F12: =COUNTIF('Guidelines - Data'!$I$3:$I$105,F3) -> 15 | G12: =COUNTIF('Guidelines - Data'!$I$3:$I$105,G3) -> 13 | J12: G9 | K12: =(C12/(C12+D12+E12+F12+G12))*100 -> 27.184466 | L12: =(D12/(C12+D12+E12+F12+G12))*100 -> 39.805825 | M12: =(E12/(C12+D12+E12+F12+G12))*100 -> 5.8252427 | N12: =(F12/(C12+D12+E12+F12+G12))*100 -> 14.563107 | O12: =(G12/(C12+D12+E12+F12+G12))*100 -> 12.621359 | S12: G9 | T12: =ROUND(K12,2) -> 27.18 | U12: =ROUND(L12,2) -> 39.81 | V12: =ROUND(M12,2) -> 5.83 | W12: =ROUND(N12,2) -> 14.56 | X12: =ROUND(O12,2) -> 12.62 | AA12: G9 | AB12: =((C12+D12)/(C12+D12+E12+F12+G12))*100 -> 66.990291 | AC12: =ROUND(AB12,2) -> 66.99 | AF12: G9 | AG12: 66.99
A13: G10 | B13: G10 - Creating a safe space | C13: =COUNTIF('Guidelines - Data'!$J$3:$J$105,C3) -> 43 | D13: =COUNTIF('Guidelines - Data'!$J$3:$J$105,D3) -> 29 | E13: =COUNTIF('Guidelines - Data'!$J$3:$J$105,E3) -> 4 | F13: =COUNTIF('Guidelines - Data'!$J$3:$J$105,F3) -> 15 | G13: =COUNTIF('Guidelines - Data'!$J$3:$J$105,G3) -> 12 | J13: G10 | K13: =(C13/(C13+D13+E13+F13+G13))*100 -> 41.747573 | L13: =(D13/(C13+D13+E13+F13+G13))*100 -> 28.15534 | M13: =(E13/(C13+D13+E13+F13+G13))*100 -> 3.8834951 | N13: =(F13/(C13+D13+E13+F13+G13))*100 -> 14.563107 | O13: =(G13/(C13+D13+E13+F13+G13))*100 -> 11.650485 | S13: G10 | T13: =ROUND(K13,2) -> 41.75 | U13: =ROUND(L13,2) -> 28.16 | V13: =ROUND(M13,2) -> 3.88 | W13: =ROUND(N13,2) -> 14.56 | X13: =ROUND(O13,2) -> 11.65 | AA13: G10 | AB13: =((C13+D13)/(C13+D13+E13+F13+G13))*100 -> 69.902913 | AC13: =ROUND(AB13,2) -> 69.9 | AF13: G7 | AG13: 65.05
A14: G11 | B14: G11 - Backup plans to manage unexpected outcomes | C14: =COUNTIF('Guidelines - Data'!$K$3:$K$105,C3) -> 42 | D14: =COUNTIF('Guidelines - Data'!$K$3:$K$105,D3) -> 32 | E14: =COUNTIF('Guidelines - Data'!$K$3:$K$105,E3) -> 9 | F14: =COUNTIF('Guidelines - Data'!$K$3:$K$105,F3) -> 9 | G14: =COUNTIF('Guidelines - Data'!$K$3:$K$105,G3) -> 11 | J14: G11 | K14: =(C14/(C14+D14+E14+F14+G14))*100 -> 40.776699 | L14: =(D14/(C14+D14+E14+F14+G14))*100 -> 31.067961 | M14: =(E14/(C14+D14+E14+F14+G14))*100 -> 8.7378641 | N14: =(F14/(C14+D14+E14+F14+G14))*100 -> 8.7378641 | O14: =(G14/(C14+D14+E14+F14+G14))*100 -> 10.679612 | S14: G11 | T14: =ROUND(K14,2) -> 40.78 | U14: =ROUND(L14,2) -> 31.07 | V14: =ROUND(M14,2) -> 8.74 | W14: =ROUND(N14,2) -> 8.74 | X14: =ROUND(O14,2) -> 10.68 | AA14: G11 | AB14: =((C14+D14)/(C14+D14+E14+F14+G14))*100 -> 71.84466 | AC14: =ROUND(AB14,2) -> 71.84 | AF14: G13 | AG14: 64.08
A15: G12 | B15: G12 - Flexibility in handling human issues | C15: =COUNTIF('Guidelines - Data'!$L$3:$L$105,C3) -> 27 | D15: =COUNTIF('Guidelines - Data'!$L$3:$L$105,D3) -> 43 | E15: =COUNTIF('Guidelines - Data'!$L$3:$L$105,E3) -> 7 | F15: =COUNTIF('Guidelines - Data'!$L$3:$L$105,F3) -> 14 | G15: =COUNTIF('Guidelines - Data'!$L$3:$L$105,G3) -> 12 | J15: G12 | K15: =(C15/(C15+D15+E15+F15+G15))*100 -> 26.213592 | L15: =(D15/(C15+D15+E15+F15+G15))*100 -> 41.747573 | M15: =(E15/(C15+D15+E15+F15+G15))*100 -> 6.7961165 | N15: =(F15/(C15+D15+E15+F15+G15))*100 -> 13.592233 | O15: =(G15/(C15+D15+E15+F15+G15))*100 -> 11.650485 | S15: G12 | T15: =ROUND(K15,2) -> 26.21 | U15: =ROUND(L15,2) -> 41.75 | V15: =ROUND(M15,2) -> 6.8 | W15: =ROUND(N15,2) -> 13.59 | X15: =ROUND(O15,2) -> 11.65 | AA15: G12 | AB15: =((C15+D15)/(C15+D15+E15+F15+G15))*100 -> 67.961165 | AC15: =ROUND(AB15,2) -> 67.96 | AF15: G11 | AG15: 55.34
A16: G13 | B16: G13 - Emphasising the real-world impact of developers’ work | C16: =COUNTIF('Guidelines - Data'!$M$3:$M$105,C3) -> 20 | D16: =COUNTIF('Guidelines - Data'!$M$3:$M$105,D3) -> 36 | E16: =COUNTIF('Guidelines - Data'!$M$3:$M$105,E3) -> 9 | F16: =COUNTIF('Guidelines - Data'!$M$3:$M$105,F3) -> 24 | G16: =COUNTIF('Guidelines - Data'!$M$3:$M$105,G3) -> 14 | J16: G13 | K16: =(C16/(C16+D16+E16+F16+G16))*100 -> 19.417476 | L16: =(D16/(C16+D16+E16+F16+G16))*100 -> 34.951456 | M16: =(E16/(C16+D16+E16+F16+G16))*100 -> 8.7378641 | N16: =(F16/(C16+D16+E16+F16+G16))*100 -> 23.300971 | O16: =(G16/(C16+D16+E16+F16+G16))*100 -> 13.592233 | S16: G13 | T16: =ROUND(K16,2) -> 19.42 | U16: =ROUND(L16,2) -> 34.95 | V16: =ROUND(M16,2) -> 8.74 | W16: =ROUND(N16,2) -> 23.3 | X16: =ROUND(O16,2) -> 13.59 | AA16: G13 | AB16: =((C16+D16)/(C16+D16+E16+F16+G16))*100 -> 54.368932 | AC16: =ROUND(AB16,2) -> 54.37 | AF16: G17 | AG16: 55.34
A17: G14 | B17: G14 - Building an empathetic team and company culture | C17: =COUNTIF('Guidelines - Data'!$N$3:$N$105,C3) -> 32 | D17: =COUNTIF('Guidelines - Data'!$N$3:$N$105,D3) -> 34 | E17: =COUNTIF('Guidelines - Data'!$N$3:$N$105,E3) -> 9 | F17: =COUNTIF('Guidelines - Data'!$N$3:$N$105,F3) -> 17 | G17: =COUNTIF('Guidelines - Data'!$N$3:$N$105,G3) -> 11 | J17: G14 | K17: =(C17/(C17+D17+E17+F17+G17))*100 -> 31.067961 | L17: =(D17/(C17+D17+E17+F17+G17))*100 -> 33.009709 | M17: =(E17/(C17+D17+E17+F17+G17))*100 -> 8.7378641 | N17: =(F17/(C17+D17+E17+F17+G17))*100 -> 16.504854 | O17: =(G17/(C17+D17+E17+F17+G17))*100 -> 10.679612 | S17: G14 | T17: =ROUND(K17,2) -> 31.07 | U17: =ROUND(L17,2) -> 33.01 | V17: =ROUND(M17,2) -> 8.74 | W17: =ROUND(N17,2) -> 16.5 | X17: =ROUND(O17,2) -> 10.68 | AA17: G14 | AB17: =((C17+D17)/(C17+D17+E17+F17+G17))*100 -> 64.07767 | AC17: =ROUND(AB17,2) -> 64.08 | AF17: G15 | AG17: 54.37
A18: G15 | B18: G15 - Empathy education and training | C18: =COUNTIF('Guidelines - Data'!$O$3:$O$105,C3) -> 21 | D18: =COUNTIF('Guidelines - Data'!$O$3:$O$105,D3) -> 36 | E18: =COUNTIF('Guidelines - Data'!$O$3:$O$105,E3) -> 11 | F18: =COUNTIF('Guidelines - Data'!$O$3:$O$105,F3) -> 22 | G18: =COUNTIF('Guidelines - Data'!$O$3:$O$105,G3) -> 13 | J18: G15 | K18: =(C18/(C18+D18+E18+F18+G18))*100 -> 20.38835 | L18: =(D18/(C18+D18+E18+F18+G18))*100 -> 34.951456 | M18: =(E18/(C18+D18+E18+F18+G18))*100 -> 10.679612 | N18: =(F18/(C18+D18+E18+F18+G18))*100 -> 21.359223 | O18: =(G18/(C18+D18+E18+F18+G18))*100 -> 12.621359 | S18: G15 | T18: =ROUND(K18,2) -> 20.39 | U18: =ROUND(L18,2) -> 34.95 | V18: =ROUND(M18,2) -> 10.68 | W18: =ROUND(N18,2) -> 21.36 | X18: =ROUND(O18,2) -> 12.62 | AA18: G15 | AB18: =((C18+D18)/(C18+D18+E18+F18+G18))*100 -> 55.339806 | AC18: =ROUND(AB18,2) -> 55.34 | AF18: G16 | AG18: 54.37
A19: G16 | B19: G16 - DEI policies | C19: =COUNTIF('Guidelines - Data'!$P$3:$P$105,C3) -> 21 | D19: =COUNTIF('Guidelines - Data'!$P$3:$P$105,D3) -> 28 | E19: =COUNTIF('Guidelines - Data'!$P$3:$P$105,E3) -> 20 | F19: =COUNTIF('Guidelines - Data'!$P$3:$P$105,F3) -> 18 | G19: =COUNTIF('Guidelines - Data'!$P$3:$P$105,G3) -> 16 | J19: G16 | K19: =(C19/(C19+D19+E19+F19+G19))*100 -> 20.38835 | L19: =(D19/(C19+D19+E19+F19+G19))*100 -> 27.184466 | M19: =(E19/(C19+D19+E19+F19+G19))*100 -> 19.417476 | N19: =(F19/(C19+D19+E19+F19+G19))*100 -> 17.475728 | O19: =(G19/(C19+D19+E19+F19+G19))*100 -> 15.533981 | S19: G16 | T19: =ROUND(K19,2) -> 20.39 | U19: =ROUND(L19,2) -> 27.18 | V19: =ROUND(M19,2) -> 19.42 | W19: =ROUND(N19,2) -> 17.48 | X19: =ROUND(O19,2) -> 15.53 | AA19: G16 | AB19: =((C19+D19)/(C19+D19+E19+F19+G19))*100 -> 47.572816 | AC19: =ROUND(AB19,2) -> 47.57 | AF19: G12 | AG19: 47.57
A20: G17 | B20: G17 - Managing empathy fatigue | C20: =COUNTIF('Guidelines - Data'!$Q$3:$Q$105,C3) -> 22 | D20: =COUNTIF('Guidelines - Data'!$Q$3:$Q$105,D3) -> 34 | E20: =COUNTIF('Guidelines - Data'!$Q$3:$Q$105,E3) -> 7 | F20: =COUNTIF('Guidelines - Data'!$Q$3:$Q$105,F3) -> 30 | G20: =COUNTIF('Guidelines - Data'!$Q$3:$Q$105,G3) -> 10 | J20: G17 | K20: =(C20/(C20+D20+E20+F20+G20))*100 -> 21.359223 | L20: =(D20/(C20+D20+E20+F20+G20))*100 -> 33.009709 | M20: =(E20/(C20+D20+E20+F20+G20))*100 -> 6.7961165 | N20: =(F20/(C20+D20+E20+F20+G20))*100 -> 29.126214 | O20: =(G20/(C20+D20+E20+F20+G20))*100 -> 9.7087379 | S20: G17 | T20: =ROUND(K20,2) -> 21.36 | U20: =ROUND(L20,2) -> 33.01 | V20: =ROUND(M20,2) -> 6.8 | W20: =ROUND(N20,2) -> 29.13 | X20: =ROUND(O20,2) -> 9.71 | AA20: G17 | AB20: =((C20+D20)/(C20+D20+E20+F20+G20))*100 -> 54.368932 | AC20: =ROUND(AB20,2) -> 54.37 | AF20: G8 | AG20: 47.57
B25: How practical and easy are our proposed guidelines to implement in real industry settings | J25: Perceived Ease of Implementation%
C26: Very Easy | D26: Easy | E26: Neither difficult nor easy | F26: Difficult | G26: Very Difficult | H26: N/A | K26: Very Easy | L26: Easy | M26: Neither difficult nor easy | N26: Difficult | O26: Very Difficult | T26: Very Easy | U26: Easy | V26: Neither difficult nor easy | W26: Difficult | X26: Very Difficult | AC26: Perceived Ease of Implementation% | AG26: Sorted Perceived Ease of Implementation%
A27: G1 | B27: G1 - Fostering strong relationships among stakeholders | C27: =COUNTIF('Guidelines - Data'!$S$3:$S$105,C26) -> 7 | D27: =COUNTIF('Guidelines - Data'!$S$3:$S$105,D26) -> 31 | E27: =COUNTIF('Guidelines - Data'!$S$3:$S$105,E26) -> 11 | F27: =COUNTIF('Guidelines - Data'!$S$3:$S$105,F26) -> 37 | G27: =COUNTIF('Guidelines - Data'!$S$3:$S$105,G26) -> 17 | H27: =COUNTIF('Guidelines - Data'!$S$3:$S$105,H26) -> 0 | J27: G1 | K27: =(C27/(C27+D27+E27+F27+G27))*100 -> 6.7961165 | L27: =(D27/(C27+D27+E27+F27+G27))*100 -> 30.097087 | M27: =(E27/(C27+D27+E27+F27+G27))*100 -> 10.679612 | N27: =(F27/(C27+D27+E27+F27+G27))*100 -> 35.92233 | O27: =(G27/(C27+D27+E27+F27+G27))*100 -> 16.504854 | S27: G1 | T27: =ROUND(K27,2) -> 6.8 | U27: =ROUND(L27,2) -> 30.1 | V27: =ROUND(M27,2) -> 10.68 | W27: =ROUND(N27,2) -> 35.92 | X27: =ROUND(O27,2) -> 16.5 | AA27: G1 | AB27: =((C27+D27)/(C27+D27+E27+F27+G27))*100 -> 36.893204 | AC27: =ROUND(AB27,2) -> 36.89 | AF27: G10 | AG27: 63.73
A28: G2 | B28: G2 - Bridging the technical and non-technical gap | C28: =COUNTIF('Guidelines - Data'!$T$3:$T$105,C26) -> 6 | D28: =COUNTIF('Guidelines - Data'!$T$3:$T$105,D26) -> 29 | E28: =COUNTIF('Guidelines - Data'!$T$3:$T$105,E26) -> 19 | F28: =COUNTIF('Guidelines - Data'!$T$3:$T$105,F26) -> 29 | G28: =COUNTIF('Guidelines - Data'!$T$3:$T$105,G26) -> 20 | H28: =COUNTIF('Guidelines - Data'!$T$3:$T$105,H26) -> 0 | J28: G2 | K28: =(C28/(C28+D28+E28+F28+G28))*100 -> 5.8252427 | L28: =(D28/(C28+D28+E28+F28+G28))*100 -> 28.15534 | M28: =(E28/(C28+D28+E28+F28+G28))*100 -> 18.446602 | N28: =(F28/(C28+D28+E28+F28+G28))*100 -> 28.15534 | O28: =(G28/(C28+D28+E28+F28+G28))*100 -> 19.417476 | S28: G2 | T28: =ROUND(K28,2) -> 5.83 | U28: =ROUND(L28,2) -> 28.16 | V28: =ROUND(M28,2) -> 18.45 | W28: =ROUND(N28,2) -> 28.16 | X28: =ROUND(O28,2) -> 19.42 | AA28: G2 | AB28: =((C28+D28)/(C28+D28+E28+F28+G28))*100 -> 33.980583 | AC28: =ROUND(AB28,2) -> 33.98 | AF28: G5 | AG28: 59.22
A29: G3 | B29: G3 - Reducing friction among different stakeholder groups | C29: =COUNTIF('Guidelines - Data'!$U$3:$U$105,C26) -> 4 | D29: =COUNTIF('Guidelines - Data'!$U$3:$U$105,D26) -> 22 | E29: =COUNTIF('Guidelines - Data'!$U$3:$U$105,E26) -> 19 | F29: =COUNTIF('Guidelines - Data'!$U$3:$U$105,F26) -> 38 | G29: =COUNTIF('Guidelines - Data'!$U$3:$U$105,G26) -> 20 | H29: =COUNTIF('Guidelines - Data'!$U$3:$U$105,H26) -> 0 | J29: G3 | K29: =(C29/(C29+D29+E29+F29+G29))*100 -> 3.8834951 | L29: =(D29/(C29+D29+E29+F29+G29))*100 -> 21.359223 | M29: =(E29/(C29+D29+E29+F29+G29))*100 -> 18.446602 | N29: =(F29/(C29+D29+E29+F29+G29))*100 -> 36.893204 | O29: =(G29/(C29+D29+E29+F29+G29))*100 -> 19.417476 | S29: G3 | T29: =ROUND(K29,2) -> 3.88 | U29: =ROUND(L29,2) -> 21.36 | V29: =ROUND(M29,2) -> 18.45 | W29: =ROUND(N29,2) -> 36.89 | X29: =ROUND(O29,2) -> 19.42 | AA29: G3 | AB29: =((C29+D29)/(C29+D29+E29+F29+G29))*100 -> 25.242718 | AC29: =ROUND(AB29,2) -> 25.24 | AF29: G9 | AG29: 57.84
A30: G4 | B30: G4 - Encouraging bi-directional communication | C30: =COUNTIF('Guidelines - Data'!$V$3:$V$105,C26) -> 6 | D30: =COUNTIF('Guidelines - Data'!$V$3:$V$105,D26) -> 47 | E30: =COUNTIF('Guidelines - Data'!$V$3:$V$105,E26) -> 16 | F30: =COUNTIF('Guidelines - Data'!$V$3:$V$105,F26) -> 26 | G30: =COUNTIF('Guidelines - Data'!$V$3:$V$105,G26) -> 8 | H30: =COUNTIF('Guidelines - Data'!$V$3:$V$105,H26) -> 0 | J30: G4 | K30: =(C30/(C30+D30+E30+F30+G30))*100 -> 5.8252427 | L30: =(D30/(C30+D30+E30+F30+G30))*100 -> 45.631068 | M30: =(E30/(C30+D30+E30+F30+G30))*100 -> 15.533981 | N30: =(F30/(C30+D30+E30+F30+G30))*100 -> 25.242718 | O30: =(G30/(C30+D30+E30+F30+G30))*100 -> 7.7669903 | S30: G4 | T30: =ROUND(K30,2) -> 5.83 | U30: =ROUND(L30,2) -> 45.63 | V30: =ROUND(M30,2) -> 15.53 | W30: =ROUND(N30,2) -> 25.24 | X30: =ROUND(O30,2) -> 7.77 | AA30: G4 | AB30: =((C30+D30)/(C30+D30+E30+F30+G30))*100 -> 51.456311 | AC30: =ROUND(AB30,2) -> 51.46 | AF30: G4 | AG30: 51.46
A31: G5 | B31: G5 - Ensuring transparency about business goals | C31: =COUNTIF('Guidelines - Data'!$W$3:$W$105,C26) -> 12 | D31: =COUNTIF('Guidelines - Data'!$W$3:$W$105,D26) -> 49 | E31: =COUNTIF('Guidelines - Data'!$W$3:$W$105,E26) -> 9 | F31: =COUNTIF('Guidelines - Data'!$W$3:$W$105,F26) -> 18 | G31: =COUNTIF('Guidelines - Data'!$W$3:$W$105,G26) -> 15 | H31: =COUNTIF('Guidelines - Data'!$W$3:$W$105,H26) -> 0 | J31: G5 | K31: =(C31/(C31+D31+E31+F31+G31))*100 -> 11.650485 | L31: =(D31/(C31+D31+E31+F31+G31))*100 -> 47.572816 | M31: =(E31/(C31+D31+E31+F31+G31))*100 -> 8.7378641 | N31: =(F31/(C31+D31+E31+F31+G31))*100 -> 17.475728 | O31: =(G31/(C31+D31+E31+F31+G31))*100 -> 14.563107 | S31: G5 | T31: =ROUND(K31,2) -> 11.65 | U31: =ROUND(L31,2) -> 47.57 | V31: =ROUND(M31,2) -> 8.74 | W31: =ROUND(N31,2) -> 17.48 | X31: =ROUND(O31,2) -> 14.56 | AA31: G5 | AB31: =((C31+D31)/(C31+D31+E31+F31+G31))*100 -> 59.223301 | AC31: =ROUND(AB31,2) -> 59.22 | AF31: G8 | AG31: 49.51
A32: G6 | B32: G6 - Use an empathetic approach to improve RE processes | C32: =COUNTIF('Guidelines - Data'!$X$3:$X$105,C26) -> 8 | D32: =COUNTIF('Guidelines - Data'!$X$3:$X$105,D26) -> 40 | E32: =COUNTIF('Guidelines - Data'!$X$3:$X$105,E26) -> 18 | F32: =COUNTIF('Guidelines - Data'!$X$3:$X$105,F26) -> 30 | G32: =COUNTIF('Guidelines - Data'!$X$3:$X$105,G26) -> 7 | H32: =COUNTIF('Guidelines - Data'!$X$3:$X$105,H26) -> 0 | J32: G6 | K32: =(C32/(C32+D32+E32+F32+G32))*100 -> 7.7669903 | L32: =(D32/(C32+D32+E32+F32+G32))*100 -> 38.834951 | M32: =(E32/(C32+D32+E32+F32+G32))*100 -> 17.475728 | N32: =(F32/(C32+D32+E32+F32+G32))*100 -> 29.126214 | O32: =(G32/(C32+D32+E32+F32+G32))*100 -> 6.7961165 | S32: G6 | T32: =ROUND(K32,2) -> 7.77 | U32: =ROUND(L32,2) -> 38.83 | V32: =ROUND(M32,2) -> 17.48 | W32: =ROUND(N32,2) -> 29.13 | X32: =ROUND(O32,2) -> 6.8 | AA32: G6 | AB32: =((C32+D32)/(C32+D32+E32+F32+G32))*100 -> 46.601942 | AC32: =ROUND(AB32,2) -> 46.6 | AF32: G15 | AG32: 49.5
A33: G7 | B33: G7 - Collaborative problem solving | C33: =COUNTIF('Guidelines - Data'!$Y$3:$Y$105,C26) -> 12 | D33: =COUNTIF('Guidelines - Data'!$Y$3:$Y$105,D26) -> 37 | E33: =COUNTIF('Guidelines - Data'!$Y$3:$Y$105,E26) -> 12 | F33: =COUNTIF('Guidelines - Data'!$Y$3:$Y$105,F26) -> 28 | G33: =COUNTIF('Guidelines - Data'!$Y$3:$Y$105,G26) -> 14 | H33: =COUNTIF('Guidelines - Data'!$Y$3:$Y$105,H26) -> 0 | J33: G7 | K33: =(C33/(C33+D33+E33+F33+G33))*100 -> 11.650485 | L33: =(D33/(C33+D33+E33+F33+G33))*100 -> 35.92233 | M33: =(E33/(C33+D33+E33+F33+G33))*100 -> 11.650485 | N33: =(F33/(C33+D33+E33+F33+G33))*100 -> 27.184466 | O33: =(G33/(C33+D33+E33+F33+G33))*100 -> 13.592233 | S33: G7 | T33: =ROUND(K33,2) -> 11.65 | U33: =ROUND(L33,2) -> 35.92 | V33: =ROUND(M33,2) -> 11.65 | W33: =ROUND(N33,2) -> 27.18 | X33: =ROUND(O33,2) -> 13.59 | AA33: G7 | AB33: =((C33+D33)/(C33+D33+E33+F33+G33))*100 -> 47.572816 | AC33: =ROUND(AB33,2) -> 47.57 | AF33: G7 | AG33: 47.57
A34: G8 | B34: G8 - Empathy during agile ceremonies | C34: =COUNTIF('Guidelines - Data'!$Z$3:$Z$105,C26) -> 11 | D34: =COUNTIF('Guidelines - Data'!$Z$3:$Z$105,D26) -> 40 | E34: =COUNTIF('Guidelines - Data'!$Z$3:$Z$105,E26) -> 19 | F34: =COUNTIF('Guidelines - Data'!$Z$3:$Z$105,F26) -> 27 | G34: =COUNTIF('Guidelines - Data'!$Z$3:$Z$105,G26) -> 6 | H34: =COUNTIF('Guidelines - Data'!$Z$3:$Z$105,H26) -> 0 | J34: G8 | K34: =(C34/(C34+D34+E34+F34+G34))*100 -> 10.679612 | L34: =(D34/(C34+D34+E34+F34+G34))*100 -> 38.834951 | M34: =(E34/(C34+D34+E34+F34+G34))*100 -> 18.446602 | N34: =(F34/(C34+D34+E34+F34+G34))*100 -> 26.213592 | O34: =(G34/(C34+D34+E34+F34+G34))*100 -> 5.8252427 | S34: G8 | T34: =ROUND(K34,2) -> 10.68 | U34: =ROUND(L34,2) -> 38.83 | V34: =ROUND(M34,2) -> 18.45 | W34: =ROUND(N34,2) -> 26.21 | X34: =ROUND(O34,2) -> 5.83 | AA34: G8 | AB34: =((C34+D34)/(C34+D34+E34+F34+G34))*100 -> 49.514563 | AC34: =ROUND(AB34,2) -> 49.51 | AF34: G6 | AG34: 46.6
A35: G9 | B35: G9 - Empathetic feedback process | C35: =COUNTIF('Guidelines - Data'!$AA$3:$AA$105,C26) -> 11 | D35: =COUNTIF('Guidelines - Data'!$AA$3:$AA$105,D26) -> 48 | E35: =COUNTIF('Guidelines - Data'!$AA$3:$AA$105,E26) -> 16 | F35: =COUNTIF('Guidelines - Data'!$AA$3:$AA$105,F26) -> 19 | G35: =COUNTIF('Guidelines - Data'!$AA$3:$AA$105,G26) -> 8 | H35: =COUNTIF('Guidelines - Data'!$AA$3:$AA$105,H26) -> 1 | J35: G9 | K35: =(C35/(C35+D35+E35+F35+G35))*100 -> 10.784314 | L35: =(D35/(C35+D35+E35+F35+G35))*100 -> 47.058824 | M35: =(E35/(C35+D35+E35+F35+G35))*100 -> 15.686275 | N35: =(F35/(C35+D35+E35+F35+G35))*100 -> 18.627451 | O35: =(G35/(C35+D35+E35+F35+G35))*100 -> 7.8431373 | S35: G9 | T35: =ROUND(K35,2) -> 10.78 | U35: =ROUND(L35,2) -> 47.06 | V35: =ROUND(M35,2) -> 15.69 | W35: =ROUND(N35,2) -> 18.63 | X35: =ROUND(O35,2) -> 7.84 | AA35: G9 | AB35: =((C35+D35)/(C35+D35+E35+F35+G35))*100 -> 57.843137 | AC35: =ROUND(AB35,2) -> 57.84 | AF35: G12 | AG35: 45.63
A36: G10 | B36: G10 - Creating a safe space | C36: =COUNTIF('Guidelines - Data'!$AB$3:$AB$105,C26) -> 17 | D36: =COUNTIF('Guidelines - Data'!$AB$3:$AB$105,D26) -> 48 | E36: =COUNTIF('Guidelines - Data'!$AB$3:$AB$105,E26) -> 9 | F36: =COUNTIF('Guidelines - Data'!$AB$3:$AB$105,F26) -> 20 | G36: =COUNTIF('Guidelines - Data'!$AB$3:$AB$105,G26) -> 8 | H36: =COUNTIF('Guidelines - Data'!$AB$3:$AB$105,H26) -> 1 | J36: G10 | K36: =(C36/(C36+D36+E36+F36+G36))*100 -> 16.666667 | L36: =(D36/(C36+D36+E36+F36+G36))*100 -> 47.058824 | M36: =(E36/(C36+D36+E36+F36+G36))*100 -> 8.8235294 | N36: =(F36/(C36+D36+E36+F36+G36))*100 -> 19.607843 | O36: =(G36/(C36+D36+E36+F36+G36))*100 -> 7.8431373 | S36: G10 | T36: =ROUND(K36,2) -> 16.67 | U36: =ROUND(L36,2) -> 47.06 | V36: =ROUND(M36,2) -> 8.82 | W36: =ROUND(N36,2) -> 19.61 | X36: =ROUND(O36,2) -> 7.84 | AA36: G10 | AB36: =((C36+D36)/(C36+D36+E36+F36+G36))*100 -> 63.72549 | AC36: =ROUND(AB36,2) -> 63.73 | AF36: G13 | AG36: 44.12
A37: G11 | B37: G11 - Backup plans to manage unexpected outcomes | C37: =COUNTIF('Guidelines - Data'!$AC$3:$AC$105,C26) -> 11 | D37: =COUNTIF('Guidelines - Data'!$AC$3:$AC$105,D26) -> 23 | E37: =COUNTIF('Guidelines - Data'!$AC$3:$AC$105,E26) -> 17 | F37: =COUNTIF('Guidelines - Data'!$AC$3:$AC$105,F26) -> 23 | G37: =COUNTIF('Guidelines - Data'!$AC$3:$AC$105,G26) -> 29 | H37: =COUNTIF('Guidelines - Data'!$AC$3:$AC$105,H26) -> 0 | J37: G11 | K37: =(C37/(C37+D37+E37+F37+G37))*100 -> 10.679612 | L37: =(D37/(C37+D37+E37+F37+G37))*100 -> 22.330097 | M37: =(E37/(C37+D37+E37+F37+G37))*100 -> 16.504854 | N37: =(F37/(C37+D37+E37+F37+G37))*100 -> 22.330097 | O37: =(G37/(C37+D37+E37+F37+G37))*100 -> 28.15534 | S37: G11 | T37: =ROUND(K37,2) -> 10.68 | U37: =ROUND(L37,2) -> 22.33 | V37: =ROUND(M37,2) -> 16.5 | W37: =ROUND(N37,2) -> 22.33 | X37: =ROUND(O37,2) -> 28.16 | AA37: G11 | AB37: =((C37+D37)/(C37+D37+E37+F37+G37))*100 -> 33.009709 | AC37: =ROUND(AB37,2) -> 33.01 | AF37: G16 | AG37: 44
A38: G12 | B38: G12 - Flexibility in handling human issues | C38: =COUNTIF('Guidelines - Data'!$AD$3:$AD$105,C26) -> 10 | D38: =COUNTIF('Guidelines - Data'!$AD$3:$AD$105,D26) -> 37 | E38: =COUNTIF('Guidelines - Data'!$AD$3:$AD$105,E26) -> 10 | F38: =COUNTIF('Guidelines - Data'!$AD$3:$AD$105,F26) -> 31 | G38: =COUNTIF('Guidelines - Data'!$AD$3:$AD$105,G26) -> 15 | H38: =COUNTIF('Guidelines - Data'!$AD$3:$AD$105,H26) -> 0 | J38: G12 | K38: =(C38/(C38+D38+E38+F38+G38))*100 -> 9.7087379 | L38: =(D38/(C38+D38+E38+F38+G38))*100 -> 35.92233 | M38: =(E38/(C38+D38+E38+F38+G38))*100 -> 9.7087379 | N38: =(F38/(C38+D38+E38+F38+G38))*100 -> 30.097087 | O38: =(G38/(C38+D38+E38+F38+G38))*100 -> 14.563107 | S38: G12 | T38: =ROUND(K38,2) -> 9.71 | U38: =ROUND(L38,2) -> 35.92 | V38: =ROUND(M38,2) -> 9.71 | W38: =ROUND(N38,2) -> 30.1 | X38: =ROUND(O38,2) -> 14.56 | AA38: G12 | AB38: =((C38+D38)/(C38+D38+E38+F38+G38))*100 -> 45.631068 | AC38: =ROUND(AB38,2) -> 45.63 | AF38: G1 | AG38: 36.89
A39: G13 | B39: G13 - Emphasising the real-world impact of developers’ work | C39: =COUNTIF('Guidelines - Data'!$AE$3:$AE$105,C26) -> 8 | D39: =COUNTIF('Guidelines - Data'!$AE$3:$AE$105,D26) -> 37 | E39: =COUNTIF('Guidelines - Data'!$AE$3:$AE$105,E26) -> 21 | F39: =COUNTIF('Guidelines - Data'!$AE$3:$AE$105,F26) -> 24 | G39: =COUNTIF('Guidelines - Data'!$AE$3:$AE$105,G26) -> 12 | H39: =COUNTIF('Guidelines - Data'!$AE$3:$AE$105,H26) -> 1 | J39: G13 | K39: =(C39/(C39+D39+E39+F39+G39))*100 -> 7.8431373 | L39: =(D39/(C39+D39+E39+F39+G39))*100 -> 36.27451 | M39: =(E39/(C39+D39+E39+F39+G39))*100 -> 20.588235 | N39: =(F39/(C39+D39+E39+F39+G39))*100 -> 23.529412 | O39: =(G39/(C39+D39+E39+F39+G39))*100 -> 11.764706 | S39: G13 | T39: =ROUND(K39,2) -> 7.84 | U39: =ROUND(L39,2) -> 36.27 | V39: =ROUND(M39,2) -> 20.59 | W39: =ROUND(N39,2) -> 23.53 | X39: =ROUND(O39,2) -> 11.76 | AA39: G13 | AB39: =((C39+D39)/(C39+D39+E39+F39+G39))*100 -> 44.117647 | AC39: =ROUND(AB39,2) -> 44.12 | AF39: G2 | AG39: 33.98
A40: G14 | B40: G14 - Building an empathetic team and company culture | C40: =COUNTIF('Guidelines - Data'!$AF$3:$AF$105,C26) -> 3 | D40: =COUNTIF('Guidelines - Data'!$AF$3:$AF$105,D26) -> 27 | E40: =COUNTIF('Guidelines - Data'!$AF$3:$AF$105,E26) -> 21 | F40: =COUNTIF('Guidelines - Data'!$AF$3:$AF$105,F26) -> 35 | G40: =COUNTIF('Guidelines - Data'!$AF$3:$AF$105,G26) -> 16 | H40: =COUNTIF('Guidelines - Data'!$AF$3:$AF$105,H26) -> 1 | J40: G14 | K40: =(C40/(C40+D40+E40+F40+G40))*100 -> 2.9411765 | L40: =(D40/(C40+D40+E40+F40+G40))*100 -> 26.470588 | M40: =(E40/(C40+D40+E40+F40+G40))*100 -> 20.588235 | N40: =(F40/(C40+D40+E40+F40+G40))*100 -> 34.313725 | O40: =(G40/(C40+D40+E40+F40+G40))*100 -> 15.686275 | S40: G14 | T40: =ROUND(K40,2) -> 2.94 | U40: =ROUND(L40,2) -> 26.47 | V40: =ROUND(M40,2) -> 20.59 | W40: =ROUND(N40,2) -> 34.31 | X40: =ROUND(O40,2) -> 15.69 | AA40: G14 | AB40: =((C40+D40)/(C40+D40+E40+F40+G40))*100 -> 29.411765 | AC40: =ROUND(AB40,2) -> 29.41 | AF40: G11 | AG40: 33.01
A41: G15 | B41: G15 - Empathy education and training | C41: =COUNTIF('Guidelines - Data'!$AG$3:$AG$105,C26) -> 8 | D41: =COUNTIF('Guidelines - Data'!$AG$3:$AG$105,D26) -> 42 | E41: =COUNTIF('Guidelines - Data'!$AG$3:$AG$105,E26) -> 17 | F41: =COUNTIF('Guidelines - Data'!$AG$3:$AG$105,F26) -> 24 | G41: =COUNTIF('Guidelines - Data'!$AG$3:$AG$105,G26) -> 10 | H41: =COUNTIF('Guidelines - Data'!$AG$3:$AG$105,H26) -> 2 | J41: G15 | K41: =(C41/(C41+D41+E41+F41+G41))*100 -> 7.9207921 | L41: =(D41/(C41+D41+E41+F41+G41))*100 -> 41.584158 | M41: =(E41/(C41+D41+E41+F41+G41))*100 -> 16.831683 | N41: =(F41/(C41+D41+E41+F41+G41))*100 -> 23.762376 | O41: =(G41/(C41+D41+E41+F41+G41))*100 -> 9.9009901 | S41: G15 | T41: =ROUND(K41,2) -> 7.92 | U41: =ROUND(L41,2) -> 41.58 | V41: =ROUND(M41,2) -> 16.83 | W41: =ROUND(N41,2) -> 23.76 | X41: =ROUND(O41,2) -> 9.9 | AA41: G15 | AB41: =((C41+D41)/(C41+D41+E41+F41+G41))*100 -> 49.50495 | AC41: =ROUND(AB41,2) -> 49.5 | AF41: G14 | AG41: 29.41
A42: G16 | B42: G16 - DEI policies | C42: =COUNTIF('Guidelines - Data'!$AH$3:$AH$105,C26) -> 9 | D42: =COUNTIF('Guidelines - Data'!$AH$3:$AH$105,D26) -> 35 | E42: =COUNTIF('Guidelines - Data'!$AH$3:$AH$105,E26) -> 18 | F42: =COUNTIF('Guidelines - Data'!$AH$3:$AH$105,F26) -> 23 | G42: =COUNTIF('Guidelines - Data'!$AH$3:$AH$105,G26) -> 15 | H42: =COUNTIF('Guidelines - Data'!$AH$3:$AH$105,H26) -> 3 | J42: G16 | K42: =(C42/(C42+D42+E42+F42+G42))*100 -> 9 | L42: =(D42/(C42+D42+E42+F42+G42))*100 -> 35 | M42: =(E42/(C42+D42+E42+F42+G42))*100 -> 18 | N42: =(F42/(C42+D42+E42+F42+G42))*100 -> 23 | O42: =(G42/(C42+D42+E42+F42+G42))*100 -> 15 | S42: G16 | T42: =ROUND(K42,2) -> 9 | U42: =ROUND(L42,2) -> 35 | V42: =ROUND(M42,2) -> 18 | W42: =ROUND(N42,2) -> 23 | X42: =ROUND(O42,2) -> 15 | AA42: G16 | AB42: =((C42+D42)/(C42+D42+E42+F42+G42))*100 -> 44 | AC42: =ROUND(AB42,2) -> 44 | AF42: G17 | AG42: 26
A43: G17 | B43: G17 - Managing empathy fatigue | C43: =COUNTIF('Guidelines - Data'!$AI$3:$AI$105,C26) -> 6 | D43: =COUNTIF('Guidelines - Data'!$AI$3:$AI$105,D26) -> 20 | E43: =COUNTIF('Guidelines - Data'!$AI$3:$AI$105,E26) -> 16 | F43: =COUNTIF('Guidelines - Data'!$AI$3:$AI$105,F26) -> 45 | G43: =COUNTIF('Guidelines - Data'!$AI$3:$AI$105,G26) -> 13 | H43: =COUNTIF('Guidelines - Data'!$AI$3:$AI$105,H26) -> 3 | J43: G17 | K43: =(C43/(C43+D43+E43+F43+G43))*100 -> 6 | L43: =(D43/(C43+D43+E43+F43+G43))*100 -> 20 | M43: =(E43/(C43+D43+E43+F43+G43))*100 -> 16 | N43: =(F43/(C43+D43+E43+F43+G43))*100 -> 45 | O43: =(G43/(C43+D43+E43+F43+G43))*100 -> 13 | S43: G17 | T43: =ROUND(K43,2) -> 6 | U43: =ROUND(L43,2) -> 20 | V43: =ROUND(M43,2) -> 16 | W43: =ROUND(N43,2) -> 45 | X43: =ROUND(O43,2) -> 13 | AA43: G17 | AB43: =((C43+D43)/(C43+D43+E43+F43+G43))*100 -> 26 | AC43: =ROUND(AB43,2) -> 26 | AF43: G3 | AG43: 25.24
B51: Would you consider using our proposed guidelines to enhance empathy in your software engineering practice | J51: Willingness to Adopt %
C52: I am currently using it | D52: I will definitely use it | E52: I am likely to regularly use it | F52: I might occasionally use it | G52: I am unlikely to use it | H52: I will never use it | K52: I am currently using it | L52: I will definitely use it | M52: I am likely to regularly use it | N52: I might occasionally use it | O52: I am unlikely to use it | P52: I will never use it | T52: I am currently using it | U52: I will definitely use it | V52: I am likely to regularly use it | W52: I might occasionally use it | X52: I am unlikely to use it | Y52: I will never use it | AC52: Willingness to Adopt % | AG52: Sorted Willingness to Adopt %
A53: G1 | B53: G1 - Fostering strong relationships among stakeholders | C53: =COUNTIF('Guidelines - Data'!$AK$3:$AK$105,C52) -> 34 | D53: =COUNTIF('Guidelines - Data'!$AK$3:$AK$105,D52) -> 28 | E53: =COUNTIF('Guidelines - Data'!$AK$3:$AK$105,E52) -> 27 | F53: =COUNTIF('Guidelines - Data'!$AK$3:$AK$105,F52) -> 10 | G53: =COUNTIF('Guidelines - Data'!$AK$3:$AK$105,G52) -> 3 | H53: =COUNTIF('Guidelines - Data'!$AK$3:$AK$105,H52) -> 1 | J53: G1 | K53: =(C53/(C53+D53+E53+F53+G53+H53))*100 -> 33.009709 | L53: =(D53/(C53+D53+E53+F53+G53+H53))*100 -> 27.184466 | M53: =(E53/(C53+D53+E53+F53+G53+H53))*100 -> 26.213592 | N53: =(F53/(C53+D53+E53+F53+G53+H53))*100 -> 9.7087379 | O53: =(G53/(C53+D53+E53+F53+G53+H53))*100 -> 2.9126214 | P53: =(H53/(C53+D53+E53+F53+G53+H53))*100 -> 0.97087379 | S53: G1 | T53: =ROUND(K53,2) -> 33.01 | U53: =ROUND(L53,2) -> 27.18 | V53: =ROUND(M53,2) -> 26.21 | W53: =ROUND(N53,2) -> 9.71 | X53: =ROUND(O53,2) -> 2.91 | Y53: =ROUND(P53,2) -> 0.97 | AA53: G1 | AB53: =((C53+D53+E53)/(C53+D53+E53+F53+G53+H53))*100 -> 86.407767 | AC53: =ROUND(AB53,2) -> 86.41 | AF53: G7 | AG53: 93.2
A54: G2 | B54: G2 - Bridging the technical and non-technical gap | C54: =COUNTIF('Guidelines - Data'!$AL$3:$AL$105,C52) -> 42 | D54: =COUNTIF('Guidelines - Data'!$AL$3:$AL$105,D52) -> 27 | E54: =COUNTIF('Guidelines - Data'!$AL$3:$AL$105,E52) -> 21 | F54: =COUNTIF('Guidelines - Data'!$AL$3:$AL$105,F52) -> 12 | G54: =COUNTIF('Guidelines - Data'!$AL$3:$AL$105,G52) -> 1 | H54: =COUNTIF('Guidelines - Data'!$AL$3:$AL$105,H52) -> 0 | J54: G2 | K54: =(C54/(C54+D54+E54+F54+G54+H54))*100 -> 40.776699 | L54: =(D54/(C54+D54+E54+F54+G54+H54))*100 -> 26.213592 | M54: =(E54/(C54+D54+E54+F54+G54+H54))*100 -> 20.38835 | N54: =(F54/(C54+D54+E54+F54+G54+H54))*100 -> 11.650485 | O54: =(G54/(C54+D54+E54+F54+G54+H54))*100 -> 0.97087379 | P54: =(H54/(C54+D54+E54+F54+G54+H54))*100 -> 0 | S54: G2 | T54: =ROUND(K54,2) -> 40.78 | U54: =ROUND(L54,2) -> 26.21 | V54: =ROUND(M54,2) -> 20.39 | W54: =ROUND(N54,2) -> 11.65 | X54: =ROUND(O54,2) -> 0.97 | Y54: =ROUND(P54,2) -> 0 | AA54: G2 | AB54: =((C54+D54+E54)/(C54+D54+E54+F54+G54+H54))*100 -> 87.378641 | AC54: =ROUND(AB54,2) -> 87.38 | AF54: G4 | AG54: 91.26
A55: G3 | B55: G3 - Reducing friction among different stakeholder groups | C55: =COUNTIF('Guidelines - Data'!$AM$3:$AM$105,C52) -> 23 | D55: =COUNTIF('Guidelines - Data'!$AM$3:$AM$105,D52) -> 34 | E55: =COUNTIF('Guidelines - Data'!$AM$3:$AM$105,E52) -> 28 | F55: =COUNTIF('Guidelines - Data'!$AM$3:$AM$105,F52) -> 11 | G55: =COUNTIF('Guidelines - Data'!$AM$3:$AM$105,G52) -> 5 | H55: =COUNTIF('Guidelines - Data'!$AM$3:$AM$105,H52) -> 2 | J55: G3 | K55: =(C55/(C55+D55+E55+F55+G55+H55))*100 -> 22.330097 | L55: =(D55/(C55+D55+E55+F55+G55+H55))*100 -> 33.009709 | M55: =(E55/(C55+D55+E55+F55+G55+H55))*100 -> 27.184466 | N55: =(F55/(C55+D55+E55+F55+G55+H55))*100 -> 10.679612 | O55: =(G55/(C55+D55+E55+F55+G55+H55))*100 -> 4.8543689 | P55: =(H55/(C55+D55+E55+F55+G55+H55))*100 -> 1.9417476 | S55: G3 | T55: =ROUND(K55,2) -> 22.33 | U55: =ROUND(L55,2) -> 33.01 | V55: =ROUND(M55,2) -> 27.18 | W55: =ROUND(N55,2) -> 10.68 | X55: =ROUND(O55,2) -> 4.85 | Y55: =ROUND(P55,2) -> 1.94 | AA55: G3 | AB55: =((C55+D55+E55)/(C55+D55+E55+F55+G55+H55))*100 -> 82.524272 | AC55: =ROUND(AB55,2) -> 82.52 | AF55: G10 | AG55: 89.32
A56: G4 | B56: G4 - Encouraging bi-directional communication | C56: =COUNTIF('Guidelines - Data'!$AN$3:$AN$105,C52) -> 43 | D56: =COUNTIF('Guidelines - Data'!$AN$3:$AN$105,D52) -> 28 | E56: =COUNTIF('Guidelines - Data'!$AN$3:$AN$105,E52) -> 23 | F56: =COUNTIF('Guidelines - Data'!$AN$3:$AN$105,F52) -> 7 | G56: =COUNTIF('Guidelines - Data'!$AN$3:$AN$105,G52) -> 2 | H56: =COUNTIF('Guidelines - Data'!$AN$3:$AN$105,H52) -> 0 | J56: G4 | K56: =(C56/(C56+D56+E56+F56+G56+H56))*100 -> 41.747573 | L56: =(D56/(C56+D56+E56+F56+G56+H56))*100 -> 27.184466 | M56: =(E56/(C56+D56+E56+F56+G56+H56))*100 -> 22.330097 | N56: =(F56/(C56+D56+E56+F56+G56+H56))*100 -> 6.7961165 | O56: =(G56/(C56+D56+E56+F56+G56+H56))*100 -> 1.9417476 | P56: =(H56/(C56+D56+E56+F56+G56+H56))*100 -> 0 | S56: G4 | T56: =ROUND(K56,2) -> 41.75 | U56: =ROUND(L56,2) -> 27.18 | V56: =ROUND(M56,2) -> 22.33 | W56: =ROUND(N56,2) -> 6.8 | X56: =ROUND(O56,2) -> 1.94 | Y56: =ROUND(P56,2) -> 0 | AA56: G4 | AB56: =((C56+D56+E56)/(C56+D56+E56+F56+G56+H56))*100 -> 91.262136 | AC56: =ROUND(AB56,2) -> 91.26 | AF56: G12 | AG56: 89.32
A57: G5 | B57: G5 - Ensuring transparency about business goals | C57: =COUNTIF('Guidelines - Data'!$AO$3:$AO$105,C52) -> 46 | D57: =COUNTIF('Guidelines - Data'!$AO$3:$AO$105,D52) -> 29 | E57: =COUNTIF('Guidelines - Data'!$AO$3:$AO$105,E52) -> 16 | F57: =COUNTIF('Guidelines - Data'!$AO$3:$AO$105,F52) -> 10 | G57: =COUNTIF('Guidelines - Data'!$AO$3:$AO$105,G52) -> 1 | H57: =COUNTIF('Guidelines - Data'!$AO$3:$AO$105,H52) -> 1 | J57: G5 | K57: =(C57/(C57+D57+E57+F57+G57+H57))*100 -> 44.660194 | L57: =(D57/(C57+D57+E57+F57+G57+H57))*100 -> 28.15534 | M57: =(E57/(C57+D57+E57+F57+G57+H57))*100 -> 15.533981 | N57: =(F57/(C57+D57+E57+F57+G57+H57))*100 -> 9.7087379 | O57: =(G57/(C57+D57+E57+F57+G57+H57))*100 -> 0.97087379 | P57: =(H57/(C57+D57+E57+F57+G57+H57))*100 -> 0.97087379 | S57: G5 | T57: =ROUND(K57,2) -> 44.66 | U57: =ROUND(L57,2) -> 28.16 | V57: =ROUND(M57,2) -> 15.53 | W57: =ROUND(N57,2) -> 9.71 | X57: =ROUND(O57,2) -> 0.97 | Y57: =ROUND(P57,2) -> 0.97 | AA57: G5 | AB57: =((C57+D57+E57)/(C57+D57+E57+F57+G57+H57))*100 -> 88.349515 | AC57: =ROUND(AB57,2) -> 88.35 | AF57: G5 | AG57: 88.35
A58: G6 | B58: G6 - Use an empathetic approach to improve RE processes | C58: =COUNTIF('Guidelines - Data'!$AP$3:$AP$105,C52) -> 20 | D58: =COUNTIF('Guidelines - Data'!$AP$3:$AP$105,D52) -> 38 | E58: =COUNTIF('Guidelines - Data'!$AP$3:$AP$105,E52) -> 20 | F58: =COUNTIF('Guidelines - Data'!$AP$3:$AP$105,F52) -> 21 | G58: =COUNTIF('Guidelines - Data'!$AP$3:$AP$105,G52) -> 2 | H58: =COUNTIF('Guidelines - Data'!$AP$3:$AP$105,H52) -> 2 | J58: G6 | K58: =(C58/(C58+D58+E58+F58+G58+H58))*100 -> 19.417476 | L58: =(D58/(C58+D58+E58+F58+G58+H58))*100 -> 36.893204 | M58: =(E58/(C58+D58+E58+F58+G58+H58))*100 -> 19.417476 | N58: =(F58/(C58+D58+E58+F58+G58+H58))*100 -> 20.38835 | O58: =(G58/(C58+D58+E58+F58+G58+H58))*100 -> 1.9417476 | P58: =(H58/(C58+D58+E58+F58+G58+H58))*100 -> 1.9417476 | S58: G6 | T58: =ROUND(K58,2) -> 19.42 | U58: =ROUND(L58,2) -> 36.89 | V58: =ROUND(M58,2) -> 19.42 | W58: =ROUND(N58,2) -> 20.39 | X58: =ROUND(O58,2) -> 1.94 | Y58: =ROUND(P58,2) -> 1.94 | AA58: G6 | AB58: =((C58+D58+E58)/(C58+D58+E58+F58+G58+H58))*100 -> 75.728155 | AC58: =ROUND(AB58,2) -> 75.73 | AF58: G2 | AG58: 87.38
A59: G7 | B59: G7 - Collaborative problem solving | C59: =COUNTIF('Guidelines - Data'!$AQ$3:$AQ$105,C52) -> 54 | D59: =COUNTIF('Guidelines - Data'!$AQ$3:$AQ$105,D52) -> 32 | E59: =COUNTIF('Guidelines - Data'!$AQ$3:$AQ$105,E52) -> 10 | F59: =COUNTIF('Guidelines - Data'!$AQ$3:$AQ$105,F52) -> 7 | G59: =COUNTIF('Guidelines - Data'!$AQ$3:$AQ$105,G52) -> 0 | H59: =COUNTIF('Guidelines - Data'!$AQ$3:$AQ$105,H52) -> 0 | J59: G7 | K59: =(C59/(C59+D59+E59+F59+G59+H59))*100 -> 52.427184 | L59: =(D59/(C59+D59+E59+F59+G59+H59))*100 -> 31.067961 | M59: =(E59/(C59+D59+E59+F59+G59+H59))*100 -> 9.7087379 | N59: =(F59/(C59+D59+E59+F59+G59+H59))*100 -> 6.7961165 | O59: =(G59/(C59+D59+E59+F59+G59+H59))*100 -> 0 | P59: =(H59/(C59+D59+E59+F59+G59+H59))*100 -> 0 | S59: G7 | T59: =ROUND(K59,2) -> 52.43 | U59: =ROUND(L59,2) -> 31.07 | V59: =ROUND(M59,2) -> 9.71 | W59: =ROUND(N59,2) -> 6.8 | X59: =ROUND(O59,2) -> 0 | Y59: =ROUND(P59,2) -> 0 | AA59: G7 | AB59: =((C59+D59+E59)/(C59+D59+E59+F59+G59+H59))*100 -> 93.203883 | AC59: =ROUND(AB59,2) -> 93.2 | AF59: G14 | AG59: 87.38
A60: G8 | B60: G8 - Empathy during agile ceremonies | C60: =COUNTIF('Guidelines - Data'!$AR$3:$AR$105,C52) -> 21 | D60: =COUNTIF('Guidelines - Data'!$AR$3:$AR$105,D52) -> 29 | E60: =COUNTIF('Guidelines - Data'!$AR$3:$AR$105,E52) -> 19 | F60: =COUNTIF('Guidelines - Data'!$AR$3:$AR$105,F52) -> 24 | G60: =COUNTIF('Guidelines - Data'!$AR$3:$AR$105,G52) -> 9 | H60: =COUNTIF('Guidelines - Data'!$AR$3:$AR$105,H52) -> 1 | J60: G8 | K60: =(C60/(C60+D60+E60+F60+G60+H60))*100 -> 20.38835 | L60: =(D60/(C60+D60+E60+F60+G60+H60))*100 -> 28.15534 | M60: =(E60/(C60+D60+E60+F60+G60+H60))*100 -> 18.446602 | N60: =(F60/(C60+D60+E60+F60+G60+H60))*100 -> 23.300971 | O60: =(G60/(C60+D60+E60+F60+G60+H60))*100 -> 8.7378641 | P60: =(H60/(C60+D60+E60+F60+G60+H60))*100 -> 0.97087379 | S60: G8 | T60: =ROUND(K60,2) -> 20.39 | U60: =ROUND(L60,2) -> 28.16 | V60: =ROUND(M60,2) -> 18.45 | W60: =ROUND(N60,2) -> 23.3 | X60: =ROUND(O60,2) -> 8.74 | Y60: =ROUND(P60,2) -> 0.97 | AA60: G8 | AB60: =((C60+D60+E60)/(C60+D60+E60+F60+G60+H60))*100 -> 66.990291 | AC60: =ROUND(AB60,2) -> 66.99 | AF60: G1 | AG60: 86.41
A61: G9 | B61: G9 - Empathetic feedback process | C61: =COUNTIF('Guidelines - Data'!$AS$3:$AS$105,C52) -> 31 | D61: =COUNTIF('Guidelines - Data'!$AS$3:$AS$105,D52) -> 31 | E61: =COUNTIF('Guidelines - Data'!$AS$3:$AS$105,E52) -> 23 | F61: =COUNTIF('Guidelines - Data'!$AS$3:$AS$105,F52) -> 12 | G61: =COUNTIF('Guidelines - Data'!$AS$3:$AS$105,G52) -> 5 | H61: =COUNTIF('Guidelines - Data'!$AS$3:$AS$105,H52) -> 1 | J61: G9 | K61: =(C61/(C61+D61+E61+F61+G61+H61))*100 -> 30.097087 | L61: =(D61/(C61+D61+E61+F61+G61+H61))*100 -> 30.097087 | M61: =(E61/(C61+D61+E61+F61+G61+H61))*100 -> 22.330097 | N61: =(F61/(C61+D61+E61+F61+G61+H61))*100 -> 11.650485 | O61: =(G61/(C61+D61+E61+F61+G61+H61))*100 -> 4.8543689 | P61: =(H61/(C61+D61+E61+F61+G61+H61))*100 -> 0.97087379 | S61: G9 | T61: =ROUND(K61,2) -> 30.1 | U61: =ROUND(L61,2) -> 30.1 | V61: =ROUND(M61,2) -> 22.33 | W61: =ROUND(N61,2) -> 11.65 | X61: =ROUND(O61,2) -> 4.85 | Y61: =ROUND(P61,2) -> 0.97 | AA61: G9 | AB61: =((C61+D61+E61)/(C61+D61+E61+F61+G61+H61))*100 -> 82.524272 | AC61: =ROUND(AB61,2) -> 82.52 | AF61: G11 | AG61: 86.41
A62: G10 | B62: G10 - Creating a safe space | C62: =COUNTIF('Guidelines - Data'!$AT$3:$AT$105,C52) -> 44 | D62: =COUNTIF('Guidelines - Data'!$AT$3:$AT$105,D52) -> 35 | E62: =COUNTIF('Guidelines - Data'!$AT$3:$AT$105,E52) -> 13 | F62: =COUNTIF('Guidelines - Data'!$AT$3:$AT$105,F52) -> 6 | G62: =COUNTIF('Guidelines - Data'!$AT$3:$AT$105,G52) -> 4 | H62: =COUNTIF('Guidelines - Data'!$AT$3:$AT$105,H52) -> 1 | J62: G10 | K62: =(C62/(C62+D62+E62+F62+G62+H62))*100 -> 42.718447 | L62: =(D62/(C62+D62+E62+F62+G62+H62))*100 -> 33.980583 | M62: =(E62/(C62+D62+E62+F62+G62+H62))*100 -> 12.621359 | N62: =(F62/(C62+D62+E62+F62+G62+H62))*100 -> 5.8252427 | O62: =(G62/(C62+D62+E62+F62+G62+H62))*100 -> 3.8834951 | P62: =(H62/(C62+D62+E62+F62+G62+H62))*100 -> 0.97087379 | S62: G10 | T62: =ROUND(K62,2) -> 42.72 | U62: =ROUND(L62,2) -> 33.98 | V62: =ROUND(M62,2) -> 12.62 | W62: =ROUND(N62,2) -> 5.83 | X62: =ROUND(O62,2) -> 3.88 | Y62: =ROUND(P62,2) -> 0.97 | AA62: G10 | AB62: =((C62+D62+E62)/(C62+D62+E62+F62+G62+H62))*100 -> 89.320388 | AC62: =ROUND(AB62,2) -> 89.32 | AF62: G13 | AG62: 86.41
A63: G11 | B63: G11 - Backup plans to manage unexpected outcomes | C63: =COUNTIF('Guidelines - Data'!$AU$3:$AU$105,C52) -> 41 | D63: =COUNTIF('Guidelines - Data'!$AU$3:$AU$105,D52) -> 39 | E63: =COUNTIF('Guidelines - Data'!$AU$3:$AU$105,E52) -> 9 | F63: =COUNTIF('Guidelines - Data'!$AU$3:$AU$105,F52) -> 10 | G63: =COUNTIF('Guidelines - Data'!$AU$3:$AU$105,G52) -> 4 | H63: =COUNTIF('Guidelines - Data'!$AU$3:$AU$105,H52) -> 0 | J63: G11 | K63: =(C63/(C63+D63+E63+F63+G63+H63))*100 -> 39.805825 | L63: =(D63/(C63+D63+E63+F63+G63+H63))*100 -> 37.864078 | M63: =(E63/(C63+D63+E63+F63+G63+H63))*100 -> 8.7378641 | N63: =(F63/(C63+D63+E63+F63+G63+H63))*100 -> 9.7087379 | O63: =(G63/(C63+D63+E63+F63+G63+H63))*100 -> 3.8834951 | P63: =(H63/(C63+D63+E63+F63+G63+H63))*100 -> 0 | S63: G11 | T63: =ROUND(K63,2) -> 39.81 | U63: =ROUND(L63,2) -> 37.86 | V63: =ROUND(M63,2) -> 8.74 | W63: =ROUND(N63,2) -> 9.71 | X63: =ROUND(O63,2) -> 3.88 | Y63: =ROUND(P63,2) -> 0 | AA63: G11 | AB63: =((C63+D63+E63)/(C63+D63+E63+F63+G63+H63))*100 -> 86.407767 | AC63: =ROUND(AB63,2) -> 86.41 | AF63: G3 | AG63: 82.52
A64: G12 | B64: G12 - Flexibility in handling human issues | C64: =COUNTIF('Guidelines - Data'!$AV$3:$AV$105,C52) -> 36 | D64: =COUNTIF('Guidelines - Data'!$AV$3:$AV$105,D52) -> 31 | E64: =COUNTIF('Guidelines - Data'!$AV$3:$AV$105,E52) -> 25 | F64: =COUNTIF('Guidelines - Data'!$AV$3:$AV$105,F52) -> 9 | G64: =COUNTIF('Guidelines - Data'!$AV$3:$AV$105,G52) -> 2 | H64: =COUNTIF('Guidelines - Data'!$AV$3:$AV$105,H52) -> 0 | J64: G12 | K64: =(C64/(C64+D64+E64+F64+G64+H64))*100 -> 34.951456 | L64: =(D64/(C64+D64+E64+F64+G64+H64))*100 -> 30.097087 | M64: =(E64/(C64+D64+E64+F64+G64+H64))*100 -> 24.271845 | N64: =(F64/(C64+D64+E64+F64+G64+H64))*100 -> 8.7378641 | O64: =(G64/(C64+D64+E64+F64+G64+H64))*100 -> 1.9417476 | P64: =(H64/(C64+D64+E64+F64+G64+H64))*100 -> 0 | S64: G12 | T64: =ROUND(K64,2) -> 34.95 | U64: =ROUND(L64,2) -> 30.1 | V64: =ROUND(M64,2) -> 24.27 | W64: =ROUND(N64,2) -> 8.74 | X64: =ROUND(O64,2) -> 1.94 | Y64: =ROUND(P64,2) -> 0 | AA64: G12 | AB64: =((C64+D64+E64)/(C64+D64+E64+F64+G64+H64))*100 -> 89.320388 | AC64: =ROUND(AB64,2) -> 89.32 | AF64: G9 | AG64: 82.52
A65: G13 | B65: G13 - Emphasising the real-world impact of developers’ work | C65: =COUNTIF('Guidelines - Data'!$AW$3:$AW$105,C52) -> 25 | D65: =COUNTIF('Guidelines - Data'!$AW$3:$AW$105,D52) -> 46 | E65: =COUNTIF('Guidelines - Data'!$AW$3:$AW$105,E52) -> 18 | F65: =COUNTIF('Guidelines - Data'!$AW$3:$AW$105,F52) -> 8 | G65: =COUNTIF('Guidelines - Data'!$AW$3:$AW$105,G52) -> 5 | H65: =COUNTIF('Guidelines - Data'!$AW$3:$AW$105,H52) -> 1 | J65: G13 | K65: =(C65/(C65+D65+E65+F65+G65+H65))*100 -> 24.271845 | L65: =(D65/(C65+D65+E65+F65+G65+H65))*100 -> 44.660194 | M65: =(E65/(C65+D65+E65+F65+G65+H65))*100 -> 17.475728 | N65: =(F65/(C65+D65+E65+F65+G65+H65))*100 -> 7.7669903 | O65: =(G65/(C65+D65+E65+F65+G65+H65))*100 -> 4.8543689 | P65: =(H65/(C65+D65+E65+F65+G65+H65))*100 -> 0.97087379 | S65: G13 | T65: =ROUND(K65,2) -> 24.27 | U65: =ROUND(L65,2) -> 44.66 | V65: =ROUND(M65,2) -> 17.48 | W65: =ROUND(N65,2) -> 7.77 | X65: =ROUND(O65,2) -> 4.85 | Y65: =ROUND(P65,2) -> 0.97 | AA65: G13 | AB65: =((C65+D65+E65)/(C65+D65+E65+F65+G65+H65))*100 -> 86.407767 | AC65: =ROUND(AB65,2) -> 86.41 | AF65: G6 | AG65: 75.73
A66: G14 | B66: G14 - Building an empathetic team and company culture | C66: =COUNTIF('Guidelines - Data'!$AX$3:$AX$105,C52) -> 40 | D66: =COUNTIF('Guidelines - Data'!$AX$3:$AX$105,D52) -> 34 | E66: =COUNTIF('Guidelines - Data'!$AX$3:$AX$105,E52) -> 16 | F66: =COUNTIF('Guidelines - Data'!$AX$3:$AX$105,F52) -> 6 | G66: =COUNTIF('Guidelines - Data'!$AX$3:$AX$105,G52) -> 6 | H66: =COUNTIF('Guidelines - Data'!$AX$3:$AX$105,H52) -> 1 | J66: G14 | K66: =(C66/(C66+D66+E66+F66+G66+H66))*100 -> 38.834951 | L66: =(D66/(C66+D66+E66+F66+G66+H66))*100 -> 33.009709 | M66: =(E66/(C66+D66+E66+F66+G66+H66))*100 -> 15.533981 | N66: =(F66/(C66+D66+E66+F66+G66+H66))*100 -> 5.8252427 | O66: =(G66/(C66+D66+E66+F66+G66+H66))*100 -> 5.8252427 | P66: =(H66/(C66+D66+E66+F66+G66+H66))*100 -> 0.97087379 | S66: G14 | T66: =ROUND(K66,2) -> 38.83 | U66: =ROUND(L66,2) -> 33.01 | V66: =ROUND(M66,2) -> 15.53 | W66: =ROUND(N66,2) -> 5.83 | X66: =ROUND(O66,2) -> 5.83 | Y66: =ROUND(P66,2) -> 0.97 | AA66: G14 | AB66: =((C66+D66+E66)/(C66+D66+E66+F66+G66+H66))*100 -> 87.378641 | AC66: =ROUND(AB66,2) -> 87.38 | AF66: G15 | AG66: 74.76
A67: G15 | B67: G15 - Empathy education and training | C67: =COUNTIF('Guidelines - Data'!$AY$3:$AY$105,C52) -> 21 | D67: =COUNTIF('Guidelines - Data'!$AY$3:$AY$105,D52) -> 32 | E67: =COUNTIF('Guidelines - Data'!$AY$3:$AY$105,E52) -> 24 | F67: =COUNTIF('Guidelines - Data'!$AY$3:$AY$105,F52) -> 11 | G67: =COUNTIF('Guidelines - Data'!$AY$3:$AY$105,G52) -> 14 | H67: =COUNTIF('Guidelines - Data'!$AY$3:$AY$105,H52) -> 1 | J67: G15 | K67: =(C67/(C67+D67+E67+F67+G67+H67))*100 -> 20.38835 | L67: =(D67/(C67+D67+E67+F67+G67+H67))*100 -> 31.067961 | M67: =(E67/(C67+D67+E67+F67+G67+H67))*100 -> 23.300971 | N67: =(F67/(C67+D67+E67+F67+G67+H67))*100 -> 10.679612 | O67: =(G67/(C67+D67+E67+F67+G67+H67))*100 -> 13.592233 | P67: =(H67/(C67+D67+E67+F67+G67+H67))*100 -> 0.97087379 | S67: G15 | T67: =ROUND(K67,2) -> 20.39 | U67: =ROUND(L67,2) -> 31.07 | V67: =ROUND(M67,2) -> 23.3 | W67: =ROUND(N67,2) -> 10.68 | X67: =ROUND(O67,2) -> 13.59 | Y67: =ROUND(P67,2) -> 0.97 | AA67: G15 | AB67: =((C67+D67+E67)/(C67+D67+E67+F67+G67+H67))*100 -> 74.757282 | AC67: =ROUND(AB67,2) -> 74.76 | AF67: G16 | AG67: 72.82
A68: G16 | B68: G16 - DEI policies | C68: =COUNTIF('Guidelines - Data'!$AZ$3:$AZ$105,C52) -> 29 | D68: =COUNTIF('Guidelines - Data'!$AZ$3:$AZ$105,D52) -> 22 | E68: =COUNTIF('Guidelines - Data'!$AZ$3:$AZ$105,E52) -> 24 | F68: =COUNTIF('Guidelines - Data'!$AZ$3:$AZ$105,F52) -> 12 | G68: =COUNTIF('Guidelines - Data'!$AZ$3:$AZ$105,G52) -> 13 | H68: =COUNTIF('Guidelines - Data'!$AZ$3:$AZ$105,H52) -> 3 | J68: G16 | K68: =(C68/(C68+D68+E68+F68+G68+H68))*100 -> 28.15534 | L68: =(D68/(C68+D68+E68+F68+G68+H68))*100 -> 21.359223 | M68: =(E68/(C68+D68+E68+F68+G68+H68))*100 -> 23.300971 | N68: =(F68/(C68+D68+E68+F68+G68+H68))*100 -> 11.650485 | O68: =(G68/(C68+D68+E68+F68+G68+H68))*100 -> 12.621359 | P68: =(H68/(C68+D68+E68+F68+G68+H68))*100 -> 2.9126214 | S68: G16 | T68: =ROUND(K68,2) -> 28.16 | U68: =ROUND(L68,2) -> 21.36 | V68: =ROUND(M68,2) -> 23.3 | W68: =ROUND(N68,2) -> 11.65 | X68: =ROUND(O68,2) -> 12.62 | Y68: =ROUND(P68,2) -> 2.91 | AA68: G16 | AB68: =((C68+D68+E68)/(C68+D68+E68+F68+G68+H68))*100 -> 72.815534 | AC68: =ROUND(AB68,2) -> 72.82 | AF68: G17 | AG68: 71.84
A69: G17 | B69: G17 - Managing empathy fatigue | C69: =COUNTIF('Guidelines - Data'!$BA$3:$BA$105,C52) -> 19 | D69: =COUNTIF('Guidelines - Data'!$BA$3:$BA$105,D52) -> 36 | E69: =COUNTIF('Guidelines - Data'!$BA$3:$BA$105,E52) -> 19 | F69: =COUNTIF('Guidelines - Data'!$BA$3:$BA$105,F52) -> 19 | G69: =COUNTIF('Guidelines - Data'!$BA$3:$BA$105,G52) -> 8 | H69: =COUNTIF('Guidelines - Data'!$BA$3:$BA$105,H52) -> 2 | J69: G17 | K69: =(C69/(C69+D69+E69+F69+G69+H69))*100 -> 18.446602 | L69: =(D69/(C69+D69+E69+F69+G69+H69))*100 -> 34.951456 | M69: =(E69/(C69+D69+E69+F69+G69+H69))*100 -> 18.446602 | N69: =(F69/(C69+D69+E69+F69+G69+H69))*100 -> 18.446602 | O69: =(G69/(C69+D69+E69+F69+G69+H69))*100 -> 7.7669903 | P69: =(H69/(C69+D69+E69+F69+G69+H69))*100 -> 1.9417476 | S69: G17 | T69: =ROUND(K69,2) -> 18.45 | U69: =ROUND(L69,2) -> 34.95 | V69: =ROUND(M69,2) -> 18.45 | W69: =ROUND(N69,2) -> 18.45 | X69: =ROUND(O69,2) -> 7.77 | Y69: =ROUND(P69,2) -> 1.94 | AA69: G17 | AB69: =((C69+D69+E69)/(C69+D69+E69+F69+G69+H69))*100 -> 71.84466 | AC69: =ROUND(AB69,2) -> 71.84 | AF69: G8 | AG69: 66.99
A73: Adoption Readiness Score This score gives a concise way to prioritise guidelines based on how: Important they are seen, Practical and easy they are to implement, and Willing people are to adopt them.
C74: Importance % | D74: Ease % | E74: Adoption % | F74: Adoption Readiness Score | G74: Rounded - Adoption Readiness Score | K74: Sorted - Adoption Readiness Score
A75: G1 | B75: G1 - Fostering strong relationships among stakeholders | C75: 77.67 | D75: 36.89 | E75: 86.41 | F75: =(C75+D75+E75)/3 -> 66.99 | G75: =ROUND(F75,2) -> 66.99 | J75: G10 | K75: 74.32
A76: G2 | B76: G2 - Bridging the technical and non-technical gap | C76: 76.7 | D76: 33.98 | E76: 87.38 | F76: =(C76+D76+E76)/3 -> 66.02 | G76: =ROUND(F76,2) -> 66.02 | J76: G5 | K76: 73.14
A77: G3 | B77: G3 - Reducing friction among different stakeholder groups | C77: 65.05 | D77: 25.24 | E77: 82.52 | F77: =(C77+D77+E77)/3 -> 57.603333 | G77: =ROUND(F77,2) -> 57.6 | J77: G4 | K77: 71.52
A78: G4 | B78: G4 - Encouraging bi-directional communication | C78: 71.84 | D78: 51.46 | E78: 91.26 | F78: =(C78+D78+E78)/3 -> 71.52 | G78: =ROUND(F78,2) -> 71.52 | J78: G7 | K78: 71.2
A79: G5 | B79: G5 - Ensuring transparency about business goals | C79: 71.84 | D79: 59.22 | E79: 88.35 | F79: =(C79+D79+E79)/3 -> 73.136667 | G79: =ROUND(F79,2) -> 73.14 | J79: G9 | K79: 69.12
A80: G6 | B80: G6 - Use an empathetic approach to improve RE processes | C80: 55.34 | D80: 46.6 | E80: 75.73 | F80: =(C80+D80+E80)/3 -> 59.223333 | G80: =ROUND(F80,2) -> 59.22 | J80: G12 | K80: 67.64
A81: G7 | B81: G7 - Collaborative problem solving | C81: 72.82 | D81: 47.57 | E81: 93.2 | F81: =(C81+D81+E81)/3 -> 71.196667 | G81: =ROUND(F81,2) -> 71.2 | J81: G1 | K81: 66.99
A82: G8 | B82: G8 - Empathy during agile ceremonies | C82: 47.57 | D82: 49.51 | E82: 66.99 | F82: =(C82+D82+E82)/3 -> 54.69 | G82: =ROUND(F82,2) -> 54.69 | J82: G2 | K82: 66.02
A83: G9 | B83: G9 - Empathetic feedback process | C83: 66.99 | D83: 57.84 | E83: 82.52 | F83: =(C83+D83+E83)/3 -> 69.116667 | G83: =ROUND(F83,2) -> 69.12 | J83: G11 | K83: 63.75
A84: G10 | B84: G10 - Creating a safe space | C84: 69.9 | D84: 63.73 | E84: 89.32 | F84: =(C84+D84+E84)/3 -> 74.316667 | G84: =ROUND(F84,2) -> 74.32 | J84: G13 | K84: 61.63
A85: G11 | B85: G11 - Backup plans to manage unexpected outcomes | C85: 71.84 | D85: 33.01 | E85: 86.41 | F85: =(C85+D85+E85)/3 -> 63.753333 | G85: =ROUND(F85,2) -> 63.75 | J85: G14 | K85: 60.29
A86: G12 | B86: G12 - Flexibility in handling human issues | C86: 67.96 | D86: 45.63 | E86: 89.32 | F86: =(C86+D86+E86)/3 -> 67.636667 | G86: =ROUND(F86,2) -> 67.64 | J86: G15 | K86: 59.87
... A91: G17 | B91: G17 - Managing empathy fatigue | C91: 54.37 | D91: 26 | E91: 71.84 | F91: =(C91+D91+E91)/3 -> 50.736667 | G91: =ROUND(F91,2) -> 50.74 | J91: G17 | K91: 50.74
A95: Guideline | C95: Importance - weighted score | D95: Ease - weighted score | F95: Rounded - Importance weighted score | G95: Rounded - Ease weighted score
A96: G1 | B96: G1 - Fostering strong relationships among stakeholders | C96: =(C4*5+D4*4+E4*3+F4*2+G4*1)/(C4+D4+E4+F4+G4) -> 3.8252427 | D96: =(C27*5+D27*4+E27*3+F27*2+G27*1)/(C27+D27+E27+F27+G27) -> 2.7475728 | F96: =ROUND(C96,2) -> 3.83 | G96: =ROUND(D96,2) -> 2.75
A97: G2 | B97: G2 - Bridging the technical and non-technical gap | C97: =(C5*5+D5*4+E5*3+F5*2+G5*1)/(C5+D5+E5+F5+G5) -> 3.8543689 | D97: =(C28*5+D28*4+E28*3+F28*2+G28*1)/(C28+D28+E28+F28+G28) -> 2.7281553 | F97: =ROUND(C97,2) -> 3.85 | G97: =ROUND(D97,2) -> 2.73
A98: G3 | B98: G3 - Reducing friction among different stakeholder groups | C98: =(C6*5+D6*4+E6*3+F6*2+G6*1)/(C6+D6+E6+F6+G6) -> 3.5436893 | D98: =(C29*5+D29*4+E29*3+F29*2+G29*1)/(C29+D29+E29+F29+G29) -> 2.5339806 | F98: =ROUND(C98,2) -> 3.54 | G98: =ROUND(D98,2) -> 2.53
A99: G4 | B99: G4 - Encouraging bi-directional communication | C99: =(C7*5+D7*4+E7*3+F7*2+G7*1)/(C7+D7+E7+F7+G7) -> 3.7864078 | D99: =(C30*5+D30*4+E30*3+F30*2+G30*1)/(C30+D30+E30+F30+G30) -> 3.1650485 | F99: =ROUND(C99,2) -> 3.79 | G99: =ROUND(D99,2) -> 3.17
A100: G5 | B100: G5 - Ensuring transparency about business goals | C100: =(C8*5+D8*4+E8*3+F8*2+G8*1)/(C8+D8+E8+F8+G8) -> 3.815534 | D100: =(C31*5+D31*4+E31*3+F31*2+G31*1)/(C31+D31+E31+F31+G31) -> 3.2427184 | F100: =ROUND(C100,2) -> 3.82 | G100: =ROUND(D100,2) -> 3.24
A101: G6 | B101: G6 - Use an empathetic approach to improve RE processes | C101: =(C9*5+D9*4+E9*3+F9*2+G9*1)/(C9+D9+E9+F9+G9) -> 3.2427184 | D101: =(C32*5+D32*4+E32*3+F32*2+G32*1)/(C32+D32+E32+F32+G32) -> 3.1165049 | F101: =ROUND(C101,2) -> 3.24 | G101: =ROUND(D101,2) -> 3.12
A102: G7 | B102: G7 - Collaborative problem solving | C102: =(C10*5+D10*4+E10*3+F10*2+G10*1)/(C10+D10+E10+F10+G10) -> 3.8058252 | D102: =(C33*5+D33*4+E33*3+F33*2+G33*1)/(C33+D33+E33+F33+G33) -> 3.0485437 | F102: =ROUND(C102,2) -> 3.81 | G102: =ROUND(D102,2) -> 3.05
A103: G8 | B103: G8 - Empathy during agile ceremonies | C103: =(C11*5+D11*4+E11*3+F11*2+G11*1)/(C11+D11+E11+F11+G11) -> 3.184466 | D103: =(C34*5+D34*4+E34*3+F34*2+G34*1)/(C34+D34+E34+F34+G34) -> 3.223301 | F103: =ROUND(C103,2) -> 3.18 | G103: =ROUND(D103,2) -> 3.22
A104: G9 | B104: G9 - Empathetic feedback process | C104: =(C12*5+D12*4+E12*3+F12*2+G12*1)/(C12+D12+E12+F12+G12) -> 3.5436893 | D104: =(C35*5+D35*4+E35*3+F35*2+G35*1)/(C35+D35+E35+F35+G35) -> 3.3431373 | F104: =ROUND(C104,2) -> 3.54 | G104: =ROUND(D104,2) -> 3.34
A105: G10 | B105: G10 - Creating a safe space | C105: =(C13*5+D13*4+E13*3+F13*2+G13*1)/(C13+D13+E13+F13+G13) -> 3.7378641 | D105: =(C36*5+D36*4+E36*3+F36*2+G36*1)/(C36+D36+E36+F36+G36) -> 3.4509804 | F105: =ROUND(C105,2) -> 3.74 | G105: =ROUND(D105,2) -> 3.45
A106: G11 | B106: G11 - Backup plans to manage unexpected outcomes | C106: =(C14*5+D14*4+E14*3+F14*2+G14*1)/(C14+D14+E14+F14+G14) -> 3.8252427 | D106: =(C37*5+D37*4+E37*3+F37*2+G37*1)/(C37+D37+E37+F37+G37) -> 2.6504854 | F106: =ROUND(C106,2) -> 3.83 | G106: =ROUND(D106,2) -> 2.65
A107: G12 | B107: G12 - Flexibility in handling human issues | C107: =(C15*5+D15*4+E15*3+F15*2+G15*1)/(C15+D15+E15+F15+G15) -> 3.5728155 | D107: =(C38*5+D38*4+E38*3+F38*2+G38*1)/(C38+D38+E38+F38+G38) -> 2.961165 | F107: =ROUND(C107,2) -> 3.57 | G107: =ROUND(D107,2) -> 2.96
... A112: G17 | B112: G17 - Managing empathy fatigue | C112: =(C20*5+D20*4+E20*3+F20*2+G20*1)/(C20+D20+E20+F20+G20) -> 3.2718447 | D112: =(C43*5+D43*4+E43*3+F43*2+G43*1)/(C43+D43+E43+F43+G43) -> 2.61 | F112: =ROUND(C112,2) -> 3.27 | G112: =ROUND(D112,2) -> 2.61
B118: Mean | F118: =ROUND(SUM(F96:F112)/17,2) -> 3.55 | G118: =ROUND(SUM(G96:G112)/17,2) -> 2.98
I122: Quadrant | J122: Identifier | K122: Meaning
I123: Top Right (High Importance, High Ease) | J123: Quick Wins | K123: High Priority, High Feasibility (Implement first, valuable and doable)
I124: Top Left (Low Importance, High Ease) | J124: Nice to have | K124: Low Importance, High Feasibility (Easy to do, but possibly low impact)
I125: Bottom Right (High Importance, Low Ease) | J125: Strategic investments (Aspirational/ Challenging) | K125: High Importance, Low Feasibility (Worth planning for, need resources/effort)
I126: Bottom Left (Low Importance, Low Ease) | J126: Low priority | K126: Low Priority, Low Feasibility (Avoid or revisit later)
I132: Top Right (High Importance, High Ease): Quick wins. Prioritise these guidelines.
I133: Top Left (Low Importance, High Ease): Low-hanging fruit. Easy to implement but may have limited impact.
I134: Bottom Right (High Importance, Low Ease): Strategic investments. Valuable but may need planning and resources.
I135: Bottom Left (Low Importance, Low Ease): Lowest priority. Revisit later or revise the approach.
A139: Guideline | C139: Adoption Willingness - Weighted Score | D139: Rounded Adoption Willingness - Weighted Score
A140: G1 | B140: G1 - Fostering strong relationships among stakeholders | C140: =(C53*6+D53*5+E53*4+F53*3+G53*2+H53*1)/(C53+D53+E53+F53+G53+H53) -> 4.7475728 | D140: =ROUND(C140,2) -> 4.75
A141: G2 | B141: G2 - Bridging the technical and non-technical gap | C141: =(C54*6+D54*5+E54*4+F54*3+G54*2+H54*1)/(C54+D54+E54+F54+G54+H54) -> 4.9417476 | D141: =ROUND(C141,2) -> 4.94
...

Sheet Guidelines Analysis - Qual - Pr
A2: Guidelines | B2: Top 5 Selection Count | C2: Implementing Ways - Guideline Specific | D2: Final - Implementing Ways - Guideline Specific | E2: Implementing Ways - General | F2: Final Implementing Ways - General
A3: G1 - Fostering strong relationships among stakeholders | B3: 47 | C3: I will build relationships by scheduling regular touchpoints and informal discussions to establish rapport. Actively listening to stakeholder needs and demonstrating follow-through on commitments will strengthen trust. Celebrating shared successes will also reinforce positive collaboration. I will prioritize regular communication through meetings and one-on-ones to build trust and align stakeholder concerns with project goals. Build trust through open communication and regular team bonding activities (e.g., virtual coffee breaks). I will actively seek opportunities to connect with my colleagues, both within my team and across different departments. G1 & G3 - I am willing to make more transparent the communication of different stakeholders and create a dedicated space (software tools and physical meetings) to make the team work as one and not as different parties. I will regularly engage with team members and stakeholders to build trust and collaboration. I will also facilitate informal team-building activities to strengthen these relationships. G1, and G3 are important to implement because it affects our ability to generate investments into our companys growth. I can make this happen by simply speaking to stakeholders in a group setting and adding informal discussions to the mix and fostering discussions amognst themselves. I would actively engage with team members and stakeholders, encouraging open communication and mutual understanding. Regular informal interactions like lunch meetings or team bonding activities can help build trust. I will initiate informal team-building activities, such as lunch outings or collaborative brainstorming sessions, to strengthen interpersonal relationships and build trust. I will also encourage friendly and supportive daily interactions within the team. I would prioritize fostering strong relationships among stakeholders by promoting trust and open communication through team-building activities. Strengthen relationships with colleagues through informal conversations, shared lunches, and team building activities. I’ll build trust with stakeholders through regular check-ins and team bonding. Relationships are everything. I’d make sure to keep communication flowing with quick check-ins, honest feedback, and being approachable so everyone feels like they’re part of the same team. it's always easier to show empathy and support when you actually care about someone, so i try to create conviviality moments, we have lunch together every day, and often take times outside of work, for a nice restaurant, a christmas market, and we plan on an escape game. Daily Interactions: I will actively practice empathy by being friendly, supportive, and attentive to colleagues' needs and concerns. This involves listening actively, offering help, and showing genuine interest in their well-being. Team Bonding Activities: Organize informal activities such as team lunches, virtual coffee breaks, or team-building exercises to strengthen relationships. Company-Wide Events: Advocate for company-wide events that encourage inter-departmental interaction, such as town halls or social gatherings, to foster a sense of community. Promote Team Activities: Arrange team-building activities that promote interaction and bonding among team members. Daily Practice: Be approachable, supportive, and empathetic in every interaction, ensuring open communication with colleagues and stakeholders. Managerial Level: Organize informal team bonding activities like lunch outings or collaborative brainstorming sessions. Organizational Level: Advocate for empathy to be included in the company’s values and participate in cross-departmental team-building events. I plan to include stakeholders in more of our internal meetings, whether they're internal or not. Perhaps even sending out some sort of feedback form for them to review internally. I will meet more often with other stakeholders and be supportive when they struggle. Building rapport with stakeholders through regular, transparent conversations strengthens trust and enhances collaboration. This helps reduce communication barriers, leading to smoother project execution. I will make a concerted effort to build strong, trust-based relationships with stakeholders by being approachable, actively listening to their concerns, and offering support during discussions. I will also participate in team bonding activities to strengthen these relationships. Steps: Set regular check-ins with stakeholders, engage in informal interactions (like coffee chats or team outings), and actively listen to understand their needs and expectations. Building trust and mutual understanding is crucial. I plan to schedule regular informal check-ins with stakeholders to create open communication channels and foster stronger relationships. This could include virtual coffee meetings or team-building events. Be friendly, supportive, and open with teammates. Organize casual hangouts like lunches or virtual chats to strengthen bonds and make work fun. Schedule regular check-ins, listen actively, and involve stakeholders in decision-making (fostering strong relationships among stakeholders). I will build trust and mutual understanding through open communication and supportive interactions with team members and stakeholders. Informal activities like team lunches and collaborative discussions will help strengthen these connections. | D3: Communication: - Scheduling regular touchpoints and informal discussions to establish rapport. - Regular open communication through meetings and one-on-ones to build trust and align stakeholder concerns with project goals. - more transparent the communication with different stakeholders - actively engage with team members and stakeholders, encouraging open communication and mutual understanding. - speaking to stakeholders in a group setting and adding informal discussions to the mix and fostering discussions amognst themselves. - keep communication flowing with quick check-ins, honest feedback, and being approachable so everyone feels like they’re part of the same team. Relationship and Trust Building: - Regular informal interactions (like lunch meetings, collaborative brainstorming sessions, take times outside of work for a nice restaurant, a christmas market, and we plan on an escape game. ) or team bonding activities (e.g., virtual coffee breaks, team outings) - Celebrating shared successes - Advocate for company-wide events that encourage inter-departmental interaction, such as town halls or social gatherings, to foster a sense of community. - Organizational Level: Advocate for empathy to be included in the company’s values and participate in cross-departmental team-building events. - meet more often with other stakeholders and be supportive when they struggle. Active Listening: - Actively listening to stakeholder needs and demonstrating follow-through on commitments - listening actively, offering help, and showing genuine interest in their well-being. - actively practice empathy by being friendly, supportive, and attentive to colleagues' needs and concerns. - Be approachable, supportive, and empathetic in every interaction, ensuring open communication with colleagues and stakeholders. Collaboration: - seek opportunities to connect with colleagues, both within the team and across different departments. - create a dedicated space (software tools and physical meetings) to make the team work as one and not as different parties. - encourage friendly and supportive daily interactions within the team. - include stakeholders in more of our internal meetings, whether they're internal or not. Perhaps even sending out some sort of feedback form for them to review internally. - Involve stakeholders in decision-making | E3: the key would be to get buy in from senior management for a top down approach. I would incorporate these guidelines in my daily work and practices by encouraging everyone in my workplace to work together. I want to build a place for people who help others to improve, not afriad to ask questions, and to build strong connections with each other and other skateholders. I believe that we will implement these guidelines only with the most experienced team we have, once they have been adopted, we will choose leaders from this group to implement them in the other groups. I would choose these because in my opinion they are all fundamental points for good teamwork, having a common path, a single goal to achieve creates unity and makes everyone go in the same direction. What I usually do is to treat the different members of the group in a personal way, everyone has a different character and sensitivity and you have to adapt to these characteristics. Some of these policies may fall under the HR team's responsibilities, so my role would primarily involve raising awareness and informing the appropriate members. Others can be implemented on an individual level. I intend to achieve this by incorporating them in the company's standard and norms for everyone to work with from the leading staff down to the list staff i. e after having a discussion with the team to inform them of the changes. These guidelines should be communicated to first level managers and at the end of the year, quantitative measures should be used to evaluate them. These are the ones that stuck with me due to the fact that often we do not think about them as much as we should. Implementing it should not be difficult depending on the people you are working with and if they are willing to change, talking to them about the things you want to change and how you want to do it, and them understanding is the best approach. This would be done by making a proper plan to introduce this in several high level meetings with management to ensure people are supported at the workplace which will significantly improve the moral of the work force. I'm not a leader, nor do I have people under my supervision. Sometimes it’s hard for my suggestions to be heard, but I believe I could apply the guidelines G6, G10, G11, G12, and G13 as much as possible by suggesting them to my leader, and in turn, to their leader. I have to first educate the entire team on the benefits of each then this will make teaching them and implementing them easier. I feel that all of these it’s weave into a great mix as my top five guidelines helping any team and project have a more human touch for the development team and the users who are going to be working with the end product. I’ve found focusing on the areas while not in isolation certainly have helped the teams and projects achieve successful outcomes in a positive workplace for all parties. These are already part of my daily practices. I regularly check in on my team members' wellbeing (sometimes just being asked how you are helps) and I organize regular meetings with them to discuss status, challenges, next steps, backup plans, etc. Incorporating these guidelines requires deliberate daily actions (e.g., empathy in communication, simplifying technical details) supported by managerial initiatives (e.g., organizing team bonding and bridging gaps) and organizational policies (e.g., transparency, fostering a safe space). Consistent application at all levels ensures these practices are deeply integrated into the workplace culture. These are all simple guidelines that can be implemented as training during onboarding of new employees. They have high impact and in my opinion would lead to higher employee retention. As my field is related to technical so often I take my part to design software and share the aspect to clients. Also training process keep me to involve in modern technologies. I establish working relationship with other to make a space and implement these guidelines. I plan to incorporate this guidelines through implementation of policies and trainings on empathy. I plan to improve myself and learn more about these guidelines in order to develop myself. | F3: Management and Leadership Engagement: - get buy in from senior management for a top down approach. - These guidelines should be communicated to first level managers and at the end of the year, quantitative measures should be used to evaluate them. - making a proper plan to introduce this in several high level meetings with management to ensure people are supported at the workplace Organizational Culture and Policies: - Incorporating guidelines into the company's standard and norms, starting from the leading staff down to junior staff. - managerial initiatives (e.g., organizing team bonding and bridging gaps) - organizational policies (e.g., transparency, fostering a safe space) Team Collaboration and Individual Engagement: - incorporate these guidelines in daily work and practices by encouraging teamwork. - build a place for people who help others to improve, not afriad to ask questions, and build strong connections with each other and other skateholders. - treat the different members of the group in a personal way, respecting individual needs. - regularly check in on team members' wellbeing - organize regular meetings with them to discuss status, challenges, next steps, backup plans, etc. Implementation Strategy and Rollout: - Identify guidelines that can be implemented at individual level and in group setting. - Get the help of the HR team for the company-wide implementation of these guidelines. - raising awareness of guidelines by informing the appropriate members. - implement these guidelines only with the most experienced team, and once adopted, select leaders from this group to implement them in the other groups. - Educate the entire team on the benefits of guidelines, making teaching and implementation easier. - Incorporate these guidelines as training during onboarding for new employees. - talking to team members about desired changes and ensuring they understand the current approach is the best strategy. - Consistent application at all levels ensures these practices are deeply integrated into the workplace culture. - through implementation of policies and trainings on empathy
A4: G2 - Bridging the technical and non-technical gap | B4: 45 | C4: Communicating technical aspects effectively to non-technical stakeholders is crucial for aligning expectations and achieving project goals. Use visuals, analogies, and simplified language when explaining technical concepts. Simplify technical explanations for non-technical stakeholders and promote direct user interactions. i already do this. I schedule meetings with the business analyst and technical team when there are challenges on the proposed solution or feature. I will strive to explain technical concepts in clear and concise terms. I will also actively listen to non-technical persons and ensure mutual understanding. simplifying some of the technical concepts would ease the bridging of the technical/non-technical gap. I will tailor technical explanations to non-technical stakeholders in meetings and presentations, ensuring that everyone is aligned. G1, and G3 are important to implement because it affects our ability to generate investments into our companys growth. I can make this happen by simply speaking to stakeholders in a group setting and adding informal discussions to the mix and fostering discussions amognst themselves. because I'm working with clients that don't have technical background so I should learn to dress better to them. This would decrease the chasm of knowledge and people will understand the root meaning of tech. Use simple analogies and visualizations to explain technical details to non-technical people. I will explain technical ideas in simple terms so everyone can understand. This helps the team work better together. Not everyone speaks “tech,” so I’d break things down into simple terms and use visuals like flowcharts or quick demos to make sure everyone’s on the same page. Just by meeting and explain situation points using non technical language, or explaining some so everyone understands , giving comparisons and pratical examples. bridging gaps via simplification of shareable concepts. Bridging the technical and non-technical gap is achieved by forming cross-disciplinary groups, favoring an exchange of both technical and non-technical knowledge. it's not easy to understand each others, but we need to create a commun language. It's often my role to translate the needs of the non technical public, to the devs, and same the other way. But it supposes to undestand the basis of the technical and of the domain of expertise of the public, so i try to train myself or the team. Tailored Explanations: When explaining technical concepts, I will adjust my language to match the audience's understanding, using analogies and scenarios to illustrate points clearly. Cross-Functional Collaboration: Encourage regular meetings between technical and non-technical teams to discuss projects, gather feedback, and ensure alignment. Documentation: Create clear, user-friendly documentation that explains technical processes in a way that non-technical stakeholders can easily grasp. Facilitate Cross-Functional Workshops: Organize workshops where technical and non-technical teams can collaborate, share knowledge, and build mutual understanding. Daily Practice: Simplify technical explanations using analogies and visual aids tailored to the audience's understanding. Managerial Level: Facilitate workshops where developers and non-technical stakeholders collaborate on shared goals, encouraging direct communication. Organizational Level: Advocate for mixed-team collaborations to bridge this gap consistently. bridging the gap is hard, but again, more open communication and also having more direct interactions with end users, through feedback forms, user feedback zoom calls, and helping to collaborate that way. Technical concepts are communicated in a way that simplifies complex details for non-technical stakeholders, ensuring clarity and alignment. Cross-departmental workshops further promote a shared understanding of both technical and business perspectives. I will work on simplifying complex technical concepts when interacting with non-technical stakeholders, ensuring they understand the impact of our work. I could use analogies and real-life scenarios to make technical discussions more relatable. When talking with customers without technical expertise, I sit down with them and try to explain in plain words, draw them in paper ( or powerpoint) what the software is going to look like step by step. Then we talk about their needs, if what we have designed is what they want and what changes they need to be happy with the product. Bridging this gap is essential for effective collaboration between developers, stakeholders, and end-users. Miscommunication often leads to misunderstandings about project priorities, delays, or even failed implementations. Specific Steps: Tailoring Explanations: When communicating with non-technical stakeholders, I’ll simplify technical jargon and use analogies to explain complex concepts. For example, I’ll explain API functionality using real-world scenarios, such as courier services handling deliveries. Collaborating Across Functions: I’ll work closely with cross-functional teams, ensuring that non-technical perspectives are included in discussions and decisions. Direct Developer-End User Interactions: If feasible, I’ll advocate for developers to interact directly with end-users to gain firsthand insights into their challenges and expectations. I will simplify technical concepts for non-technical stakeholders using relatable scenarios and clear language. Direct interactions between developers and end-users will further align technical work with business objectives. | D4: Communication: Simplifying Technical Communication: - strive to explain technical concepts in clear and concise terms. - Use visuals, analogies, flowcharts, quick demos, and simplified language when explaining technical concepts. - use analogies and real-life scenarios to make technical discussions more relatable. - giving comparisons and practical examples. - create a common language. - Create clear, user-friendly documentation that explains technical processes in a way that non-technical stakeholders can easily grasp. - translate the needs of the non technical public, to the devs, and same the other way. Tailoring Communication to Audience Needs: - Communicating technical aspects effectively ( tailor technical explanations to non-technical stakeholders in meetings and presentations) to non-technical stakeholders is crucial for aligning expectations and achieving project goals. - When talking with customers without technical expertise, I sit down with them and try to explain in plain words, draw them in paper ( or powerpoint) what the software is going to look like step by step. Then we talk about their needs, if what we have designed is what they want and what changes they need to be happy with the product. - I schedule meetings with the business analyst and technical team when there are challenges on the proposed solution or feature. - more open communication Collaboration/ Collaborative Problem-Solving: Fostering Collaborative Discussions: - Encourage regular meetings between technical and non-technical teams to discuss projects, gather feedback, and ensure alignment. - Organise workshops where technical and non-technical teams can collaborate, share knowledge, and build mutual understanding. - Facilitate workshops where developers and non-technical stakeholders collaborate on shared goals, encouraging direct communication. - actively listen to non-technical persons and ensure mutual understanding. - simply speaking to stakeholders in a group setting and adding informal discussions to the mix and fostering discussions amongst themselves. Cross-Disciplinary Collaboration: - forming cross-disciplinary groups, favouring an exchange of both technical and non-technical knowledge. - work closely with cross-functional teams, ensuring that non-technical perspectives are included in discussions and decisions. - Cross-departmental workshops further promote a shared understanding of both technical and business perspectives. - Advocate for mixed-team collaborations to bridge this gap consistently. - advocate for developers to interact directly with end-users to gain firsthand insights into their challenges and expectations. - having more direct interactions with end users, through feedback forms, user feedback zoom calls, and helping to collaborate that way. - it supposes to understand the basis of the technical and of the domain of expertise of the public, so i try to train myself or the team.
A5: G3 - Reducing friction among different stakeholder groups | B5: 16 | C5: When these groups are not aligned, friction can arise, leading to miscommunication, delays, and inefficiencies. Reducing friction among these groups requires clear communication, empathy, shared goals, and an understanding of each group's priorities. I will focus on understanding stakeholder priorities and addressing conflicts early through mediation. Regular alignment meetings and transparent communication of constraints and expectations will minimize misunderstandings. Using collaborative tools can also help streamline information sharing. I intend to apply this guideline by suggesting a critical but constructive approach among team members and proposing discussion sessions in the most conflictual cases. G1 & G3 - I am willing to make more transparent the communication of different stakeholders and create a dedicated space (software tools and physical meetings) to make the team work as one and not as different parties. When it comes to the friction reduction, I feel like having regular check-ins and feedback sharing would be crucial. encouraging unidirectional work in the company it is very important, all the company should work in the same direction with the same purpose so let's try to work all together without battles between different teams. We must also trust other shareholders, We can share luncheons and foster trust and understanding among different departments in this manner. having more open communication internally between not just engineering but also product. We also implement the golden rule of not blaming anyone. I will be more considerate of quality assurance testers and plan more time for them. | D5: Alignment and Shared Goals: - When these groups are not aligned, friction can arise - shared goals - encouraging unidirectional work in the company it is very important, all the company should work in the same direction with the same purpose so let's try to work all together without battles between different teams. - focus on understanding stakeholder priorities Communication and Information Sharing: - clear communication, - Regular alignment meetings and transparent communication of constraints and expectations will minimize misunderstandings. - having regular check-ins and feedback sharing - Using collaborative tools can also help streamline information sharing. Conflict Resolution: - addressing conflicts early through mediation. - suggesting a critical but constructive approach among team members and - proposing discussion sessions in the most conflictual cases. Building Collaboration and Trust: - create a dedicated space (software tools and physical meetings) to make the team work as one and not as different parties. - trust other shareholders - share luncheons and foster trust and understanding among different departments Respectful Behaviour: - implement the golden rule of not blaming anyone. - I will be more considerate of quality assurance testers and plan more time for them.
A6: ​​G4 - Encouraging bi-directional communication | B6: 36 | C6: I will create a safe environment for team members to share feedback, using tools like anonymous surveys and regular feedback loops. I will actively listen to others, and provide constructive feedback. I will also be mindful to be clear, concise, and respectful. I plan to foster clear, two-way communication in all meetings and daily interactions, ensuring all voices are heard. I’ll also use non-verbal cues and active listening techniques to improve understanding. I will adopt open communication practices during meetings, actively listen to team members' concerns, and provide constructive feedback. I will also ensure that communication flows effectively between leadership and team members. Encouraging bi-directional communication would involve establishing clear feedback channels and stand-ups to ensure mutual understanding. Actively listen during meetings and discussions. Ask questions to clarify information and express your point of view clearly and concisely. promote open communication by actively listening and encouraging feedback. I already do this by speaking openly and listening to others. I will keep creating space for discussion and sharing ideas. Communication goes both ways, so I’d create spaces where people feel comfortable sharing their thoughts—whether that’s in meetings, chats, or casual convos—so we can all collaborate better. fostering open communication. Encouraging bi-directional communication is also a result forming cross-disciplinary groups, creating strong relationships between all members. Cultivate an open environment where communication flows both ways, ensuring that feedback and ideas are shared freely between all levels of the team. Actively listen to feedback from peers, subordinates, and stakeholders, and act on it where feasible. Specific Steps: Implement weekly stand-up meetings where everyone can share updates, concerns, and ideas. Use tools like Slack or Microsoft Teams to keep communication channels open and accessible. Provide constructive feedback while welcoming it in return, creating a culture of mutual respect. I will encourage open communication both ways with my team and managers. I’ll actively listen to feedback, ensuring we all have a shared understanding of goals and progress. Regular check-ins and feedback loops will help promote this. Listen to everyone’s ideas, ask for feedback, and have regular one-on-one chats to make sure everyone feels heard and understood. Promoting two-way communication ensures all voices are heard and valued, fostering mutual understanding and trust. Regular feedback sessions and active listening will help maintain this open exchange. | D6: Effective Communication: - be mindful to be clear, concise, and respectful when communicating. - foster clear, two-way communication in all meetings and daily interactions, ensuring that feedback and ideas are shared freely between all levels of the team. - ensure that communication flows effectively between leadership and team members. - Use tools like Slack or Microsoft Teams to keep communication channels open and accessible. Feedback and Continuous Improvement: - create a safe environment for team members to discuss, share feedback and ideas, using tools like anonymous surveys and regular feedback loops. - Actively listen to feedback from peers, subordinates, and stakeholders, and act on it where feasible. - establishing clear feedback channels and stand-ups to ensure mutual understanding. - Provide constructive feedback while welcoming it in return, creating a culture of mutual respect. Understanding and Relationship Building: - use non-verbal cues to improve understanding. - Ask questions to clarify information and express your point of view clearly and concisely. - forming cross-disciplinary groups, creating strong relationships between all members.
A7: G5 - Ensuring transparency about business goals | B7: 29 | C7: I plan to incorporate this by clearly communicating objectives in all meetings and documentation. This includes aligning team tasks with broader goals to ensure everyone understands their role in the bigger picture. Regular updates and feedback sessions will reinforce clarity and shared purpose. Transparency helps align individual efforts with organizational objectives, fostering a shared sense of purpose. Explain how team tasks contribute to larger organizational goals during project meetings and keep team members informed about shifts in priorities or business strategies. Regularly clarify how tasks align with business objectives during stand-ups or sprint planning. Clear communication with my team would be the of the utmost importance to start incorporating them in our work. providing background information on managerial / company level decisions, explaining why such decisions were made, answering questions about the reasons. I will work with my managers to ensure that business goals are communicated clearly during team meetings and that team members understand how their work contributes to the larger organizational objectives. Set clear expectations around project goals, timelines, and deliverables. Ensure that stakeholders have a shared understanding of requirements and potential challenges. first of all those goals must be set. Then just explain to the working team, wite it down on a board as , Keep in mind. Use it as a development step. prioritize transparency. when we have clear and honest goal, we are more determined to reach them. I always try to be as transparent as possible with my team, but often the difficulty is with higher hierarchy, who want to retain some informations, and doesnt always trust the employes with details. So i essentially try to convince my n+1 to be more open, and show them example of how beneficial it is. Daily Practice: Seek clarity about how my work impacts business objectives and communicate this understanding to peers. Managerial Level: Advocate for regular updates on business goals during team meetings and ensure alignment with tasks. Organizational Level: Push for transparency to be formalized through dashboards or open forums for all employees. I will ensure clear communication of business goals within my team and help align our technical work with organizational objectives. I will make an effort to understand the broader business context and share this information with colleagues to foster empathy and clarity. Steps: Regularly communicate business goals to the team, align technical efforts with these goals, and provide feedback loops that ensure everyone understands how their work contributes to the larger mission. | D7: Clear Communication of Objectives: - clearly communicating objectives in all meetings and documentation. - Set clear expectations around project goals, timelines, and deliverables. - Ensure that stakeholders have a shared understanding of requirements and potential challenges. Alignment with Broader Business Goals: - aligning team tasks with broader goals to ensure everyone understands their role in the bigger picture. - Explain how team tasks contribute to larger organisational goals during project meetings - Regularly clarify how tasks align with business objectives during stand-ups or sprint planning. Continuous Updates and Feedback: - Regular updates and feedback sessions will reinforce clarity and shared purpose. - keep team members informed about shifts in priorities or business strategies. - Seek clarity about how my work impacts business objectives and communicate this understanding to peers. Transparency and Decision-Making: - providing background information on managerial / company level decisions, explaining why such decisions were made, answering questions about the reasons. - Push for transparency to be formalised through dashboards or open forums for all employees.
A8: G6 - Use an empathetic approach to improve requirements engineering (RE) processes | B8: 18 | C8: my intention is to apply a more communicative and impersonal approach, in order to create a bond and a sharing strategy that has an empathetic fabric and can allow the parties to express and share specific emotions and information, without limits. G6, G7 and G9 - first of all I would lead by example showing how you can work as an empathetic peer and secondly point out behaviours of feedbacks and communication that could have been given in a more collaborative manner (one to one meetings and feedback). improving requirements engineering with empathy (G6) by focusing on open communication, active listening, and understanding stakeholder needs. clarify requirements with stakeholders to align expectations. aligning on user needs. I will be more considerate and patient when requirements change. Clear communication is key to successful requirements gathering. I will prioritize active listening when collecting requirements, ask clarifying questions, and ensure there’s mutual understanding of the goals before proceeding with development. Ask lots of questions to avoid confusion, explain tech stuff in simple terms, and share stories about how the product will help users. Unclear requirements are one of the leading causes of project delays and rework. Empathy in requirements gathering ensures that the developers truly understand user needs and business objectives. Specific Steps: Active Listening During Requirements Gathering: I will ask follow-up questions to understand the "why" behind requirements, ensuring we align with end-user needs. Collaborative Documentation: I’ll use tools like user stories or journey mapping to visualize requirements in a way that resonates with both technical and non-technical stakeholders. Iterative Clarification: I’ll keep an open line of communication to clarify evolving requirements throughout the project lifecycle. I will ensure clear communication and active stakeholder engagement to capture and address their needs effectively. | D8: Communication and Stakeholder Engagement: - Use clear and neutral communication to build trust and create an open environment where people can freely share their emotions and information. - focusing on open communication - ensure active stakeholder engagement to capture and address their needs effectively. - explain tech stuff in simple terms, and share stories about how the product will help users. - Collaborative Documentation: use tools like user stories or journey mapping to visualise requirements in a way that resonates with both technical and non-technical stakeholders. Active Listening and Clarification: - prioritise active listening when collecting requirements - ask follow-up questions to understand the "why" behind requirements, ensuring we align with end-user needs. - keep an open line of communication to clarify evolving requirements throughout the project lifecycle. Requirement Alignment and Management: - clarify requirements with stakeholders to align expectations. - be more considerate and patient when requirements change. - ensure there’s mutual understanding of the goals before proceeding with development. - ensuring requirements align with end-user needs. Extra info: - focusing on open communication - apply a more communicative and impersonal approach, in order to create a bond and a sharing strategy that has an empathetic fabric and can allow the parties to express and share specific emotions and information, without limits. : Simplified this as "Use clear and neutral communication to build trust and create an open environment where people can freely share their emotions and information."
A9: G7 - Collaborative problem solving | B9: 44 | C9: We regularly have practical problem solving sessions with just about every client problem we face - meaning we are always working as a team to develop solutions with hands-on approaches. I will facilitate collaborative sessions between technical and non-technical stakeholders to improve solution quality and foster empathy. G6, G7 and G9 - first of all I would lead by example showing how you can work as an empathetic peer and secondly point out behaviours of feedbacks and communication that could have been given in a more collaborative manner (one to one meetings and feedback). In regards to collaboration, maybe we can try to encourage the gathering of different perspectives, in order to come up with more comprehensive solutions. I will work cross-functionally to solve issues, ensuring that both technical and business perspectives are considered. making sure that the team members have the opportunity to work together on solving different tasks, that they can bring up their ideas, solutions. I think it's crucial to have a safe and collaborative workspace, where everyone can participate without feeling put down or ignored. I would talk to my boss and explain the importance of implementing those. I would also collaborate as much as I can in order to achieve the results they would expect from me. Collaborative problem-solving would be implemented by involving both technical and non-technical perspectives in team discussions to find diverse solutions. We also need to involve technicall as well as non technical people on the team. Everyone must feel they are part of the team even if their technical skills are less than others. Encourage collaboration across different teams (engineering, QA, design, operations, etc.) to bring diverse perspectives to problem-solving. I believe solutions are better when we work together. I will involve the team to find ideas and solve problems as a group. Two heads (or more) are better than one. I’d encourage brainstorming, involve the team when troubleshooting, and use tools like shared boards or pair coding to get things done together. Brainstorming and exchanging ideas once the problems are detected, sometimes the solutions come from unexpected places, someone not techinical can have the solution and not know how to make it work, and the tecnician can know how to make it but not have the insight. involving diverse stakeholders to create inclusive, user-centered solutions. I plan to use what the guideline to do better, i expect to schedule weekly meeting and use tools to enhance collaborative problem solving. engage in active collaboration in the workplace, in a manner that prioritizes empathy in our software engineering. Collaborative problem solving is fostered once more by ensuring strong bonds are built by cross-disciplinary teams who have been empowered to find innovative solutions to real world problems. The team and the results above everything else and collaboration is the best way to work. Eveyone can help and participate on several tasks and help with one another's workload. Every time our team has a new project we sit down together and try to understand everything about it, distribute the work and set expectations. After that we will have a weekly meeting and reevaluate all points, depending on the problems that arise. I will facilitate discussions to incorporate diverse perspectives, ensuring better alignment and higher-quality solutions. | D9: Collaboration and Teamwork: - Facilitate Regular Problem-Solving Sessions: Regularly host practical, hands-on problem-solving sessions for every client issue, ensuring collaboration and teamwork in finding effective solutions. - Foster Cross-Functional Collaboration: Work across teams to address issues, ensuring both technical and business perspectives are incorporated into solutions. - Encourage Team Input and Idea Sharing: Provide opportunities for team members to actively collaborate on tasks, share their ideas, and contribute solutions. - Promote Inter-Team Collaboration: Encourage collaboration across diverse teams (engineering, QA, design, operations, etc.) to gather a broad range of perspectives in problem-solving. - Leverage Collaborative Tools: Utilize tools like shared boards, pair coding, and group brainstorming to facilitate collaborative work and efficient troubleshooting. - Ensure Alignment in Project Kickoffs: At the start of each new project, ensure the team understands the scope, divides responsibilities, and sets clear expectations. - Conduct Regular Reevaluation Meetings: After project kickoffs, hold weekly meetings to review progress, reassess priorities, and adjust based on emerging issues. Inclusive and Safe Work Environment: - Create an Open, Inclusive Workspace: Foster an environment where all team members feel safe, respected, and encouraged to contribute without fear of being disregarded. - Facilitate Empathy-Building Sessions: Lead collaborative sessions between technical and non-technical stakeholders to improve solution quality and strengthen empathy across teams. Communication and Alignment: - Encourage Diverse Perspectives: Actively promote the collection of different perspectives to develop comprehensive and well-rounded solutions. - Facilitate Open Idea Exchange: Encourage team members to exchange ideas and collaborate on problem-solving as soon as challenges are identified. - Schedule Consistent Check-Ins: Set regular meetings to foster ongoing communication, align teams, and ensure everyone is aligned in problem-solving efforts. - Advocate for Collaborative Practices: Engage leadership to emphasise the importance of adopting collaborative problem-solving approaches throughout the organisation. Extra Info: - I would talk to my boss and explain the importance of implementing those: Rephrased as "Inform leadership team on the importance of adopting gollaborative problem solving" - regularly have practical problem solving sessions with just about every client problem we face - meaning we are always working as a team to develop solutions with hands-on approaches: Rephrased as"Regularly conduct practical problem-solving sessions with every client problem."
A10: G8 - Empathy during agile ceremonies | B10: 14 | C10: We often have set sessions in agile retrospectives that allow the team to (if they feel comfortable) express grievances within the project and look for ways to move forward with them. i will respect the team members when they express any dissatisfaction about anything that happened during the sprint including any stories i might have written. I will also respect the decision on how much work they can take in each sprint. During agile ceremonies like sprint planning, daily stand-ups, I will actively listen to my team members and create a positive and supportive environment where everyone feels valued and heard. I will ensure that all team members have the opportunity to voice their opinions during sprint planning and retrospectives, promoting empathy and collaboration. G8, G9, and g17 are also very important to implement because the company culture should be an empathetic one. I can make this happen successfully by holding meetings specifically to address empathy and respect amongst employees. Having one on one talks with employees for their progress reports can be slightly rehearsed to focus on each employees comfortability in the office. Also having team building exercises can do wonders regarding employees ability to empathize, and learn about eachother which will cause less grudges and with less intensity. I will make sure everyone feels heard and supported during meetings. Showing understanding helps the team stay positive and productive. Sprint Planning: During sprint planning, I will ensure that tasks are realistically allocated, considering each team member's workload and strengths. Daily Stand-Ups: Use daily stand-ups to address challenges, offer support, and celebrate achievements, fostering a positive and collaborative atmosphere. Retrospectives: In retrospectives, I will focus on constructive feedback and empathetic problem-solving to improve processes and team dynamics. Implement Regular Check-Ins: Schedule regular one-on-one check-ins with team members to discuss their workload, address any issues, and offer support. I will be more supportive during standup. Agile ceremonies become more inclusive when active listening and mutual respect are prioritised, making team members feel heard. This encourages open dialogue, fostering a collaborative atmosphere where challenges and successes can be openly discussed. | D10: Sprint Planning: - respect the decision on how much work they can take in each sprint. - ensure that tasks are realistically allocated, considering each team member's workload and strengths. Daily Standup: - Use daily stand-ups to address challenges, offer support, and celebrate achievements, fostering a positive and collaborative atmosphere. - Schedule regular one-on-one check-ins with team members to discuss their workload, address any issues, and offer support. - Having one on one talks with employees for their progress reports and focus on each employees comfortability in the office. Retrospectives: - have set sessions in agile retrospectives that allow the team to (if they feel comfortable) express grievances within the project and look for ways to move forward with them. - respect the team members when they express any dissatisfaction about anything that happened during the sprint including any stories i might have written. - focus on constructive feedback and empathetic problem-solving to improve processes and team dynamics. Creating a positive environment: - actively listen to team members and create a positive and supportive environment where everyone feels valued and heard. - ensure that all team members have the opportunity to voice their opinions promoting empathy and collaboration. - holding meetings specifically to address empathy and respect amongst employees. - having team building exercises to improve employees' ability to empathize, and learn about eachother which will cause less grudges and with less intensity. - Showing understanding
